Workbook

Sheet SKU_Base
A1: Статус | B1: Код товару | C1: Назва товару | D1: Категорія | E1: Од. (ориг) | F1: Інвойсна ціна (USD) | G1: Код митниці | H1: Імпортний коеф. | I1: Собівар- тість (грн) | J1: Маржа кл. D1 % | K1: Маржа факт. чиста D1 | L1: Маржа факт. чиста D2 | M1: Маржа факт. чиста D3 | N1: Маржа факт. чиста D4 Buy | O1: Маржа факт. чиста D4 Drop | P1: Маржа факт. чиста D5 | Q1: Маржа факт. чиста D6 | R1: RRP розрах. (грн, D1) | S1: RRP базова (корегування) | T1: RRP ефективна | U1: Роль SKU | V1: Ринок мін. (грн) | W1: Ринок макс. (грн) | X1: Відповідність ринку | Y1: Примітки | AU1: Дата оновлення | AV1: Наценка D4 НІ
B2: B7821 | C2: RAVER BAT. LITHIUM 1.5V,AA | D2: Батарейки | E2: 2 | F2: 1.589 | G2: 8506501000 | H2: 1.35 | I2: =IFERROR(F2*Settings!$B$2*H2*IF(AND(ISNUMBER(E2),E2>1),E2,1),"") | J2: =Settings!$B$66 | K2: =IFERROR(IF(T2="","",(T2*(1-AN2)*(1-Settings!$B$17)-I2)/(T2*(1-AN2)*(1-Settings!$B$17))),"") | L2: =IFERROR(IF(T2="","",(T2*(1-AO2)*(1-Settings!$C$17)-I2)/(T2*(1-AO2)*(1-Settings!$C$17))),"") | M2: =IFERROR(IF(T2="","",(T2*(1-AP2)*(1-Settings!$D$17)-I2)/(T2*(1-AP2)*(1-Settings!$D$17))),"") | N2: =IFERROR(IF(T2="","",(T2*(1-AQ2)*(1-Settings!$F$17)-I2)/(T2*(1-AQ2)*(1-Settings!$F$17))),"") | O2: =IFERROR(IF(T2="","",(T2*(1-AR2)*(1-Settings!$G$17)-I2)/(T2*(1-AR2)*(1-Settings!$G$17))),"") | P2: =IFERROR(IF(T2="","",(T2*(1-AS2)*(1-Settings!$H$17)-I2)/(T2*(1-AS2)*(1-Settings!$H$17))),"") | Q2: =IFERROR(IF(T2="","",(T2*(1-AT2)*(1-Settings!$I$68)*(1-Settings!$I$17)-I2)/(T2*(1-AT2)*(1-Settings!$I$68)*(1-Settings!$I$17))),"") | R2: =IFERROR(IF(OR(I2="",Z2>=1,Settings!$B$17>=1,AN2>=1),"",IF(MOD(ROUND(I2/(1-Z2)/(1-Settings!$B$17)/(1-AN2),0),10)=0,ROUND(I2/(1-Z2)/(1-Settings!$B$17)/(1-AN2),0)-1,IF(MOD(ROUND(I2/(1-Z2)/(1-Settings!$B$17)/(1-AN2),0),10)<=5,FLOOR(ROUND(I2/(1-Z2)/(1-Settings!$B$17)/(1-AN2),0),10)+6,FLOOR(ROUND(I2/(1-Z2)/(1-Settings!$B$17)/(1-AN2),0),10)+9))),"") | S2: 360 | T2: =IF(S2<>"", IF(MOD(S2,10)=0,S2-1,IF(MOD(S2,10)<=5,FLOOR(S2,10)+6,FLOOR(S2,10)+9)), R2) | U2: Маржинальний | X2: =IFERROR(IF(OR(V2="",W2="",T2=""),"", IF(T2>W2,"Дорогий",IF(T2<V2,"Дешевий","У ринку"))),"") | Z2: =CHOOSE(MATCH(IF($U2="","Основний",$U2),{"Трафіковий","Основний","Маржинальний","Сезонний","Стратегічний"},0),0.16,0.19,0.24,0.23,0.28) | AA2: =CHOOSE(MATCH(IF($U2="","Основний",$U2),{"Трафіковий","Основний","Маржинальний","Сезонний","Стратегічний"},0),0.18,0.21,0.26,0.25,0.3) | AB2: =CHOOSE(MATCH(IF($U2="","Основний",$U2),{"Трафіковий","Основний","Маржинальний","Сезонний","Стратегічний"},0),0.19,0.22,0.28,0.26,0.32) | AC2: =CHOOSE(MATCH(IF($U2="","Основний",$U2),{"Трафіковий","Основний","Маржинальний","Сезонний","Стратегічний"},0),0.17,0.2,0.25,0.24,0.28) | AD2: =CHOOSE(MATCH(IF($U2="","Основний",$U2),{"Трафіковий","Основний","Маржинальний","Сезонний","Стратегічний"},0),0.18,0.21,0.26,0.25,0.3) | AE2: =CHOOSE(MATCH(IF($U2="","Основний",$U2),{"Трафіковий","Основний","Маржинальний","Сезонний","Стратегічний"},0),0.18,0.2,0.28,0.27,0.32) | AF2: =CHOOSE(MATCH(IF($U2="","Основний",$U2),{"Трафіковий","Основний","Маржинальний","Сезонний","Стратегічний"},0),0.15,0.175,0.22,0.21,0.25) | AG2: =CHOOSE(MATCH(IF($U2="","Основний",$U2),{"Трафіковий","Основний","Маржинальний","Сезонний","Стратегічний"},0),0.13,0.16,0.21,0.2,0.25) | AH2: =CHOOSE(MATCH(IF($U2="","Основний",$U2),{"Трафіковий","Основний","Маржинальний","Сезонний","Стратегічний"},0),0.15,0.18,0.23,0.22,0.27) | AI2: =CHOOSE(MATCH(IF($U2="","Основний",$U2),{"Трафіковий","Основний","Маржинальний","Сезонний","Стратегічний"},0),0.16,0.19,0.25,0.23,0.29) | AJ2: =CHOOSE(MATCH(IF($U2="","Основний",$U2),{"Трафіковий","Основний","Маржинальний","Сезонний","Стратегічний"},0),0.14,0.17,0.22,0.21,0.25) | AK2: =CHOOSE(MATCH(IF($U2="","Основний",$U2),{"Трафіковий","Основний","Маржинальний","Сезонний","Стратегічний"},0),0.15,0.18,0.23,0.22,0.27) | AL2: =CHOOSE(MATCH(IF($U2="","Основний",$U2),{"Трафіковий","Основний","Маржинальний","Сезонний","Стратегічний"},0),0.15,0.17,0.25,0.24,0.29) | AM2: =CHOOSE(MATCH(IF($U2="","Основний",$U2),{"Трафіковий","Основний","Маржинальний","Сезонний","Стратегічний"},0),0.12,0.145,0.19,0.18,0.22) | AN2: =CHOOSE(MATCH(IF($U2="","Основний",$U2),{"Трафіковий","Основний","Маржинальний","Сезонний","Стратегічний"},0),Settings!$B$78,Settings!$B$80,Settings!$B$82,Settings!$B$84,Settings!$B$86) | AO2: =CHOOSE(MATCH(IF($U2="","Основний",$U2),{"Трафіковий","Основний","Маржинальний","Сезонний","Стратегічний"},0),Settings!$C$78,Settings!$C$80,Settings!$C$82,Settings!$C$84,Settings!$C$86) | AP2: =CHOOSE(MATCH(IF($U2="","Основний",$U2),{"Трафіковий","Основний","Маржинальний","Сезонний","Стратегічний"},0),Settings!$D$78,Settings!$D$80,Settings!$D$82,Settings!$D$84,Settings!$D$86) | AQ2: =CHOOSE(MATCH(IF($U2="","Основний",$U2),{"Трафіковий","Основний","Маржинальний","Сезонний","Стратегічний"},0),Settings!$F$78,Settings!$F$80,Settings!$F$82,Settings!$F$84,Settings!$F$86) | AR2: =CHOOSE(MATCH(IF($U2="","Основний",$U2),{"Трафіковий","Основний","Маржинальний","Сезонний","Стратегічний"},0),Settings!$G$78,Settings!$G$80,Settings!$G$82,Settings!$G$84,Settings!$G$86) | AS2: =CHOOSE(MATCH(IF($U2="","Основний",$U2),{"Трафіковий","Основний","Маржинальний","Сезонний","Стратегічний"},0),Settings!$H$78,Settings!$H$80,Settings!$H$82,Settings!$H$84,Settings!$H$86) | AT2: =CHOOSE(MATCH(IF($U2="","Основний",$U2),{"Трафіковий","Основний","Маржинальний","Сезонний","Стратегічний"},0),Settings!$I$78,Settings!$I$80,Settings!$I$82,Settings!$I$84,Settings!$I$86) | AV2: 1.4
B3: B7811 | C3: RAVER BAT. LITHIUM 1.5V,AAA | D3: Батарейки | E3: 2 | F3: 1.241 | G3: 8506501000 | H3: 1.35 | I3: =IFERROR(F3*Settings!$B$2*H3*IF(AND(ISNUMBER(E3),E3>1),E3,1),"") | J3: =Settings!$B$66 | K3: =IFERROR(IF(T3="","",(T3*(1-AN3)*(1-Settings!$B$17)-I3)/(T3*(1-AN3)*(1-Settings!$B$17))),"") | L3: =IFERROR(IF(T3="","",(T3*(1-AO3)*(1-Settings!$C$17)-I3)/(T3*(1-AO3)*(1-Settings!$C$17))),"") | M3: =IFERROR(IF(T3="","",(T3*(1-AP3)*(1-Settings!$D$17)-I3)/(T3*(1-AP3)*(1-Settings!$D$17))),"") | N3: =IFERROR(IF(T3="","",(T3*(1-AQ3)*(1-Settings!$F$17)-I3)/(T3*(1-AQ3)*(1-Settings!$F$17))),"") | O3: =IFERROR(IF(T3="","",(T3*(1-AR3)*(1-Settings!$G$17)-I3)/(T3*(1-AR3)*(1-Settings!$G$17))),"") | P3: =IFERROR(IF(T3="","",(T3*(1-AS3)*(1-Settings!$H$17)-I3)/(T3*(1-AS3)*(1-Settings!$H$17))),"") | Q3: =IFERROR(IF(T3="","",(T3*(1-AT3)*(1-Settings!$I$68)*(1-Settings!$I$17)-I3)/(T3*(1-AT3)*(1-Settings!$I$68)*(1-Settings!$I$17))),"") | R3: =IFERROR(IF(OR(I3="",Z3>=1,Settings!$B$17>=1,AN3>=1),"",IF(MOD(ROUND(I3/(1-Z3)/(1-Settings!$B$17)/(1-AN3),0),10)=0,ROUND(I3/(1-Z3)/(1-Settings!$B$17)/(1-AN3),0)-1,IF(MOD(ROUND(I3/(1-Z3)/(1-Settings!$B$17)/(1-AN3),0),10)<=5,FLOOR(ROUND(I3/(1-Z3)/(1-Settings!$B$17)/(1-AN3),0),10)+6,FLOOR(ROUND(I3/(1-Z3)/(1-Settings!$B$17)/(1-AN3),0),10)+9))),"") | S3: 289 | T3: =IF(S3<>"", IF(MOD(S3,10)=0,S3-1,IF(MOD(S3,10)<=5,FLOOR(S3,10)+6,FLOOR(S3,10)+9)), R3) | U3: Маржинальний | X3: =IFERROR(IF(OR(V3="",W3="",T3=""),"", IF(T3>W3,"Дорогий",IF(T3<V3,"Дешевий","У ринку"))),"") | Z3: =CHOOSE(MATCH(IF($U3="","Основний",$U3),{"Трафіковий","Основний","Маржинальний","Сезонний","Стратегічний"},0),0.16,0.19,0.24,0.23,0.28) | AA3: =CHOOSE(MATCH(IF($U3="","Основний",$U3),{"Трафіковий","Основний","Маржинальний","Сезонний","Стратегічний"},0),0.18,0.21,0.26,0.25,0.3) | AB3: =CHOOSE(MATCH(IF($U3="","Основний",$U3),{"Трафіковий","Основний","Маржинальний","Сезонний","Стратегічний"},0),0.19,0.22,0.28,0.26,0.32) | AC3: =CHOOSE(MATCH(IF($U3="","Основний",$U3),{"Трафіковий","Основний","Маржинальний","Сезонний","Стратегічний"},0),0.17,0.2,0.25,0.24,0.28) | AD3: =CHOOSE(MATCH(IF($U3="","Основний",$U3),{"Трафіковий","Основний","Маржинальний","Сезонний","Стратегічний"},0),0.18,0.21,0.26,0.25,0.3) | AE3: =CHOOSE(MATCH(IF($U3="","Основний",$U3),{"Трафіковий","Основний","Маржинальний","Сезонний","Стратегічний"},0),0.18,0.2,0.28,0.27,0.32) | AF3: =CHOOSE(MATCH(IF($U3="","Основний",$U3),{"Трафіковий","Основний","Маржинальний","Сезонний","Стратегічний"},0),0.15,0.175,0.22,0.21,0.25) | AG3: =CHOOSE(MATCH(IF($U3="","Основний",$U3),{"Трафіковий","Основний","Маржинальний","Сезонний","Стратегічний"},0),0.13,0.16,0.21,0.2,0.25) | AH3: =CHOOSE(MATCH(IF($U3="","Основний",$U3),{"Трафіковий","Основний","Маржинальний","Сезонний","Стратегічний"},0),0.15,0.18,0.23,0.22,0.27) | AI3: =CHOOSE(MATCH(IF($U3="","Основний",$U3),{"Трафіковий","Основний","Маржинальний","Сезонний","Стратегічний"},0),0.16,0.19,0.25,0.23,0.29) | AJ3: =CHOOSE(MATCH(IF($U3="","Основний",$U3),{"Трафіковий","Основний","Маржинальний","Сезонний","Стратегічний"},0),0.14,0.17,0.22,0.21,0.25) | AK3: =CHOOSE(MATCH(IF($U3="","Основний",$U3),{"Трафіковий","Основний","Маржинальний","Сезонний","Стратегічний"},0),0.15,0.18,0.23,0.22,0.27) | AL3: =CHOOSE(MATCH(IF($U3="","Основний",$U3),{"Трафіковий","Основний","Маржинальний","Сезонний","Стратегічний"},0),0.15,0.17,0.25,0.24,0.29) | AM3: =CHOOSE(MATCH(IF($U3="","Основний",$U3),{"Трафіковий","Основний","Маржинальний","Сезонний","Стратегічний"},0),0.12,0.145,0.19,0.18,0.22) | AN3: =CHOOSE(MATCH(IF($U3="","Основний",$U3),{"Трафіковий","Основний","Маржинальний","Сезонний","Стратегічний"},0),Settings!$B$78,Settings!$B$80,Settings!$B$82,Settings!$B$84,Settings!$B$86) | AO3: =CHOOSE(MATCH(IF($U3="","Основний",$U3),{"Трафіковий","Основний","Маржинальний","Сезонний","Стратегічний"},0),Settings!$C$78,Settings!$C$80,Settings!$C$82,Settings!$C$84,Settings!$C$86) | AP3: =CHOOSE(MATCH(IF($U3="","Основний",$U3),{"Трафіковий","Основний","Маржинальний","Сезонний","Стратегічний"},0),Settings!$D$78,Settings!$D$80,Settings!$D$82,Settings!$D$84,Settings!$D$86) | AQ3: =CHOOSE(MATCH(IF($U3="","Основний",$U3),{"Трафіковий","Основний","Маржинальний","Сезонний","Стратегічний"},0),Settings!$F$78,Settings!$F$80,Settings!$F$82,Settings!$F$84,Settings!$F$86) | AR3: =CHOOSE(MATCH(IF($U3="","Основний",$U3),{"Трафіковий","Основний","Маржинальний","Сезонний","Стратегічний"},0),Settings!$G$78,Settings!$G$80,Settings!$G$82,Settings!$G$84,Settings!$G$86) | AS3: =CHOOSE(MATCH(IF($U3="","Основний",$U3),{"Трафіковий","Основний","Маржинальний","Сезонний","Стратегічний"},0),Settings!$H$78,Settings!$H$80,Settings!$H$82,Settings!$H$84,Settings!$H$86) | AT3: =CHOOSE(MATCH(IF($U3="","Основний",$U3),{"Трафіковий","Основний","Маржинальний","Сезонний","Стратегічний"},0),Settings!$I$78,Settings!$I$80,Settings!$I$82,Settings!$I$84,Settings!$I$86) | AV3: 1.4
B4: B7911 | C4: RAVER BAT.ALKALINE LR03 4BL | D4: Батарейки | E4: 4 | F4: 0.134 | G4: 8506101100 | H4: 1.35 | I4: =IFERROR(F4*Settings!$B$2*H4*IF(AND(ISNUMBER(E4),E4>1),E4,1),"") | J4: =Settings!$B$66 | K4: =IFERROR(IF(T4="","",(T4*(1-AN4)*(1-Settings!$B$17)-I4)/(T4*(1-AN4)*(1-Settings!$B$17))),"") | L4: =IFERROR(IF(T4="","",(T4*(1-AO4)*(1-Settings!$C$17)-I4)/(T4*(1-AO4)*(1-Settings!$C$17))),"") | M4: =IFERROR(IF(T4="","",(T4*(1-AP4)*(1-Settings!$D$17)-I4)/(T4*(1-AP4)*(1-Settings!$D$17))),"") | N4: =IFERROR(IF(T4="","",(T4*(1-AQ4)*(1-Settings!$F$17)-I4)/(T4*(1-AQ4)*(1-Settings!$F$17))),"") | O4: =IFERROR(IF(T4="","",(T4*(1-AR4)*(1-Settings!$G$17)-I4)/(T4*(1-AR4)*(1-Settings!$G$17))),"") | P4: =IFERROR(IF(T4="","",(T4*(1-AS4)*(1-Settings!$H$17)-I4)/(T4*(1-AS4)*(1-Settings!$H$17))),"") | Q4: =IFERROR(IF(T4="","",(T4*(1-AT4)*(1-Settings!$I$68)*(1-Settings!$I$17)-I4)/(T4*(1-AT4)*(1-Settings!$I$68)*(1-Settings!$I$17))),"") | R4: =IFERROR(IF(OR(I4="",Z4>=1,Settings!$B$17>=1,AN4>=1),"",IF(MOD(ROUND(I4/(1-Z4)/(1-Settings!$B$17)/(1-AN4),0),10)=0,ROUND(I4/(1-Z4)/(1-Settings!$B$17)/(1-AN4),0)-1,IF(MOD(ROUND(I4/(1-Z4)/(1-Settings!$B$17)/(1-AN4),0),10)<=5,FLOOR(ROUND(I4/(1-Z4)/(1-Settings!$B$17)/(1-AN4),0),10)+6,FLOOR(ROUND(I4/(1-Z4)/(1-Settings!$B$17)/(1-AN4),0),10)+9))),"") | S4: 89 | T4: =IF(S4<>"", IF(MOD(S4,10)=0,S4-1,IF(MOD(S4,10)<=5,FLOOR(S4,10)+6,FLOOR(S4,10)+9)), R4) | U4: Трафіковий | X4: =IFERROR(IF(OR(V4="",W4="",T4=""),"", IF(T4>W4,"Дорогий",IF(T4<V4,"Дешевий","У ринку"))),"") | Z4: =CHOOSE(MATCH(IF($U4="","Основний",$U4),{"Трафіковий","Основний","Маржинальний","Сезонний","Стратегічний"},0),0.16,0.19,0.24,0.23,0.28) | AA4: =CHOOSE(MATCH(IF($U4="","Основний",$U4),{"Трафіковий","Основний","Маржинальний","Сезонний","Стратегічний"},0),0.18,0.21,0.26,0.25,0.3) | AB4: =CHOOSE(MATCH(IF($U4="","Основний",$U4),{"Трафіковий","Основний","Маржинальний","Сезонний","Стратегічний"},0),0.19,0.22,0.28,0.26,0.32) | AC4: =CHOOSE(MATCH(IF($U4="","Основний",$U4),{"Трафіковий","Основний","Маржинальний","Сезонний","Стратегічний"},0),0.17,0.2,0.25,0.24,0.28) | AD4: =CHOOSE(MATCH(IF($U4="","Основний",$U4),{"Трафіковий","Основний","Маржинальний","Сезонний","Стратегічний"},0),0.18,0.21,0.26,0.25,0.3) | AE4: =CHOOSE(MATCH(IF($U4="","Основний",$U4),{"Трафіковий","Основний","Маржинальний","Сезонний","Стратегічний"},0),0.18,0.2,0.28,0.27,0.32) | AF4: =CHOOSE(MATCH(IF($U4="","Основний",$U4),{"Трафіковий","Основний","Маржинальний","Сезонний","Стратегічний"},0),0.15,0.175,0.22,0.21,0.25) | AG4: =CHOOSE(MATCH(IF($U4="","Основний",$U4),{"Трафіковий","Основний","Маржинальний","Сезонний","Стратегічний"},0),0.13,0.16,0.21,0.2,0.25) | AH4: =CHOOSE(MATCH(IF($U4="","Основний",$U4),{"Трафіковий","Основний","Маржинальний","Сезонний","Стратегічний"},0),0.15,0.18,0.23,0.22,0.27) | AI4: =CHOOSE(MATCH(IF($U4="","Основний",$U4),{"Трафіковий","Основний","Маржинальний","Сезонний","Стратегічний"},0),0.16,0.19,0.25,0.23,0.29) | AJ4: =CHOOSE(MATCH(IF($U4="","Основний",$U4),{"Трафіковий","Основний","Маржинальний","Сезонний","Стратегічний"},0),0.14,0.17,0.22,0.21,0.25) | AK4: =CHOOSE(MATCH(IF($U4="","Основний",$U4),{"Трафіковий","Основний","Маржинальний","Сезонний","Стратегічний"},0),0.15,0.18,0.23,0.22,0.27) | AL4: =CHOOSE(MATCH(IF($U4="","Основний",$U4),{"Трафіковий","Основний","Маржинальний","Сезонний","Стратегічний"},0),0.15,0.17,0.25,0.24,0.29) | AM4: =CHOOSE(MATCH(IF($U4="","Основний",$U4),{"Трафіковий","Основний","Маржинальний","Сезонний","Стратегічний"},0),0.12,0.145,0.19,0.18,0.22) | AN4: =CHOOSE(MATCH(IF($U4="","Основний",$U4),{"Трафіковий","Основний","Маржинальний","Сезонний","Стратегічний"},0),Settings!$B$78,Settings!$B$80,Settings!$B$82,Settings!$B$84,Settings!$B$86) | AO4: =CHOOSE(MATCH(IF($U4="","Основний",$U4),{"Трафіковий","Основний","Маржинальний","Сезонний","Стратегічний"},0),Settings!$C$78,Settings!$C$80,Settings!$C$82,Settings!$C$84,Settings!$C$86) | AP4: =CHOOSE(MATCH(IF($U4="","Основний",$U4),{"Трафіковий","Основний","Маржинальний","Сезонний","Стратегічний"},0),Settings!$D$78,Settings!$D$80,Settings!$D$82,Settings!$D$84,Settings!$D$86) | AQ4: =CHOOSE(MATCH(IF($U4="","Основний",$U4),{"Трафіковий","Основний","Маржинальний","Сезонний","Стратегічний"},0),Settings!$F$78,Settings!$F$80,Settings!$F$82,Settings!$F$84,Settings!$F$86) | AR4: =CHOOSE(MATCH(IF($U4="","Основний",$U4),{"Трафіковий","Основний","Маржинальний","Сезонний","Стратегічний"},0),Settings!$G$78,Settings!$G$80,Settings!$G$82,Settings!$G$84,Settings!$G$86) | AS4: =CHOOSE(MATCH(IF($U4="","Основний",$U4),{"Трафіковий","Основний","Маржинальний","Сезонний","Стратегічний"},0),Settings!$H$78,Settings!$H$80,Settings!$H$82,Settings!$H$84,Settings!$H$86) | AT4: =CHOOSE(MATCH(IF($U4="","Основний",$U4),{"Трафіковий","Основний","Маржинальний","Сезонний","Стратегічний"},0),Settings!$I$78,Settings!$I$80,Settings!$I$82,Settings!$I$84,Settings!$I$86) | AV4: 1.67
B5: B7426 | C5: RAVER BAT. NIMH HR6 2BL | D5: Батарейки | E5: 2 | F5: 0.491 | G5: 8507500090 | H5: 1.3 | I5: =IFERROR(F5*Settings!$B$2*H5*IF(AND(ISNUMBER(E5),E5>1),E5,1),"") | J5: =Settings!$B$66 | K5: =IFERROR(IF(T5="","",(T5*(1-AN5)*(1-Settings!$B$17)-I5)/(T5*(1-AN5)*(1-Settings!$B$17))),"") | L5: =IFERROR(IF(T5="","",(T5*(1-AO5)*(1-Settings!$C$17)-I5)/(T5*(1-AO5)*(1-Settings!$C$17))),"") | M5: =IFERROR(IF(T5="","",(T5*(1-AP5)*(1-Settings!$D$17)-I5)/(T5*(1-AP5)*(1-Settings!$D$17))),"") | N5: =IFERROR(IF(T5="","",(T5*(1-AQ5)*(1-Settings!$F$17)-I5)/(T5*(1-AQ5)*(1-Settings!$F$17))),"") | O5: =IFERROR(IF(T5="","",(T5*(1-AR5)*(1-Settings!$G$17)-I5)/(T5*(1-AR5)*(1-Settings!$G$17))),"") | P5: =IFERROR(IF(T5="","",(T5*(1-AS5)*(1-Settings!$H$17)-I5)/(T5*(1-AS5)*(1-Settings!$H$17))),"") | Q5: =IFERROR(IF(T5="","",(T5*(1-AT5)*(1-Settings!$I$68)*(1-Settings!$I$17)-I5)/(T5*(1-AT5)*(1-Settings!$I$68)*(1-Settings!$I$17))),"") | R5: =IFERROR(IF(OR(I5="",Z5>=1,Settings!$B$17>=1,AN5>=1),"",IF(MOD(ROUND(I5/(1-Z5)/(1-Settings!$B$17)/(1-AN5),0),10)=0,ROUND(I5/(1-Z5)/(1-Settings!$B$17)/(1-AN5),0)-1,IF(MOD(ROUND(I5/(1-Z5)/(1-Settings!$B$17)/(1-AN5),0),10)<=5,FLOOR(ROUND(I5/(1-Z5)/(1-Settings!$B$17)/(1-AN5),0),10)+6,FLOOR(ROUND(I5/(1-Z5)/(1-Settings!$B$17)/(1-AN5),0),10)+9))),"") | S5: 130 | T5: =IF(S5<>"", IF(MOD(S5,10)=0,S5-1,IF(MOD(S5,10)<=5,FLOOR(S5,10)+6,FLOOR(S5,10)+9)), R5) | U5: Маржинальний | X5: =IFERROR(IF(OR(V5="",W5="",T5=""),"", IF(T5>W5,"Дорогий",IF(T5<V5,"Дешевий","У ринку"))),"") | Z5: =CHOOSE(MATCH(IF($U5="","Основний",$U5),{"Трафіковий","Основний","Маржинальний","Сезонний","Стратегічний"},0),0.16,0.19,0.24,0.23,0.28) | AA5: =CHOOSE(MATCH(IF($U5="","Основний",$U5),{"Трафіковий","Основний","Маржинальний","Сезонний","Стратегічний"},0),0.18,0.21,0.26,0.25,0.3) | AB5: =CHOOSE(MATCH(IF($U5="","Основний",$U5),{"Трафіковий","Основний","Маржинальний","Сезонний","Стратегічний"},0),0.19,0.22,0.28,0.26,0.32) | AC5: =CHOOSE(MATCH(IF($U5="","Основний",$U5),{"Трафіковий","Основний","Маржинальний","Сезонний","Стратегічний"},0),0.17,0.2,0.25,0.24,0.28) | AD5: =CHOOSE(MATCH(IF($U5="","Основний",$U5),{"Трафіковий","Основний","Маржинальний","Сезонний","Стратегічний"},0),0.18,0.21,0.26,0.25,0.3) | AE5: =CHOOSE(MATCH(IF($U5="","Основний",$U5),{"Трафіковий","Основний","Маржинальний","Сезонний","Стратегічний"},0),0.18,0.2,0.28,0.27,0.32) | AF5: =CHOOSE(MATCH(IF($U5="","Основний",$U5),{"Трафіковий","Основний","Маржинальний","Сезонний","Стратегічний"},0),0.15,0.175,0.22,0.21,0.25) | AG5: =CHOOSE(MATCH(IF($U5="","Основний",$U5),{"Трафіковий","Основний","Маржинальний","Сезонний","Стратегічний"},0),0.13,0.16,0.21,0.2,0.25) | AH5: =CHOOSE(MATCH(IF($U5="","Основний",$U5),{"Трафіковий","Основний","Маржинальний","Сезонний","Стратегічний"},0),0.15,0.18,0.23,0.22,0.27) | AI5: =CHOOSE(MATCH(IF($U5="","Основний",$U5),{"Трафіковий","Основний","Маржинальний","Сезонний","Стратегічний"},0),0.16,0.19,0.25,0.23,0.29) | AJ5: =CHOOSE(MATCH(IF($U5="","Основний",$U5),{"Трафіковий","Основний","Маржинальний","Сезонний","Стратегічний"},0),0.14,0.17,0.22,0.21,0.25) | AK5: =CHOOSE(MATCH(IF($U5="","Основний",$U5),{"Трафіковий","Основний","Маржинальний","Сезонний","Стратегічний"},0),0.15,0.18,0.23,0.22,0.27) | AL5: =CHOOSE(MATCH(IF($U5="","Основний",$U5),{"Трафіковий","Основний","Маржинальний","Сезонний","Стратегічний"},0),0.15,0.17,0.25,0.24,0.29) | AM5: =CHOOSE(MATCH(IF($U5="","Основний",$U5),{"Трафіковий","Основний","Маржинальний","Сезонний","Стратегічний"},0),0.12,0.145,0.19,0.18,0.22) | AN5: =CHOOSE(MATCH(IF($U5="","Основний",$U5),{"Трафіковий","Основний","Маржинальний","Сезонний","Стратегічний"},0),Settings!$B$78,Settings!$B$80,Settings!$B$82,Settings!$B$84,Settings!$B$86) | AO5: =CHOOSE(MATCH(IF($U5="","Основний",$U5),{"Трафіковий","Основний","Маржинальний","Сезонний","Стратегічний"},0),Settings!$C$78,Settings!$C$80,Settings!$C$82,Settings!$C$84,Settings!$C$86) | AP5: =CHOOSE(MATCH(IF($U5="","Основний",$U5),{"Трафіковий","Основний","Маржинальний","Сезонний","Стратегічний"},0),Settings!$D$78,Settings!$D$80,Settings!$D$82,Settings!$D$84,Settings!$D$86) | AQ5: =CHOOSE(MATCH(IF($U5="","Основний",$U5),{"Трафіковий","Основний","Маржинальний","Сезонний","Стратегічний"},0),Settings!$F$78,Settings!$F$80,Settings!$F$82,Settings!$F$84,Settings!$F$86) | AR5: =CHOOSE(MATCH(IF($U5="","Основний",$U5),{"Трафіковий","Основний","Маржинальний","Сезонний","Стратегічний"},0),Settings!$G$78,Settings!$G$80,Settings!$G$82,Settings!$G$84,Settings!$G$86) | AS5: =CHOOSE(MATCH(IF($U5="","Основний",$U5),{"Трафіковий","Основний","Маржинальний","Сезонний","Стратегічний"},0),Settings!$H$78,Settings!$H$80,Settings!$H$82,Settings!$H$84,Settings!$H$86) | AT5: =CHOOSE(MATCH(IF($U5="","Основний",$U5),{"Трафіковий","Основний","Маржинальний","Сезонний","Стратегічний"},0),Settings!$I$78,Settings!$I$80,Settings!$I$82,Settings!$I$84,Settings!$I$86) | AV5: 1.4
B6: B7414 | C6: RAVER BAT. NIMH HR03 2BL | D6: Батарейки | E6: 2 | F6: 0.428 | G6: 8507500090 | H6: 1.3 | I6: =IFERROR(F6*Settings!$B$2*H6*IF(AND(ISNUMBER(E6),E6>1),E6,1),"") | J6: =Settings!$B$66 | K6: =IFERROR(IF(T6="","",(T6*(1-AN6)*(1-Settings!$B$17)-I6)/(T6*(1-AN6)*(1-Settings!$B$17))),"") | L6: =IFERROR(IF(T6="","",(T6*(1-AO6)*(1-Settings!$C$17)-I6)/(T6*(1-AO6)*(1-Settings!$C$17))),"") | M6: =IFERROR(IF(T6="","",(T6*(1-AP6)*(1-Settings!$D$17)-I6)/(T6*(1-AP6)*(1-Settings!$D$17))),"") | N6: =IFERROR(IF(T6="","",(T6*(1-AQ6)*(1-Settings!$F$17)-I6)/(T6*(1-AQ6)*(1-Settings!$F$17))),"") | O6: =IFERROR(IF(T6="","",(T6*(1-AR6)*(1-Settings!$G$17)-I6)/(T6*(1-AR6)*(1-Settings!$G$17))),"") | P6: =IFERROR(IF(T6="","",(T6*(1-AS6)*(1-Settings!$H$17)-I6)/(T6*(1-AS6)*(1-Settings!$H$17))),"") | Q6: =IFERROR(IF(T6="","",(T6*(1-AT6)*(1-Settings!$I$68)*(1-Settings!$I$17)-I6)/(T6*(1-AT6)*(1-Settings!$I$68)*(1-Settings!$I$17))),"") | R6: =IFERROR(IF(OR(I6="",Z6>=1,Settings!$B$17>=1,AN6>=1),"",IF(MOD(ROUND(I6/(1-Z6)/(1-Settings!$B$17)/(1-AN6),0),10)=0,ROUND(I6/(1-Z6)/(1-Settings!$B$17)/(1-AN6),0)-1,IF(MOD(ROUND(I6/(1-Z6)/(1-Settings!$B$17)/(1-AN6),0),10)<=5,FLOOR(ROUND(I6/(1-Z6)/(1-Settings!$B$17)/(1-AN6),0),10)+6,FLOOR(ROUND(I6/(1-Z6)/(1-Settings!$B$17)/(1-AN6),0),10)+9))),"") | S6: 120 | T6: =IF(S6<>"", IF(MOD(S6,10)=0,S6-1,IF(MOD(S6,10)<=5,FLOOR(S6,10)+6,FLOOR(S6,10)+9)), R6) | U6: Маржинальний | X6: =IFERROR(IF(OR(V6="",W6="",T6=""),"", IF(T6>W6,"Дорогий",IF(T6<V6,"Дешевий","У ринку"))),"") | Z6: =CHOOSE(MATCH(IF($U6="","Основний",$U6),{"Трафіковий","Основний","Маржинальний","Сезонний","Стратегічний"},0),0.16,0.19,0.24,0.23,0.28) | AA6: =CHOOSE(MATCH(IF($U6="","Основний",$U6),{"Трафіковий","Основний","Маржинальний","Сезонний","Стратегічний"},0),0.18,0.21,0.26,0.25,0.3) | AB6: =CHOOSE(MATCH(IF($U6="","Основний",$U6),{"Трафіковий","Основний","Маржинальний","Сезонний","Стратегічний"},0),0.19,0.22,0.28,0.26,0.32) | AC6: =CHOOSE(MATCH(IF($U6="","Основний",$U6),{"Трафіковий","Основний","Маржинальний","Сезонний","Стратегічний"},0),0.17,0.2,0.25,0.24,0.28) | AD6: =CHOOSE(MATCH(IF($U6="","Основний",$U6),{"Трафіковий","Основний","Маржинальний","Сезонний","Стратегічний"},0),0.18,0.21,0.26,0.25,0.3) | AE6: =CHOOSE(MATCH(IF($U6="","Основний",$U6),{"Трафіковий","Основний","Маржинальний","Сезонний","Стратегічний"},0),0.18,0.2,0.28,0.27,0.32) | AF6: =CHOOSE(MATCH(IF($U6="","Основний",$U6),{"Трафіковий","Основний","Маржинальний","Сезонний","Стратегічний"},0),0.15,0.175,0.22,0.21,0.25) | AG6: =CHOOSE(MATCH(IF($U6="","Основний",$U6),{"Трафіковий","Основний","Маржинальний","Сезонний","Стратегічний"},0),0.13,0.16,0.21,0.2,0.25) | AH6: =CHOOSE(MATCH(IF($U6="","Основний",$U6),{"Трафіковий","Основний","Маржинальний","Сезонний","Стратегічний"},0),0.15,0.18,0.23,0.22,0.27) | AI6: =CHOOSE(MATCH(IF($U6="","Основний",$U6),{"Трафіковий","Основний","Маржинальний","Сезонний","Стратегічний"},0),0.16,0.19,0.25,0.23,0.29) | AJ6: =CHOOSE(MATCH(IF($U6="","Основний",$U6),{"Трафіковий","Основний","Маржинальний","Сезонний","Стратегічний"},0),0.14,0.17,0.22,0.21,0.25) | AK6: =CHOOSE(MATCH(IF($U6="","Основний",$U6),{"Трафіковий","Основний","Маржинальний","Сезонний","Стратегічний"},0),0.15,0.18,0.23,0.22,0.27) | AL6: =CHOOSE(MATCH(IF($U6="","Основний",$U6),{"Трафіковий","Основний","Маржинальний","Сезонний","Стратегічний"},0),0.15,0.17,0.25,0.24,0.29) | AM6: =CHOOSE(MATCH(IF($U6="","Основний",$U6),{"Трафіковий","Основний","Маржинальний","Сезонний","Стратегічний"},0),0.12,0.145,0.19,0.18,0.22) | AN6: =CHOOSE(MATCH(IF($U6="","Основний",$U6),{"Трафіковий","Основний","Маржинальний","Сезонний","Стратегічний"},0),Settings!$B$78,Settings!$B$80,Settings!$B$82,Settings!$B$84,Settings!$B$86) | AO6: =CHOOSE(MATCH(IF($U6="","Основний",$U6),{"Трафіковий","Основний","Маржинальний","Сезонний","Стратегічний"},0),Settings!$C$78,Settings!$C$80,Settings!$C$82,Settings!$C$84,Settings!$C$86) | AP6: =CHOOSE(MATCH(IF($U6="","Основний",$U6),{"Трафіковий","Основний","Маржинальний","Сезонний","Стратегічний"},0),Settings!$D$78,Settings!$D$80,Settings!$D$82,Settings!$D$84,Settings!$D$86) | AQ6: =CHOOSE(MATCH(IF($U6="","Основний",$U6),{"Трафіковий","Основний","Маржинальний","Сезонний","Стратегічний"},0),Settings!$F$78,Settings!$F$80,Settings!$F$82,Settings!$F$84,Settings!$F$86) | AR6: =CHOOSE(MATCH(IF($U6="","Основний",$U6),{"Трафіковий","Основний","Маржинальний","Сезонний","Стратегічний"},0),Settings!$G$78,Settings!$G$80,Settings!$G$82,Settings!$G$84,Settings!$G$86) | AS6: =CHOOSE(MATCH(IF($U6="","Основний",$U6),{"Трафіковий","Основний","Маржинальний","Сезонний","Стратегічний"},0),Settings!$H$78,Settings!$H$80,Settings!$H$82,Settings!$H$84,Settings!$H$86) | AT6: =CHOOSE(MATCH(IF($U6="","Основний",$U6),{"Трафіковий","Основний","Маржинальний","Сезонний","Стратегічний"},0),Settings!$I$78,Settings!$I$80,Settings!$I$82,Settings!$I$84,Settings!$I$86) | AV6: 1.4
A7: SELL OUT | B7: B7316 | C7: RAVER BAT. WATCH CR2016, 5BL | D7: Батарейки | E7: 5 | F7: 0.083 | G7: 8506503000 | H7: 1.35 | I7: =IFERROR(F7*Settings!$B$2*H7*IF(AND(ISNUMBER(E7),E7>1),E7,1),"") | J7: =Settings!$B$66 | K7: =IFERROR(IF(T7="","",(T7*(1-AN7)*(1-Settings!$B$17)-I7)/(T7*(1-AN7)*(1-Settings!$B$17))),"") | L7: =IFERROR(IF(T7="","",(T7*(1-AO7)*(1-Settings!$C$17)-I7)/(T7*(1-AO7)*(1-Settings!$C$17))),"") | M7: =IFERROR(IF(T7="","",(T7*(1-AP7)*(1-Settings!$D$17)-I7)/(T7*(1-AP7)*(1-Settings!$D$17))),"") | N7: =IFERROR(IF(T7="","",(T7*(1-AQ7)*(1-Settings!$F$17)-I7)/(T7*(1-AQ7)*(1-Settings!$F$17))),"") | O7: =IFERROR(IF(T7="","",(T7*(1-AR7)*(1-Settings!$G$17)-I7)/(T7*(1-AR7)*(1-Settings!$G$17))),"") | P7: =IFERROR(IF(T7="","",(T7*(1-AS7)*(1-Settings!$H$17)-I7)/(T7*(1-AS7)*(1-Settings!$H$17))),"") | Q7: =IFERROR(IF(T7="","",(T7*(1-AT7)*(1-Settings!$I$68)*(1-Settings!$I$17)-I7)/(T7*(1-AT7)*(1-Settings!$I$68)*(1-Settings!$I$17))),"") | R7: =IFERROR(IF(OR(I7="",Z7>=1,Settings!$B$17>=1,AN7>=1),"",IF(MOD(ROUND(I7/(1-Z7)/(1-Settings!$B$17)/(1-AN7),0),10)=0,ROUND(I7/(1-Z7)/(1-Settings!$B$17)/(1-AN7),0)-1,IF(MOD(ROUND(I7/(1-Z7)/(1-Settings!$B$17)/(1-AN7),0),10)<=5,FLOOR(ROUND(I7/(1-Z7)/(1-Settings!$B$17)/(1-AN7),0),10)+6,FLOOR(ROUND(I7/(1-Z7)/(1-Settings!$B$17)/(1-AN7),0),10)+9))),"") | S7: 69 | T7: =IF(S7<>"", IF(MOD(S7,10)=0,S7-1,IF(MOD(S7,10)<=5,FLOOR(S7,10)+6,FLOOR(S7,10)+9)), R7) | U7: Маржинальний | X7: =IFERROR(IF(OR(V7="",W7="",T7=""),"", IF(T7>W7,"Дорогий",IF(T7<V7,"Дешевий","У ринку"))),"") | Z7: =CHOOSE(MATCH(IF($U7="","Основний",$U7),{"Трафіковий","Основний","Маржинальний","Сезонний","Стратегічний"},0),0.16,0.19,0.24,0.23,0.28) | AA7: =CHOOSE(MATCH(IF($U7="","Основний",$U7),{"Трафіковий","Основний","Маржинальний","Сезонний","Стратегічний"},0),0.18,0.21,0.26,0.25,0.3) | AB7: =CHOOSE(MATCH(IF($U7="","Основний",$U7),{"Трафіковий","Основний","Маржинальний","Сезонний","Стратегічний"},0),0.19,0.22,0.28,0.26,0.32) | AC7: =CHOOSE(MATCH(IF($U7="","Основний",$U7),{"Трафіковий","Основний","Маржинальний","Сезонний","Стратегічний"},0),0.17,0.2,0.25,0.24,0.28) | AD7: =CHOOSE(MATCH(IF($U7="","Основний",$U7),{"Трафіковий","Основний","Маржинальний","Сезонний","Стратегічний"},0),0.18,0.21,0.26,0.25,0.3) | AE7: =CHOOSE(MATCH(IF($U7="","Основний",$U7),{"Трафіковий","Основний","Маржинальний","Сезонний","Стратегічний"},0),0.18,0.2,0.28,0.27,0.32) | AF7: =CHOOSE(MATCH(IF($U7="","Основний",$U7),{"Трафіковий","Основний","Маржинальний","Сезонний","Стратегічний"},0),0.15,0.175,0.22,0.21,0.25) | AG7: =CHOOSE(MATCH(IF($U7="","Основний",$U7),{"Трафіковий","Основний","Маржинальний","Сезонний","Стратегічний"},0),0.13,0.16,0.21,0.2,0.25) | AH7: =CHOOSE(MATCH(IF($U7="","Основний",$U7),{"Трафіковий","Основний","Маржинальний","Сезонний","Стратегічний"},0),0.15,0.18,0.23,0.22,0.27) | AI7: =CHOOSE(MATCH(IF($U7="","Основний",$U7),{"Трафіковий","Основний","Маржинальний","Сезонний","Стратегічний"},0),0.16,0.19,0.25,0.23,0.29) | AJ7: =CHOOSE(MATCH(IF($U7="","Основний",$U7),{"Трафіковий","Основний","Маржинальний","Сезонний","Стратегічний"},0),0.14,0.17,0.22,0.21,0.25) | AK7: =CHOOSE(MATCH(IF($U7="","Основний",$U7),{"Трафіковий","Основний","Маржинальний","Сезонний","Стратегічний"},0),0.15,0.18,0.23,0.22,0.27) | AL7: =CHOOSE(MATCH(IF($U7="","Основний",$U7),{"Трафіковий","Основний","Маржинальний","Сезонний","Стратегічний"},0),0.15,0.17,0.25,0.24,0.29) | AM7: =CHOOSE(MATCH(IF($U7="","Основний",$U7),{"Трафіковий","Основний","Маржинальний","Сезонний","Стратегічний"},0),0.12,0.145,0.19,0.18,0.22) | AN7: =CHOOSE(MATCH(IF($U7="","Основний",$U7),{"Трафіковий","Основний","Маржинальний","Сезонний","Стратегічний"},0),Settings!$B$78,Settings!$B$80,Settings!$B$82,Settings!$B$84,Settings!$B$86) | AO7: =CHOOSE(MATCH(IF($U7="","Основний",$U7),{"Трафіковий","Основний","Маржинальний","Сезонний","Стратегічний"},0),Settings!$C$78,Settings!$C$80,Settings!$C$82,Settings!$C$84,Settings!$C$86) | AP7: =CHOOSE(MATCH(IF($U7="","Основний",$U7),{"Трафіковий","Основний","Маржинальний","Сезонний","Стратегічний"},0),Settings!$D$78,Settings!$D$80,Settings!$D$82,Settings!$D$84,Settings!$D$86) | AQ7: =CHOOSE(MATCH(IF($U7="","Основний",$U7),{"Трафіковий","Основний","Маржинальний","Сезонний","Стратегічний"},0),Settings!$F$78,Settings!$F$80,Settings!$F$82,Settings!$F$84,Settings!$F$86) | AR7: =CHOOSE(MATCH(IF($U7="","Основний",$U7),{"Трафіковий","Основний","Маржинальний","Сезонний","Стратегічний"},0),Settings!$G$78,Settings!$G$80,Settings!$G$82,Settings!$G$84,Settings!$G$86) | AS7: =CHOOSE(MATCH(IF($U7="","Основний",$U7),{"Трафіковий","Основний","Маржинальний","Сезонний","Стратегічний"},0),Settings!$H$78,Settings!$H$80,Settings!$H$82,Settings!$H$84,Settings!$H$86) | AT7: =CHOOSE(MATCH(IF($U7="","Основний",$U7),{"Трафіковий","Основний","Маржинальний","Сезонний","Стратегічний"},0),Settings!$I$78,Settings!$I$80,Settings!$I$82,Settings!$I$84,Settings!$I$86) | AV7: 1.67
A8: SELL OUT | B8: B7325 | C8: RAVER BAT. WATCH CR2025, 5BL | D8: Батарейки | E8: 5 | F8: 0.089 | G8: 8506503000 | H8: 1.35 | I8: =IFERROR(F8*Settings!$B$2*H8*IF(AND(ISNUMBER(E8),E8>1),E8,1),"") | J8: =Settings!$B$66 | K8: =IFERROR(IF(T8="","",(T8*(1-AN8)*(1-Settings!$B$17)-I8)/(T8*(1-AN8)*(1-Settings!$B$17))),"") | L8: =IFERROR(IF(T8="","",(T8*(1-AO8)*(1-Settings!$C$17)-I8)/(T8*(1-AO8)*(1-Settings!$C$17))),"") | M8: =IFERROR(IF(T8="","",(T8*(1-AP8)*(1-Settings!$D$17)-I8)/(T8*(1-AP8)*(1-Settings!$D$17))),"") | N8: =IFERROR(IF(T8="","",(T8*(1-AQ8)*(1-Settings!$F$17)-I8)/(T8*(1-AQ8)*(1-Settings!$F$17))),"") | O8: =IFERROR(IF(T8="","",(T8*(1-AR8)*(1-Settings!$G$17)-I8)/(T8*(1-AR8)*(1-Settings!$G$17))),"") | P8: =IFERROR(IF(T8="","",(T8*(1-AS8)*(1-Settings!$H$17)-I8)/(T8*(1-AS8)*(1-Settings!$H$17))),"") | Q8: =IFERROR(IF(T8="","",(T8*(1-AT8)*(1-Settings!$I$68)*(1-Settings!$I$17)-I8)/(T8*(1-AT8)*(1-Settings!$I$68)*(1-Settings!$I$17))),"") | R8: =IFERROR(IF(OR(I8="",Z8>=1,Settings!$B$17>=1,AN8>=1),"",IF(MOD(ROUND(I8/(1-Z8)/(1-Settings!$B$17)/(1-AN8),0),10)=0,ROUND(I8/(1-Z8)/(1-Settings!$B$17)/(1-AN8),0)-1,IF(MOD(ROUND(I8/(1-Z8)/(1-Settings!$B$17)/(1-AN8),0),10)<=5,FLOOR(ROUND(I8/(1-Z8)/(1-Settings!$B$17)/(1-AN8),0),10)+6,FLOOR(ROUND(I8/(1-Z8)/(1-Settings!$B$17)/(1-AN8),0),10)+9))),"") | S8: 70 | T8: =IF(S8<>"", IF(MOD(S8,10)=0,S8-1,IF(MOD(S8,10)<=5,FLOOR(S8,10)+6,FLOOR(S8,10)+9)), R8) | U8: Маржинальний | X8: =IFERROR(IF(OR(V8="",W8="",T8=""),"", IF(T8>W8,"Дорогий",IF(T8<V8,"Дешевий","У ринку"))),"") | Z8: =CHOOSE(MATCH(IF($U8="","Основний",$U8),{"Трафіковий","Основний","Маржинальний","Сезонний","Стратегічний"},0),0.16,0.19,0.24,0.23,0.28) | AA8: =CHOOSE(MATCH(IF($U8="","Основний",$U8),{"Трафіковий","Основний","Маржинальний","Сезонний","Стратегічний"},0),0.18,0.21,0.26,0.25,0.3) | AB8: =CHOOSE(MATCH(IF($U8="","Основний",$U8),{"Трафіковий","Основний","Маржинальний","Сезонний","Стратегічний"},0),0.19,0.22,0.28,0.26,0.32) | AC8: =CHOOSE(MATCH(IF($U8="","Основний",$U8),{"Трафіковий","Основний","Маржинальний","Сезонний","Стратегічний"},0),0.17,0.2,0.25,0.24,0.28) | AD8: =CHOOSE(MATCH(IF($U8="","Основний",$U8),{"Трафіковий","Основний","Маржинальний","Сезонний","Стратегічний"},0),0.18,0.21,0.26,0.25,0.3) | AE8: =CHOOSE(MATCH(IF($U8="","Основний",$U8),{"Трафіковий","Основний","Маржинальний","Сезонний","Стратегічний"},0),0.18,0.2,0.28,0.27,0.32) | AF8: =CHOOSE(MATCH(IF($U8="","Основний",$U8),{"Трафіковий","Основний","Маржинальний","Сезонний","Стратегічний"},0),0.15,0.175,0.22,0.21,0.25) | AG8: =CHOOSE(MATCH(IF($U8="","Основний",$U8),{"Трафіковий","Основний","Маржинальний","Сезонний","Стратегічний"},0),0.13,0.16,0.21,0.2,0.25) | AH8: =CHOOSE(MATCH(IF($U8="","Основний",$U8),{"Трафіковий","Основний","Маржинальний","Сезонний","Стратегічний"},0),0.15,0.18,0.23,0.22,0.27) | AI8: =CHOOSE(MATCH(IF($U8="","Основний",$U8),{"Трафіковий","Основний","Маржинальний","Сезонний","Стратегічний"},0),0.16,0.19,0.25,0.23,0.29) | AJ8: =CHOOSE(MATCH(IF($U8="","Основний",$U8),{"Трафіковий","Основний","Маржинальний","Сезонний","Стратегічний"},0),0.14,0.17,0.22,0.21,0.25) | AK8: =CHOOSE(MATCH(IF($U8="","Основний",$U8),{"Трафіковий","Основний","Маржинальний","Сезонний","Стратегічний"},0),0.15,0.18,0.23,0.22,0.27) | AL8: =CHOOSE(MATCH(IF($U8="","Основний",$U8),{"Трафіковий","Основний","Маржинальний","Сезонний","Стратегічний"},0),0.15,0.17,0.25,0.24,0.29) | AM8: =CHOOSE(MATCH(IF($U8="","Основний",$U8),{"Трафіковий","Основний","Маржинальний","Сезонний","Стратегічний"},0),0.12,0.145,0.19,0.18,0.22) | AN8: =CHOOSE(MATCH(IF($U8="","Основний",$U8),{"Трафіковий","Основний","Маржинальний","Сезонний","Стратегічний"},0),Settings!$B$78,Settings!$B$80,Settings!$B$82,Settings!$B$84,Settings!$B$86) | AO8: =CHOOSE(MATCH(IF($U8="","Основний",$U8),{"Трафіковий","Основний","Маржинальний","Сезонний","Стратегічний"},0),Settings!$C$78,Settings!$C$80,Settings!$C$82,Settings!$C$84,Settings!$C$86) | AP8: =CHOOSE(MATCH(IF($U8="","Основний",$U8),{"Трафіковий","Основний","Маржинальний","Сезонний","Стратегічний"},0),Settings!$D$78,Settings!$D$80,Settings!$D$82,Settings!$D$84,Settings!$D$86) | AQ8: =CHOOSE(MATCH(IF($U8="","Основний",$U8),{"Трафіковий","Основний","Маржинальний","Сезонний","Стратегічний"},0),Settings!$F$78,Settings!$F$80,Settings!$F$82,Settings!$F$84,Settings!$F$86) | AR8: =CHOOSE(MATCH(IF($U8="","Основний",$U8),{"Трафіковий","Основний","Маржинальний","Сезонний","Стратегічний"},0),Settings!$G$78,Settings!$G$80,Settings!$G$82,Settings!$G$84,Settings!$G$86) | AS8: =CHOOSE(MATCH(IF($U8="","Основний",$U8),{"Трафіковий","Основний","Маржинальний","Сезонний","Стратегічний"},0),Settings!$H$78,Settings!$H$80,Settings!$H$82,Settings!$H$84,Settings!$H$86) | AT8: =CHOOSE(MATCH(IF($U8="","Основний",$U8),{"Трафіковий","Основний","Маржинальний","Сезонний","Стратегічний"},0),Settings!$I$78,Settings!$I$80,Settings!$I$82,Settings!$I$84,Settings!$I$86) | AV8: 1.67
B9: N0322 | C9: UNI BATTERY TESTER LCD | D9: Зарядні пристрої для акумуляторів | E9: PC | F9: 2.244 | G9: 9030337000 | H9: 1.3 | I9: =IFERROR(F9*Settings!$B$2*H9*IF(AND(ISNUMBER(E9),E9>1),E9,1),"") | J9: =Settings!$B$66 | K9: =IFERROR(IF(T9="","",(T9*(1-AN9)*(1-Settings!$B$17)-I9)/(T9*(1-AN9)*(1-Settings!$B$17))),"") | L9: =IFERROR(IF(T9="","",(T9*(1-AO9)*(1-Settings!$C$17)-I9)/(T9*(1-AO9)*(1-Settings!$C$17))),"") | M9: =IFERROR(IF(T9="","",(T9*(1-AP9)*(1-Settings!$D$17)-I9)/(T9*(1-AP9)*(1-Settings!$D$17))),"") | N9: =IFERROR(IF(T9="","",(T9*(1-AQ9)*(1-Settings!$F$17)-I9)/(T9*(1-AQ9)*(1-Settings!$F$17))),"") | O9: =IFERROR(IF(T9="","",(T9*(1-AR9)*(1-Settings!$G$17)-I9)/(T9*(1-AR9)*(1-Settings!$G$17))),"") | P9: =IFERROR(IF(T9="","",(T9*(1-AS9)*(1-Settings!$H$17)-I9)/(T9*(1-AS9)*(1-Settings!$H$17))),"") | Q9: =IFERROR(IF(T9="","",(T9*(1-AT9)*(1-Settings!$I$68)*(1-Settings!$I$17)-I9)/(T9*(1-AT9)*(1-Settings!$I$68)*(1-Settings!$I$17))),"") | R9: =IFERROR(IF(OR(I9="",Z9>=1,Settings!$B$17>=1,AN9>=1),"",IF(MOD(ROUND(I9/(1-Z9)/(1-Settings!$B$17)/(1-AN9),0),10)=0,ROUND(I9/(1-Z9)/(1-Settings!$B$17)/(1-AN9),0)-1,IF(MOD(ROUND(I9/(1-Z9)/(1-Settings!$B$17)/(1-AN9),0),10)<=5,FLOOR(ROUND(I9/(1-Z9)/(1-Settings!$B$17)/(1-AN9),0),10)+6,FLOOR(ROUND(I9/(1-Z9)/(1-Settings!$B$17)/(1-AN9),0),10)+9))),"") | T9: =IF(S9<>"", IF(MOD(S9,10)=0,S9-1,IF(MOD(S9,10)<=5,FLOOR(S9,10)+6,FLOOR(S9,10)+9)), R9) | U9: Основний | X9: =IFERROR(IF(OR(V9="",W9="",T9=""),"", IF(T9>W9,"Дорогий",IF(T9<V9,"Дешевий","У ринку"))),"") | Z9: =CHOOSE(MATCH(IF($U9="","Основний",$U9),{"Трафіковий","Основний","Маржинальний","Сезонний","Стратегічний"},0),0.16,0.19,0.24,0.23,0.28) | AA9: =CHOOSE(MATCH(IF($U9="","Основний",$U9),{"Трафіковий","Основний","Маржинальний","Сезонний","Стратегічний"},0),0.18,0.21,0.26,0.25,0.3) | AB9: =CHOOSE(MATCH(IF($U9="","Основний",$U9),{"Трафіковий","Основний","Маржинальний","Сезонний","Стратегічний"},0),0.19,0.22,0.28,0.26,0.32) | AC9: =CHOOSE(MATCH(IF($U9="","Основний",$U9),{"Трафіковий","Основний","Маржинальний","Сезонний","Стратегічний"},0),0.17,0.2,0.25,0.24,0.28) | AD9: =CHOOSE(MATCH(IF($U9="","Основний",$U9),{"Трафіковий","Основний","Маржинальний","Сезонний","Стратегічний"},0),0.18,0.21,0.26,0.25,0.3) | AE9: =CHOOSE(MATCH(IF($U9="","Основний",$U9),{"Трафіковий","Основний","Маржинальний","Сезонний","Стратегічний"},0),0.18,0.2,0.28,0.27,0.32) | AF9: =CHOOSE(MATCH(IF($U9="","Основний",$U9),{"Трафіковий","Основний","Маржинальний","Сезонний","Стратегічний"},0),0.15,0.175,0.22,0.21,0.25) | AG9: =CHOOSE(MATCH(IF($U9="","Основний",$U9),{"Трафіковий","Основний","Маржинальний","Сезонний","Стратегічний"},0),0.13,0.16,0.21,0.2,0.25) | AH9: =CHOOSE(MATCH(IF($U9="","Основний",$U9),{"Трафіковий","Основний","Маржинальний","Сезонний","Стратегічний"},0),0.15,0.18,0.23,0.22,0.27) | AI9: =CHOOSE(MATCH(IF($U9="","Основний",$U9),{"Трафіковий","Основний","Маржинальний","Сезонний","Стратегічний"},0),0.16,0.19,0.25,0.23,0.29) | AJ9: =CHOOSE(MATCH(IF($U9="","Основний",$U9),{"Трафіковий","Основний","Маржинальний","Сезонний","Стратегічний"},0),0.14,0.17,0.22,0.21,0.25) | AK9: =CHOOSE(MATCH(IF($U9="","Основний",$U9),{"Трафіковий","Основний","Маржинальний","Сезонний","Стратегічний"},0),0.15,0.18,0.23,0.22,0.27) | AL9: =CHOOSE(MATCH(IF($U9="","Основний",$U9),{"Трафіковий","Основний","Маржинальний","Сезонний","Стратегічний"},0),0.15,0.17,0.25,0.24,0.29) | AM9: =CHOOSE(MATCH(IF($U9="","Основний",$U9),{"Трафіковий","Основний","Маржинальний","Сезонний","Стратегічний"},0),0.12,0.145,0.19,0.18,0.22) | AN9: =CHOOSE(MATCH(IF($U9="","Основний",$U9),{"Трафіковий","Основний","Маржинальний","Сезонний","Стратегічний"},0),Settings!$B$78,Settings!$B$80,Settings!$B$82,Settings!$B$84,Settings!$B$86) | AO9: =CHOOSE(MATCH(IF($U9="","Основний",$U9),{"Трафіковий","Основний","Маржинальний","Сезонний","Стратегічний"},0),Settings!$C$78,Settings!$C$80,Settings!$C$82,Settings!$C$84,Settings!$C$86) | AP9: =CHOOSE(MATCH(IF($U9="","Основний",$U9),{"Трафіковий","Основний","Маржинальний","Сезонний","Стратегічний"},0),Settings!$D$78,Settings!$D$80,Settings!$D$82,Settings!$D$84,Settings!$D$86) | AQ9: =CHOOSE(MATCH(IF($U9="","Основний",$U9),{"Трафіковий","Основний","Маржинальний","Сезонний","Стратегічний"},0),Settings!$F$78,Settings!$F$80,Settings!$F$82,Settings!$F$84,Settings!$F$86) | AR9: =CHOOSE(MATCH(IF($U9="","Основний",$U9),{"Трафіковий","Основний","Маржинальний","Сезонний","Стратегічний"},0),Settings!$G$78,Settings!$G$80,Settings!$G$82,Settings!$G$84,Settings!$G$86) | AS9: =CHOOSE(MATCH(IF($U9="","Основний",$U9),{"Трафіковий","Основний","Маржинальний","Сезонний","Стратегічний"},0),Settings!$H$78,Settings!$H$80,Settings!$H$82,Settings!$H$84,Settings!$H$86) | AT9: =CHOOSE(MATCH(IF($U9="","Основний",$U9),{"Трафіковий","Основний","Маржинальний","Сезонний","Стратегічний"},0),Settings!$I$78,Settings!$I$80,Settings!$I$82,Settings!$I$84,Settings!$I$86) | AV9: 1.35
B10: N9221 | C10: EMOS Universal Li-ion Battery Charger BCL-20D | D10: Зарядні пристрої для акумуляторів | E10: PC | F10: 8.901 | G10: 8504406090 | H10: 1.3 | I10: =IFERROR(F10*Settings!$B$2*H10*IF(AND(ISNUMBER(E10),E10>1),E10,1),"") | J10: =Settings!$B$66 | K10: =IFERROR(IF(T10="","",(T10*(1-AN10)*(1-Settings!$B$17)-I10)/(T10*(1-AN10)*(1-Settings!$B$17))),"") | L10: =IFERROR(IF(T10="","",(T10*(1-AO10)*(1-Settings!$C$17)-I10)/(T10*(1-AO10)*(1-Settings!$C$17))),"") | M10: =IFERROR(IF(T10="","",(T10*(1-AP10)*(1-Settings!$D$17)-I10)/(T10*(1-AP10)*(1-Settings!$D$17))),"") | N10: =IFERROR(IF(T10="","",(T10*(1-AQ10)*(1-Settings!$F$17)-I10)/(T10*(1-AQ10)*(1-Settings!$F$17))),"") | O10: =IFERROR(IF(T10="","",(T10*(1-AR10)*(1-Settings!$G$17)-I10)/(T10*(1-AR10)*(1-Settings!$G$17))),"") | P10: =IFERROR(IF(T10="","",(T10*(1-AS10)*(1-Settings!$H$17)-I10)/(T10*(1-AS10)*(1-Settings!$H$17))),"") | Q10: =IFERROR(IF(T10="","",(T10*(1-AT10)*(1-Settings!$I$68)*(1-Settings!$I$17)-I10)/(T10*(1-AT10)*(1-Settings!$I$68)*(1-Settings!$I$17))),"") | R10: =IFERROR(IF(OR(I10="",Z10>=1,Settings!$B$17>=1,AN10>=1),"",IF(MOD(ROUND(I10/(1-Z10)/(1-Settings!$B$17)/(1-AN10),0),10)=0,ROUND(I10/(1-Z10)/(1-Settings!$B$17)/(1-AN10),0)-1,IF(MOD(ROUND(I10/(1-Z10)/(1-Settings!$B$17)/(1-AN10),0),10)<=5,FLOOR(ROUND(I10/(1-Z10)/(1-Settings!$B$17)/(1-AN10),0),10)+6,FLOOR(ROUND(I10/(1-Z10)/(1-Settings!$B$17)/(1-AN10),0),10)+9))),"") | T10: =IF(S10<>"", IF(MOD(S10,10)=0,S10-1,IF(MOD(S10,10)<=5,FLOOR(S10,10)+6,FLOOR(S10,10)+9)), R10) | U10: Основний | X10: =IFERROR(IF(OR(V10="",W10="",T10=""),"", IF(T10>W10,"Дорогий",IF(T10<V10,"Дешевий","У ринку"))),"") | Z10: =CHOOSE(MATCH(IF($U10="","Основний",$U10),{"Трафіковий","Основний","Маржинальний","Сезонний","Стратегічний"},0),0.16,0.19,0.24,0.23,0.28) | AA10: =CHOOSE(MATCH(IF($U10="","Основний",$U10),{"Трафіковий","Основний","Маржинальний","Сезонний","Стратегічний"},0),0.18,0.21,0.26,0.25,0.3) | AB10: =CHOOSE(MATCH(IF($U10="","Основний",$U10),{"Трафіковий","Основний","Маржинальний","Сезонний","Стратегічний"},0),0.19,0.22,0.28,0.26,0.32) | AC10: =CHOOSE(MATCH(IF($U10="","Основний",$U10),{"Трафіковий","Основний","Маржинальний","Сезонний","Стратегічний"},0),0.17,0.2,0.25,0.24,0.28) | AD10: =CHOOSE(MATCH(IF($U10="","Основний",$U10),{"Трафіковий","Основний","Маржинальний","Сезонний","Стратегічний"},0),0.18,0.21,0.26,0.25,0.3) | AE10: =CHOOSE(MATCH(IF($U10="","Основний",$U10),{"Трафіковий","Основний","Маржинальний","Сезонний","Стратегічний"},0),0.18,0.2,0.28,0.27,0.32) | AF10: =CHOOSE(MATCH(IF($U10="","Основний",$U10),{"Трафіковий","Основний","Маржинальний","Сезонний","Стратегічний"},0),0.15,0.175,0.22,0.21,0.25) | AG10: =CHOOSE(MATCH(IF($U10="","Основний",$U10),{"Трафіковий","Основний","Маржинальний","Сезонний","Стратегічний"},0),0.13,0.16,0.21,0.2,0.25) | AH10: =CHOOSE(MATCH(IF($U10="","Основний",$U10),{"Трафіковий","Основний","Маржинальний","Сезонний","Стратегічний"},0),0.15,0.18,0.23,0.22,0.27) | AI10: =CHOOSE(MATCH(IF($U10="","Основний",$U10),{"Трафіковий","Основний","Маржинальний","Сезонний","Стратегічний"},0),0.16,0.19,0.25,0.23,0.29) | AJ10: =CHOOSE(MATCH(IF($U10="","Основний",$U10),{"Трафіковий","Основний","Маржинальний","Сезонний","Стратегічний"},0),0.14,0.17,0.22,0.21,0.25) | AK10: =CHOOSE(MATCH(IF($U10="","Основний",$U10),{"Трафіковий","Основний","Маржинальний","Сезонний","Стратегічний"},0),0.15,0.18,0.23,0.22,0.27) | AL10: =CHOOSE(MATCH(IF($U10="","Основний",$U10),{"Трафіковий","Основний","Маржинальний","Сезонний","Стратегічний"},0),0.15,0.17,0.25,0.24,0.29) | AM10: =CHOOSE(MATCH(IF($U10="","Основний",$U10),{"Трафіковий","Основний","Маржинальний","Сезонний","Стратегічний"},0),0.12,0.145,0.19,0.18,0.22) | AN10: =CHOOSE(MATCH(IF($U10="","Основний",$U10),{"Трафіковий","Основний","Маржинальний","Сезонний","Стратегічний"},0),Settings!$B$78,Settings!$B$80,Settings!$B$82,Settings!$B$84,Settings!$B$86) | AO10: =CHOOSE(MATCH(IF($U10="","Основний",$U10),{"Трафіковий","Основний","Маржинальний","Сезонний","Стратегічний"},0),Settings!$C$78,Settings!$C$80,Settings!$C$82,Settings!$C$84,Settings!$C$86) | AP10: =CHOOSE(MATCH(IF($U10="","Основний",$U10),{"Трафіковий","Основний","Маржинальний","Сезонний","Стратегічний"},0),Settings!$D$78,Settings!$D$80,Settings!$D$82,Settings!$D$84,Settings!$D$86) | AQ10: =CHOOSE(MATCH(IF($U10="","Основний",$U10),{"Трафіковий","Основний","Маржинальний","Сезонний","Стратегічний"},0),Settings!$F$78,Settings!$F$80,Settings!$F$82,Settings!$F$84,Settings!$F$86) | AR10: =CHOOSE(MATCH(IF($U10="","Основний",$U10),{"Трафіковий","Основний","Маржинальний","Сезонний","Стратегічний"},0),Settings!$G$78,Settings!$G$80,Settings!$G$82,Settings!$G$84,Settings!$G$86) | AS10: =CHOOSE(MATCH(IF($U10="","Основний",$U10),{"Трафіковий","Основний","Маржинальний","Сезонний","Стратегічний"},0),Settings!$H$78,Settings!$H$80,Settings!$H$82,Settings!$H$84,Settings!$H$86) | AT10: =CHOOSE(MATCH(IF($U10="","Основний",$U10),{"Трафіковий","Основний","Маржинальний","Сезонний","Стратегічний"},0),Settings!$I$78,Settings!$I$80,Settings!$I$82,Settings!$I$84,Settings!$I$86) | AV10: 1.35
B11: N9321 | C11: EMOS battery charger BCN-40 | D11: Зарядні пристрої для акумуляторів | E11: PC | F11: 5.105 | G11: 8504406090 | H11: 1.3 | I11: =IFERROR(F11*Settings!$B$2*H11*IF(AND(ISNUMBER(E11),E11>1),E11,1),"") | J11: =Settings!$B$66 | K11: =IFERROR(IF(T11="","",(T11*(1-AN11)*(1-Settings!$B$17)-I11)/(T11*(1-AN11)*(1-Settings!$B$17))),"") | L11: =IFERROR(IF(T11="","",(T11*(1-AO11)*(1-Settings!$C$17)-I11)/(T11*(1-AO11)*(1-Settings!$C$17))),"") | M11: =IFERROR(IF(T11="","",(T11*(1-AP11)*(1-Settings!$D$17)-I11)/(T11*(1-AP11)*(1-Settings!$D$17))),"") | N11: =IFERROR(IF(T11="","",(T11*(1-AQ11)*(1-Settings!$F$17)-I11)/(T11*(1-AQ11)*(1-Settings!$F$17))),"") | O11: =IFERROR(IF(T11="","",(T11*(1-AR11)*(1-Settings!$G$17)-I11)/(T11*(1-AR11)*(1-Settings!$G$17))),"") | P11: =IFERROR(IF(T11="","",(T11*(1-AS11)*(1-Settings!$H$17)-I11)/(T11*(1-AS11)*(1-Settings!$H$17))),"") | Q11: =IFERROR(IF(T11="","",(T11*(1-AT11)*(1-Settings!$I$68)*(1-Settings!$I$17)-I11)/(T11*(1-AT11)*(1-Settings!$I$68)*(1-Settings!$I$17))),"") | R11: =IFERROR(IF(OR(I11="",Z11>=1,Settings!$B$17>=1,AN11>=1),"",IF(MOD(ROUND(I11/(1-Z11)/(1-Settings!$B$17)/(1-AN11),0),10)=0,ROUND(I11/(1-Z11)/(1-Settings!$B$17)/(1-AN11),0)-1,IF(MOD(ROUND(I11/(1-Z11)/(1-Settings!$B$17)/(1-AN11),0),10)<=5,FLOOR(ROUND(I11/(1-Z11)/(1-Settings!$B$17)/(1-AN11),0),10)+6,FLOOR(ROUND(I11/(1-Z11)/(1-Settings!$B$17)/(1-AN11),0),10)+9))),"") | T11: =IF(S11<>"", IF(MOD(S11,10)=0,S11-1,IF(MOD(S11,10)<=5,FLOOR(S11,10)+6,FLOOR(S11,10)+9)), R11) | U11: Основний | X11: =IFERROR(IF(OR(V11="",W11="",T11=""),"", IF(T11>W11,"Дорогий",IF(T11<V11,"Дешевий","У ринку"))),"") | Z11: =CHOOSE(MATCH(IF($U11="","Основний",$U11),{"Трафіковий","Основний","Маржинальний","Сезонний","Стратегічний"},0),0.16,0.19,0.24,0.23,0.28) | AA11: =CHOOSE(MATCH(IF($U11="","Основний",$U11),{"Трафіковий","Основний","Маржинальний","Сезонний","Стратегічний"},0),0.18,0.21,0.26,0.25,0.3) | AB11: =CHOOSE(MATCH(IF($U11="","Основний",$U11),{"Трафіковий","Основний","Маржинальний","Сезонний","Стратегічний"},0),0.19,0.22,0.28,0.26,0.32) | AC11: =CHOOSE(MATCH(IF($U11="","Основний",$U11),{"Трафіковий","Основний","Маржинальний","Сезонний","Стратегічний"},0),0.17,0.2,0.25,0.24,0.28) | AD11: =CHOOSE(MATCH(IF($U11="","Основний",$U11),{"Трафіковий","Основний","Маржинальний","Сезонний","Стратегічний"},0),0.18,0.21,0.26,0.25,0.3) | AE11: =CHOOSE(MATCH(IF($U11="","Основний",$U11),{"Трафіковий","Основний","Маржинальний","Сезонний","Стратегічний"},0),0.18,0.2,0.28,0.27,0.32) | AF11: =CHOOSE(MATCH(IF($U11="","Основний",$U11),{"Трафіковий","Основний","Маржинальний","Сезонний","Стратегічний"},0),0.15,0.175,0.22,0.21,0.25) | AG11: =CHOOSE(MATCH(IF($U11="","Основний",$U11),{"Трафіковий","Основний","Маржинальний","Сезонний","Стратегічний"},0),0.13,0.16,0.21,0.2,0.25) | AH11: =CHOOSE(MATCH(IF($U11="","Основний",$U11),{"Трафіковий","Основний","Маржинальний","Сезонний","Стратегічний"},0),0.15,0.18,0.23,0.22,0.27) | AI11: =CHOOSE(MATCH(IF($U11="","Основний",$U11),{"Трафіковий","Основний","Маржинальний","Сезонний","Стратегічний"},0),0.16,0.19,0.25,0.23,0.29) | AJ11: =CHOOSE(MATCH(IF($U11="","Основний",$U11),{"Трафіковий","Основний","Маржинальний","Сезонний","Стратегічний"},0),0.14,0.17,0.22,0.21,0.25) | AK11: =CHOOSE(MATCH(IF($U11="","Основний",$U11),{"Трафіковий","Основний","Маржинальний","Сезонний","Стратегічний"},0),0.15,0.18,0.23,0.22,0.27) | AL11: =CHOOSE(MATCH(IF($U11="","Основний",$U11),{"Трафіковий","Основний","Маржинальний","Сезонний","Стратегічний"},0),0.15,0.17,0.25,0.24,0.29) | AM11: =CHOOSE(MATCH(IF($U11="","Основний",$U11),{"Трафіковий","Основний","Маржинальний","Сезонний","Стратегічний"},0),0.12,0.145,0.19,0.18,0.22) | AN11: =CHOOSE(MATCH(IF($U11="","Основний",$U11),{"Трафіковий","Основний","Маржинальний","Сезонний","Стратегічний"},0),Settings!$B$78,Settings!$B$80,Settings!$B$82,Settings!$B$84,Settings!$B$86) | AO11: =CHOOSE(MATCH(IF($U11="","Основний",$U11),{"Трафіковий","Основний","Маржинальний","Сезонний","Стратегічний"},0),Settings!$C$78,Settings!$C$80,Settings!$C$82,Settings!$C$84,Settings!$C$86) | AP11: =CHOOSE(MATCH(IF($U11="","Основний",$U11),{"Трафіковий","Основний","Маржинальний","Сезонний","Стратегічний"},0),Settings!$D$78,Settings!$D$80,Settings!$D$82,Settings!$D$84,Settings!$D$86) | AQ11: =CHOOSE(MATCH(IF($U11="","Основний",$U11),{"Трафіковий","Основний","Маржинальний","Сезонний","Стратегічний"},0),Settings!$F$78,Settings!$F$80,Settings!$F$82,Settings!$F$84,Settings!$F$86) | AR11: =CHOOSE(MATCH(IF($U11="","Основний",$U11),{"Трафіковий","Основний","Маржинальний","Сезонний","Стратегічний"},0),Settings!$G$78,Settings!$G$80,Settings!$G$82,Settings!$G$84,Settings!$G$86) | AS11: =CHOOSE(MATCH(IF($U11="","Основний",$U11),{"Трафіковий","Основний","Маржинальний","Сезонний","Стратегічний"},0),Settings!$H$78,Settings!$H$80,Settings!$H$82,Settings!$H$84,Settings!$H$86) | AT11: =CHOOSE(MATCH(IF($U11="","Основний",$U11),{"Трафіковий","Основний","Маржинальний","Сезонний","Стратегічний"},0),Settings!$I$78,Settings!$I$80,Settings!$I$82,Settings!$I$84,Settings!$I$86) | AV11: 1.35
B12: N9361 | C12: EMOS universal battery charger BCN-60U | D12: Зарядні пристрої для акумуляторів | E12: PC | F12: 9.842 | G12: 8504406090 | H12: 1.3 | I12: =IFERROR(F12*Settings!$B$2*H12*IF(AND(ISNUMBER(E12),E12>1),E12,1),"") | J12: =Settings!$B$66 | K12: =IFERROR(IF(T12="","",(T12*(1-AN12)*(1-Settings!$B$17)-I12)/(T12*(1-AN12)*(1-Settings!$B$17))),"") | L12: =IFERROR(IF(T12="","",(T12*(1-AO12)*(1-Settings!$C$17)-I12)/(T12*(1-AO12)*(1-Settings!$C$17))),"") | M12: =IFERROR(IF(T12="","",(T12*(1-AP12)*(1-Settings!$D$17)-I12)/(T12*(1-AP12)*(1-Settings!$D$17))),"") | N12: =IFERROR(IF(T12="","",(T12*(1-AQ12)*(1-Settings!$F$17)-I12)/(T12*(1-AQ12)*(1-Settings!$F$17))),"") | O12: =IFERROR(IF(T12="","",(T12*(1-AR12)*(1-Settings!$G$17)-I12)/(T12*(1-AR12)*(1-Settings!$G$17))),"") | P12: =IFERROR(IF(T12="","",(T12*(1-AS12)*(1-Settings!$H$17)-I12)/(T12*(1-AS12)*(1-Settings!$H$17))),"") | Q12: =IFERROR(IF(T12="","",(T12*(1-AT12)*(1-Settings!$I$68)*(1-Settings!$I$17)-I12)/(T12*(1-AT12)*(1-Settings!$I$68)*(1-Settings!$I$17))),"") | R12: =IFERROR(IF(OR(I12="",Z12>=1,Settings!$B$17>=1,AN12>=1),"",IF(MOD(ROUND(I12/(1-Z12)/(1-Settings!$B$17)/(1-AN12),0),10)=0,ROUND(I12/(1-Z12)/(1-Settings!$B$17)/(1-AN12),0)-1,IF(MOD(ROUND(I12/(1-Z12)/(1-Settings!$B$17)/(1-AN12),0),10)<=5,FLOOR(ROUND(I12/(1-Z12)/(1-Settings!$B$17)/(1-AN12),0),10)+6,FLOOR(ROUND(I12/(1-Z12)/(1-Settings!$B$17)/(1-AN12),0),10)+9))),"") | T12: =IF(S12<>"", IF(MOD(S12,10)=0,S12-1,IF(MOD(S12,10)<=5,FLOOR(S12,10)+6,FLOOR(S12,10)+9)), R12) | U12: Основний | X12: =IFERROR(IF(OR(V12="",W12="",T12=""),"", IF(T12>W12,"Дорогий",IF(T12<V12,"Дешевий","У ринку"))),"") | Z12: =CHOOSE(MATCH(IF($U12="","Основний",$U12),{"Трафіковий","Основний","Маржинальний","Сезонний","Стратегічний"},0),0.16,0.19,0.24,0.23,0.28) | AA12: =CHOOSE(MATCH(IF($U12="","Основний",$U12),{"Трафіковий","Основний","Маржинальний","Сезонний","Стратегічний"},0),0.18,0.21,0.26,0.25,0.3) | AB12: =CHOOSE(MATCH(IF($U12="","Основний",$U12),{"Трафіковий","Основний","Маржинальний","Сезонний","Стратегічний"},0),0.19,0.22,0.28,0.26,0.32) | AC12: =CHOOSE(MATCH(IF($U12="","Основний",$U12),{"Трафіковий","Основний","Маржинальний","Сезонний","Стратегічний"},0),0.17,0.2,0.25,0.24,0.28) | AD12: =CHOOSE(MATCH(IF($U12="","Основний",$U12),{"Трафіковий","Основний","Маржинальний","Сезонний","Стратегічний"},0),0.18,0.21,0.26,0.25,0.3) | AE12: =CHOOSE(MATCH(IF($U12="","Основний",$U12),{"Трафіковий","Основний","Маржинальний","Сезонний","Стратегічний"},0),0.18,0.2,0.28,0.27,0.32) | AF12: =CHOOSE(MATCH(IF($U12="","Основний",$U12),{"Трафіковий","Основний","Маржинальний","Сезонний","Стратегічний"},0),0.15,0.175,0.22,0.21,0.25) | AG12: =CHOOSE(MATCH(IF($U12="","Основний",$U12),{"Трафіковий","Основний","Маржинальний","Сезонний","Стратегічний"},0),0.13,0.16,0.21,0.2,0.25) | AH12: =CHOOSE(MATCH(IF($U12="","Основний",$U12),{"Трафіковий","Основний","Маржинальний","Сезонний","Стратегічний"},0),0.15,0.18,0.23,0.22,0.27) | AI12: =CHOOSE(MATCH(IF($U12="","Основний",$U12),{"Трафіковий","Основний","Маржинальний","Сезонний","Стратегічний"},0),0.16,0.19,0.25,0.23,0.29) | AJ12: =CHOOSE(MATCH(IF($U12="","Основний",$U12),{"Трафіковий","Основний","Маржинальний","Сезонний","Стратегічний"},0),0.14,0.17,0.22,0.21,0.25) | AK12: =CHOOSE(MATCH(IF($U12="","Основний",$U12),{"Трафіковий","Основний","Маржинальний","Сезонний","Стратегічний"},0),0.15,0.18,0.23,0.22,0.27) | AL12: =CHOOSE(MATCH(IF($U12="","Основний",$U12),{"Трафіковий","Основний","Маржинальний","Сезонний","Стратегічний"},0),0.15,0.17,0.25,0.24,0.29) | AM12: =CHOOSE(MATCH(IF($U12="","Основний",$U12),{"Трафіковий","Основний","Маржинальний","Сезонний","Стратегічний"},0),0.12,0.145,0.19,0.18,0.22) | AN12: =CHOOSE(MATCH(IF($U12="","Основний",$U12),{"Трафіковий","Основний","Маржинальний","Сезонний","Стратегічний"},0),Settings!$B$78,Settings!$B$80,Settings!$B$82,Settings!$B$84,Settings!$B$86) | AO12: =CHOOSE(MATCH(IF($U12="","Основний",$U12),{"Трафіковий","Основний","Маржинальний","Сезонний","Стратегічний"},0),Settings!$C$78,Settings!$C$80,Settings!$C$82,Settings!$C$84,Settings!$C$86) | AP12: =CHOOSE(MATCH(IF($U12="","Основний",$U12),{"Трафіковий","Основний","Маржинальний","Сезонний","Стратегічний"},0),Settings!$D$78,Settings!$D$80,Settings!$D$82,Settings!$D$84,Settings!$D$86) | AQ12: =CHOOSE(MATCH(IF($U12="","Основний",$U12),{"Трафіковий","Основний","Маржинальний","Сезонний","Стратегічний"},0),Settings!$F$78,Settings!$F$80,Settings!$F$82,Settings!$F$84,Settings!$F$86) | AR12: =CHOOSE(MATCH(IF($U12="","Основний",$U12),{"Трафіковий","Основний","Маржинальний","Сезонний","Стратегічний"},0),Settings!$G$78,Settings!$G$80,Settings!$G$82,Settings!$G$84,Settings!$G$86) | AS12: =CHOOSE(MATCH(IF($U12="","Основний",$U12),{"Трафіковий","Основний","Маржинальний","Сезонний","Стратегічний"},0),Settings!$H$78,Settings!$H$80,Settings!$H$82,Settings!$H$84,Settings!$H$86) | AT12: =CHOOSE(MATCH(IF($U12="","Основний",$U12),{"Трафіковий","Основний","Маржинальний","Сезонний","Стратегічний"},0),Settings!$I$78,Settings!$I$80,Settings!$I$82,Settings!$I$84,Settings!$I$86) | AV12: 1.35
B13: P2311 | C13: LED RECHARGEABLE FLASHLIGHT 300LM | D13: Ліхтарі | E13: PC | F13: 11.483 | G13: 8513100000 | H13: 1.4 | I13: =IFERROR(F13*Settings!$B$2*H13*IF(AND(ISNUMBER(E13),E13>1),E13,1),"") | J13: =Settings!$B$66 | K13: =IFERROR(IF(T13="","",(T13*(1-AN13)*(1-Settings!$B$17)-I13)/(T13*(1-AN13)*(1-Settings!$B$17))),"") | L13: =IFERROR(IF(T13="","",(T13*(1-AO13)*(1-Settings!$C$17)-I13)/(T13*(1-AO13)*(1-Settings!$C$17))),"") | M13: =IFERROR(IF(T13="","",(T13*(1-AP13)*(1-Settings!$D$17)-I13)/(T13*(1-AP13)*(1-Settings!$D$17))),"") | N13: =IFERROR(IF(T13="","",(T13*(1-AQ13)*(1-Settings!$F$17)-I13)/(T13*(1-AQ13)*(1-Settings!$F$17))),"") | O13: =IFERROR(IF(T13="","",(T13*(1-AR13)*(1-Settings!$G$17)-I13)/(T13*(1-AR13)*(1-Settings!$G$17))),"") | P13: =IFERROR(IF(T13="","",(T13*(1-AS13)*(1-Settings!$H$17)-I13)/(T13*(1-AS13)*(1-Settings!$H$17))),"") | Q13: =IFERROR(IF(T13="","",(T13*(1-AT13)*(1-Settings!$I$68)*(1-Settings!$I$17)-I13)/(T13*(1-AT13)*(1-Settings!$I$68)*(1-Settings!$I$17))),"") | R13: =IFERROR(IF(OR(I13="",Z13>=1,Settings!$B$17>=1,AN13>=1),"",IF(MOD(ROUND(I13/(1-Z13)/(1-Settings!$B$17)/(1-AN13),0),10)=0,ROUND(I13/(1-Z13)/(1-Settings!$B$17)/(1-AN13),0)-1,IF(MOD(ROUND(I13/(1-Z13)/(1-Settings!$B$17)/(1-AN13),0),10)<=5,FLOOR(ROUND(I13/(1-Z13)/(1-Settings!$B$17)/(1-AN13),0),10)+6,FLOOR(ROUND(I13/(1-Z13)/(1-Settings!$B$17)/(1-AN13),0),10)+9))),"") | S13: 1539 | T13: =IF(S13<>"", IF(MOD(S13,10)=0,S13-1,IF(MOD(S13,10)<=5,FLOOR(S13,10)+6,FLOOR(S13,10)+9)), R13) | U13: Основний | X13: =IFERROR(IF(OR(V13="",W13="",T13=""),"", IF(T13>W13,"Дорогий",IF(T13<V13,"Дешевий","У ринку"))),"") | Z13: =CHOOSE(MATCH(IF($U13="","Основний",$U13),{"Трафіковий","Основний","Маржинальний","Сезонний","Стратегічний"},0),0.16,0.19,0.24,0.23,0.28) | AA13: =CHOOSE(MATCH(IF($U13="","Основний",$U13),{"Трафіковий","Основний","Маржинальний","Сезонний","Стратегічний"},0),0.18,0.21,0.26,0.25,0.3) | AB13: =CHOOSE(MATCH(IF($U13="","Основний",$U13),{"Трафіковий","Основний","Маржинальний","Сезонний","Стратегічний"},0),0.19,0.22,0.28,0.26,0.32) | AC13: =CHOOSE(MATCH(IF($U13="","Основний",$U13),{"Трафіковий","Основний","Маржинальний","Сезонний","Стратегічний"},0),0.17,0.2,0.25,0.24,0.28) | AD13: =CHOOSE(MATCH(IF($U13="","Основний",$U13),{"Трафіковий","Основний","Маржинальний","Сезонний","Стратегічний"},0),0.18,0.21,0.26,0.25,0.3) | AE13: =CHOOSE(MATCH(IF($U13="","Основний",$U13),{"Трафіковий","Основний","Маржинальний","Сезонний","Стратегічний"},0),0.18,0.2,0.28,0.27,0.32) | AF13: =CHOOSE(MATCH(IF($U13="","Основний",$U13),{"Трафіковий","Основний","Маржинальний","Сезонний","Стратегічний"},0),0.15,0.175,0.22,0.21,0.25) | AG13: =CHOOSE(MATCH(IF($U13="","Основний",$U13),{"Трафіковий","Основний","Маржинальний","Сезонний","Стратегічний"},0),0.13,0.16,0.21,0.2,0.25) | AH13: =CHOOSE(MATCH(IF($U13="","Основний",$U13),{"Трафіковий","Основний","Маржинальний","Сезонний","Стратегічний"},0),0.15,0.18,0.23,0.22,0.27) | AI13: =CHOOSE(MATCH(IF($U13="","Основний",$U13),{"Трафіковий","Основний","Маржинальний","Сезонний","Стратегічний"},0),0.16,0.19,0.25,0.23,0.29) | AJ13: =CHOOSE(MATCH(IF($U13="","Основний",$U13),{"Трафіковий","Основний","Маржинальний","Сезонний","Стратегічний"},0),0.14,0.17,0.22,0.21,0.25) | AK13: =CHOOSE(MATCH(IF($U13="","Основний",$U13),{"Трафіковий","Основний","Маржинальний","Сезонний","Стратегічний"},0),0.15,0.18,0.23,0.22,0.27) | AL13: =CHOOSE(MATCH(IF($U13="","Основний",$U13),{"Трафіковий","Основний","Маржинальний","Сезонний","Стратегічний"},0),0.15,0.17,0.25,0.24,0.29) | AM13: =CHOOSE(MATCH(IF($U13="","Основний",$U13),{"Трафіковий","Основний","Маржинальний","Сезонний","Стратегічний"},0),0.12,0.145,0.19,0.18,0.22) | AN13: =CHOOSE(MATCH(IF($U13="","Основний",$U13),{"Трафіковий","Основний","Маржинальний","Сезонний","Стратегічний"},0),Settings!$B$78,Settings!$B$80,Settings!$B$82,Settings!$B$84,Settings!$B$86) | AO13: =CHOOSE(MATCH(IF($U13="","Основний",$U13),{"Трафіковий","Основний","Маржинальний","Сезонний","Стратегічний"},0),Settings!$C$78,Settings!$C$80,Settings!$C$82,Settings!$C$84,Settings!$C$86) | AP13: =CHOOSE(MATCH(IF($U13="","Основний",$U13),{"Трафіковий","Основний","Маржинальний","Сезонний","Стратегічний"},0),Settings!$D$78,Settings!$D$80,Settings!$D$82,Settings!$D$84,Settings!$D$86) | AQ13: =CHOOSE(MATCH(IF($U13="","Основний",$U13),{"Трафіковий","Основний","Маржинальний","Сезонний","Стратегічний"},0),Settings!$F$78,Settings!$F$80,Settings!$F$82,Settings!$F$84,Settings!$F$86) | AR13: =CHOOSE(MATCH(IF($U13="","Основний",$U13),{"Трафіковий","Основний","Маржинальний","Сезонний","Стратегічний"},0),Settings!$G$78,Settings!$G$80,Settings!$G$82,Settings!$G$84,Settings!$G$86) | AS13: =CHOOSE(MATCH(IF($U13="","Основний",$U13),{"Трафіковий","Основний","Маржинальний","Сезонний","Стратегічний"},0),Settings!$H$78,Settings!$H$80,Settings!$H$82,Settings!$H$84,Settings!$H$86) | AT13: =CHOOSE(MATCH(IF($U13="","Основний",$U13),{"Трафіковий","Основний","Маржинальний","Сезонний","Стратегічний"},0),Settings!$I$78,Settings!$I$80,Settings!$I$82,Settings!$I$84,Settings!$I$86) | AV13: 1.35
A14: SELL OUT | B14: P2313 | C14: LED RECHARGEABLE CAMPING FLASHLIGHT 350LM | D14: Ліхтарі | E14: PC | F14: 12.896 | G14: 8513100000 | H14: 1.4 | I14: =IFERROR(F14*Settings!$B$2*H14*IF(AND(ISNUMBER(E14),E14>1),E14,1),"") | J14: =Settings!$B$66 | K14: =IFERROR(IF(T14="","",(T14*(1-AN14)*(1-Settings!$B$17)-I14)/(T14*(1-AN14)*(1-Settings!$B$17))),"") | L14: =IFERROR(IF(T14="","",(T14*(1-AO14)*(1-Settings!$C$17)-I14)/(T14*(1-AO14)*(1-Settings!$C$17))),"") | M14: =IFERROR(IF(T14="","",(T14*(1-AP14)*(1-Settings!$D$17)-I14)/(T14*(1-AP14)*(1-Settings!$D$17))),"") | N14: =IFERROR(IF(T14="","",(T14*(1-AQ14)*(1-Settings!$F$17)-I14)/(T14*(1-AQ14)*(1-Settings!$F$17))),"") | O14: =IFERROR(IF(T14="","",(T14*(1-AR14)*(1-Settings!$G$17)-I14)/(T14*(1-AR14)*(1-Settings!$G$17))),"") | P14: =IFERROR(IF(T14="","",(T14*(1-AS14)*(1-Settings!$H$17)-I14)/(T14*(1-AS14)*(1-Settings!$H$17))),"") | Q14: =IFERROR(IF(T14="","",(T14*(1-AT14)*(1-Settings!$I$68)*(1-Settings!$I$17)-I14)/(T14*(1-AT14)*(1-Settings!$I$68)*(1-Settings!$I$17))),"") | R14: =IFERROR(IF(OR(I14="",Z14>=1,Settings!$B$17>=1,AN14>=1),"",IF(MOD(ROUND(I14/(1-Z14)/(1-Settings!$B$17)/(1-AN14),0),10)=0,ROUND(I14/(1-Z14)/(1-Settings!$B$17)/(1-AN14),0)-1,IF(MOD(ROUND(I14/(1-Z14)/(1-Settings!$B$17)/(1-AN14),0),10)<=5,FLOOR(ROUND(I14/(1-Z14)/(1-Settings!$B$17)/(1-AN14),0),10)+6,FLOOR(ROUND(I14/(1-Z14)/(1-Settings!$B$17)/(1-AN14),0),10)+9))),"") | S14: 1670 | T14: =IF(S14<>"", IF(MOD(S14,10)=0,S14-1,IF(MOD(S14,10)<=5,FLOOR(S14,10)+6,FLOOR(S14,10)+9)), R14) | U14: Основний | X14: =IFERROR(IF(OR(V14="",W14="",T14=""),"", IF(T14>W14,"Дорогий",IF(T14<V14,"Дешевий","У ринку"))),"") | Z14: =CHOOSE(MATCH(IF($U14="","Основний",$U14),{"Трафіковий","Основний","Маржинальний","Сезонний","Стратегічний"},0),0.16,0.19,0.24,0.23,0.28) | AA14: =CHOOSE(MATCH(IF($U14="","Основний",$U14),{"Трафіковий","Основний","Маржинальний","Сезонний","Стратегічний"},0),0.18,0.21,0.26,0.25,0.3) | AB14: =CHOOSE(MATCH(IF($U14="","Основний",$U14),{"Трафіковий","Основний","Маржинальний","Сезонний","Стратегічний"},0),0.19,0.22,0.28,0.26,0.32) | AC14: =CHOOSE(MATCH(IF($U14="","Основний",$U14),{"Трафіковий","Основний","Маржинальний","Сезонний","Стратегічний"},0),0.17,0.2,0.25,0.24,0.28) | AD14: =CHOOSE(MATCH(IF($U14="","Основний",$U14),{"Трафіковий","Основний","Маржинальний","Сезонний","Стратегічний"},0),0.18,0.21,0.26,0.25,0.3) | AE14: =CHOOSE(MATCH(IF($U14="","Основний",$U14),{"Трафіковий","Основний","Маржинальний","Сезонний","Стратегічний"},0),0.18,0.2,0.28,0.27,0.32) | AF14: =CHOOSE(MATCH(IF($U14="","Основний",$U14),{"Трафіковий","Основний","Маржинальний","Сезонний","Стратегічний"},0),0.15,0.175,0.22,0.21,0.25) | AG14: =CHOOSE(MATCH(IF($U14="","Основний",$U14),{"Трафіковий","Основний","Маржинальний","Сезонний","Стратегічний"},0),0.13,0.16,0.21,0.2,0.25) | AH14: =CHOOSE(MATCH(IF($U14="","Основний",$U14),{"Трафіковий","Основний","Маржинальний","Сезонний","Стратегічний"},0),0.15,0.18,0.23,0.22,0.27) | AI14: =CHOOSE(MATCH(IF($U14="","Основний",$U14),{"Трафіковий","Основний","Маржинальний","Сезонний","Стратегічний"},0),0.16,0.19,0.25,0.23,0.29) | AJ14: =CHOOSE(MATCH(IF($U14="","Основний",$U14),{"Трафіковий","Основний","Маржинальний","Сезонний","Стратегічний"},0),0.14,0.17,0.22,0.21,0.25) | AK14: =CHOOSE(MATCH(IF($U14="","Основний",$U14),{"Трафіковий","Основний","Маржинальний","Сезонний","Стратегічний"},0),0.15,0.18,0.23,0.22,0.27) | AL14: =CHOOSE(MATCH(IF($U14="","Основний",$U14),{"Трафіковий","Основний","Маржинальний","Сезонний","Стратегічний"},0),0.15,0.17,0.25,0.24,0.29) | AM14: =CHOOSE(MATCH(IF($U14="","Основний",$U14),{"Трафіковий","Основний","Маржинальний","Сезонний","Стратегічний"},0),0.12,0.145,0.19,0.18,0.22) | AN14: =CHOOSE(MATCH(IF($U14="","Основний",$U14),{"Трафіковий","Основний","Маржинальний","Сезонний","Стратегічний"},0),Settings!$B$78,Settings!$B$80,Settings!$B$82,Settings!$B$84,Settings!$B$86) | AO14: =CHOOSE(MATCH(IF($U14="","Основний",$U14),{"Трафіковий","Основний","Маржинальний","Сезонний","Стратегічний"},0),Settings!$C$78,Settings!$C$80,Settings!$C$82,Settings!$C$84,Settings!$C$86) | AP14: =CHOOSE(MATCH(IF($U14="","Основний",$U14),{"Трафіковий","Основний","Маржинальний","Сезонний","Стратегічний"},0),Settings!$D$78,Settings!$D$80,Settings!$D$82,Settings!$D$84,Settings!$D$86) | AQ14: =CHOOSE(MATCH(IF($U14="","Основний",$U14),{"Трафіковий","Основний","Маржинальний","Сезонний","Стратегічний"},0),Settings!$F$78,Settings!$F$80,Settings!$F$82,Settings!$F$84,Settings!$F$86) | AR14: =CHOOSE(MATCH(IF($U14="","Основний",$U14),{"Трафіковий","Основний","Маржинальний","Сезонний","Стратегічний"},0),Settings!$G$78,Settings!$G$80,Settings!$G$82,Settings!$G$84,Settings!$G$86) | AS14: =CHOOSE(MATCH(IF($U14="","Основний",$U14),{"Трафіковий","Основний","Маржинальний","Сезонний","Стратегічний"},0),Settings!$H$78,Settings!$H$80,Settings!$H$82,Settings!$H$84,Settings!$H$86) | AT14: =CHOOSE(MATCH(IF($U14="","Основний",$U14),{"Трафіковий","Основний","Маржинальний","Сезонний","Стратегічний"},0),Settings!$I$78,Settings!$I$80,Settings!$I$82,Settings!$I$84,Settings!$I$86) | AV14: 1.35
B15: P2314 | C15: SMD LED+COB LED RECHARGEABLE FLASHLIGHT 210lm | D15: Ліхтарі | E15: PC | F15: 6.553 | G15: 8513100000 | H15: 1.4 | I15: =IFERROR(F15*Settings!$B$2*H15*IF(AND(ISNUMBER(E15),E15>1),E15,1),"") | J15: =Settings!$B$66 | K15: =IFERROR(IF(T15="","",(T15*(1-AN15)*(1-Settings!$B$17)-I15)/(T15*(1-AN15)*(1-Settings!$B$17))),"") | L15: =IFERROR(IF(T15="","",(T15*(1-AO15)*(1-Settings!$C$17)-I15)/(T15*(1-AO15)*(1-Settings!$C$17))),"") | M15: =IFERROR(IF(T15="","",(T15*(1-AP15)*(1-Settings!$D$17)-I15)/(T15*(1-AP15)*(1-Settings!$D$17))),"") | N15: =IFERROR(IF(T15="","",(T15*(1-AQ15)*(1-Settings!$F$17)-I15)/(T15*(1-AQ15)*(1-Settings!$F$17))),"") | O15: =IFERROR(IF(T15="","",(T15*(1-AR15)*(1-Settings!$G$17)-I15)/(T15*(1-AR15)*(1-Settings!$G$17))),"") | P15: =IFERROR(IF(T15="","",(T15*(1-AS15)*(1-Settings!$H$17)-I15)/(T15*(1-AS15)*(1-Settings!$H$17))),"") | Q15: =IFERROR(IF(T15="","",(T15*(1-AT15)*(1-Settings!$I$68)*(1-Settings!$I$17)-I15)/(T15*(1-AT15)*(1-Settings!$I$68)*(1-Settings!$I$17))),"") | R15: =IFERROR(IF(OR(I15="",Z15>=1,Settings!$B$17>=1,AN15>=1),"",IF(MOD(ROUND(I15/(1-Z15)/(1-Settings!$B$17)/(1-AN15),0),10)=0,ROUND(I15/(1-Z15)/(1-Settings!$B$17)/(1-AN15),0)-1,IF(MOD(ROUND(I15/(1-Z15)/(1-Settings!$B$17)/(1-AN15),0),10)<=5,FLOOR(ROUND(I15/(1-Z15)/(1-Settings!$B$17)/(1-AN15),0),10)+6,FLOOR(ROUND(I15/(1-Z15)/(1-Settings!$B$17)/(1-AN15),0),10)+9))),"") | S15: 850 | T15: =IF(S15<>"", IF(MOD(S15,10)=0,S15-1,IF(MOD(S15,10)<=5,FLOOR(S15,10)+6,FLOOR(S15,10)+9)), R15) | U15: Основний | X15: =IFERROR(IF(OR(V15="",W15="",T15=""),"", IF(T15>W15,"Дорогий",IF(T15<V15,"Дешевий","У ринку"))),"") | Z15: =CHOOSE(MATCH(IF($U15="","Основний",$U15),{"Трафіковий","Основний","Маржинальний","Сезонний","Стратегічний"},0),0.16,0.19,0.24,0.23,0.28) | AA15: =CHOOSE(MATCH(IF($U15="","Основний",$U15),{"Трафіковий","Основний","Маржинальний","Сезонний","Стратегічний"},0),0.18,0.21,0.26,0.25,0.3) | AB15: =CHOOSE(MATCH(IF($U15="","Основний",$U15),{"Трафіковий","Основний","Маржинальний","Сезонний","Стратегічний"},0),0.19,0.22,0.28,0.26,0.32) | AC15: =CHOOSE(MATCH(IF($U15="","Основний",$U15),{"Трафіковий","Основний","Маржинальний","Сезонний","Стратегічний"},0),0.17,0.2,0.25,0.24,0.28) | AD15: =CHOOSE(MATCH(IF($U15="","Основний",$U15),{"Трафіковий","Основний","Маржинальний","Сезонний","Стратегічний"},0),0.18,0.21,0.26,0.25,0.3) | AE15: =CHOOSE(MATCH(IF($U15="","Основний",$U15),{"Трафіковий","Основний","Маржинальний","Сезонний","Стратегічний"},0),0.18,0.2,0.28,0.27,0.32) | AF15: =CHOOSE(MATCH(IF($U15="","Основний",$U15),{"Трафіковий","Основний","Маржинальний","Сезонний","Стратегічний"},0),0.15,0.175,0.22,0.21,0.25) | AG15: =CHOOSE(MATCH(IF($U15="","Основний",$U15),{"Трафіковий","Основний","Маржинальний","Сезонний","Стратегічний"},0),0.13,0.16,0.21,0.2,0.25) | AH15: =CHOOSE(MATCH(IF($U15="","Основний",$U15),{"Трафіковий","Основний","Маржинальний","Сезонний","Стратегічний"},0),0.15,0.18,0.23,0.22,0.27) | AI15: =CHOOSE(MATCH(IF($U15="","Основний",$U15),{"Трафіковий","Основний","Маржинальний","Сезонний","Стратегічний"},0),0.16,0.19,0.25,0.23,0.29) | AJ15: =CHOOSE(MATCH(IF($U15="","Основний",$U15),{"Трафіковий","Основний","Маржинальний","Сезонний","Стратегічний"},0),0.14,0.17,0.22,0.21,0.25) | AK15: =CHOOSE(MATCH(IF($U15="","Основний",$U15),{"Трафіковий","Основний","Маржинальний","Сезонний","Стратегічний"},0),0.15,0.18,0.23,0.22,0.27) | AL15: =CHOOSE(MATCH(IF($U15="","Основний",$U15),{"Трафіковий","Основний","Маржинальний","Сезонний","Стратегічний"},0),0.15,0.17,0.25,0.24,0.29) | AM15: =CHOOSE(MATCH(IF($U15="","Основний",$U15),{"Трафіковий","Основний","Маржинальний","Сезонний","Стратегічний"},0),0.12,0.145,0.19,0.18,0.22) | AN15: =CHOOSE(MATCH(IF($U15="","Основний",$U15),{"Трафіковий","Основний","Маржинальний","Сезонний","Стратегічний"},0),Settings!$B$78,Settings!$B$80,Settings!$B$82,Settings!$B$84,Settings!$B$86) | AO15: =CHOOSE(MATCH(IF($U15="","Основний",$U15),{"Трафіковий","Основний","Маржинальний","Сезонний","Стратегічний"},0),Settings!$C$78,Settings!$C$80,Settings!$C$82,Settings!$C$84,Settings!$C$86) | AP15: =CHOOSE(MATCH(IF($U15="","Основний",$U15),{"Трафіковий","Основний","Маржинальний","Сезонний","Стратегічний"},0),Settings!$D$78,Settings!$D$80,Settings!$D$82,Settings!$D$84,Settings!$D$86) | AQ15: =CHOOSE(MATCH(IF($U15="","Основний",$U15),{"Трафіковий","Основний","Маржинальний","Сезонний","Стратегічний"},0),Settings!$F$78,Settings!$F$80,Settings!$F$82,Settings!$F$84,Settings!$F$86) | AR15: =CHOOSE(MATCH(IF($U15="","Основний",$U15),{"Трафіковий","Основний","Маржинальний","Сезонний","Стратегічний"},0),Settings!$G$78,Settings!$G$80,Settings!$G$82,Settings!$G$84,Settings!$G$86) | AS15: =CHOOSE(MATCH(IF($U15="","Основний",$U15),{"Трафіковий","Основний","Маржинальний","Сезонний","Стратегічний"},0),Settings!$H$78,Settings!$H$80,Settings!$H$82,Settings!$H$84,Settings!$H$86) | AT15: =CHOOSE(MATCH(IF($U15="","Основний",$U15),{"Трафіковий","Основний","Маржинальний","Сезонний","Стратегічний"},0),Settings!$I$78,Settings!$I$80,Settings!$I$82,Settings!$I$84,Settings!$I$86) | AV15: 1.35
B16: P2315 | C16: LED+COB LED RECH. FLASHLIGHT 700 LM 3 600 mAh | D16: Ліхтарі | E16: PC | F16: 13.87 | G16: 8513100000 | H16: 1.4 | I16: =IFERROR(F16*Settings!$B$2*H16*IF(AND(ISNUMBER(E16),E16>1),E16,1),"") | J16: =Settings!$B$66 | K16: =IFERROR(IF(T16="","",(T16*(1-AN16)*(1-Settings!$B$17)-I16)/(T16*(1-AN16)*(1-Settings!$B$17))),"") | L16: =IFERROR(IF(T16="","",(T16*(1-AO16)*(1-Settings!$C$17)-I16)/(T16*(1-AO16)*(1-Settings!$C$17))),"") | M16: =IFERROR(IF(T16="","",(T16*(1-AP16)*(1-Settings!$D$17)-I16)/(T16*(1-AP16)*(1-Settings!$D$17))),"") | N16: =IFERROR(IF(T16="","",(T16*(1-AQ16)*(1-Settings!$F$17)-I16)/(T16*(1-AQ16)*(1-Settings!$F$17))),"") | O16: =IFERROR(IF(T16="","",(T16*(1-AR16)*(1-Settings!$G$17)-I16)/(T16*(1-AR16)*(1-Settings!$G$17))),"") | P16: =IFERROR(IF(T16="","",(T16*(1-AS16)*(1-Settings!$H$17)-I16)/(T16*(1-AS16)*(1-Settings!$H$17))),"") | Q16: =IFERROR(IF(T16="","",(T16*(1-AT16)*(1-Settings!$I$68)*(1-Settings!$I$17)-I16)/(T16*(1-AT16)*(1-Settings!$I$68)*(1-Settings!$I$17))),"") | R16: =IFERROR(IF(OR(I16="",Z16>=1,Settings!$B$17>=1,AN16>=1),"",IF(MOD(ROUND(I16/(1-Z16)/(1-Settings!$B$17)/(1-AN16),0),10)=0,ROUND(I16/(1-Z16)/(1-Settings!$B$17)/(1-AN16),0)-1,IF(MOD(ROUND(I16/(1-Z16)/(1-Settings!$B$17)/(1-AN16),0),10)<=5,FLOOR(ROUND(I16/(1-Z16)/(1-Settings!$B$17)/(1-AN16),0),10)+6,FLOOR(ROUND(I16/(1-Z16)/(1-Settings!$B$17)/(1-AN16),0),10)+9))),"") | S16: 1889 | T16: =IF(S16<>"", IF(MOD(S16,10)=0,S16-1,IF(MOD(S16,10)<=5,FLOOR(S16,10)+6,FLOOR(S16,10)+9)), R16) | U16: Основний | X16: =IFERROR(IF(OR(V16="",W16="",T16=""),"", IF(T16>W16,"Дорогий",IF(T16<V16,"Дешевий","У ринку"))),"") | Z16: =CHOOSE(MATCH(IF($U16="","Основний",$U16),{"Трафіковий","Основний","Маржинальний","Сезонний","Стратегічний"},0),0.16,0.19,0.24,0.23,0.28) | AA16: =CHOOSE(MATCH(IF($U16="","Основний",$U16),{"Трафіковий","Основний","Маржинальний","Сезонний","Стратегічний"},0),0.18,0.21,0.26,0.25,0.3) | AB16: =CHOOSE(MATCH(IF($U16="","Основний",$U16),{"Трафіковий","Основний","Маржинальний","Сезонний","Стратегічний"},0),0.19,0.22,0.28,0.26,0.32) | AC16: =CHOOSE(MATCH(IF($U16="","Основний",$U16),{"Трафіковий","Основний","Маржинальний","Сезонний","Стратегічний"},0),0.17,0.2,0.25,0.24,0.28) | AD16: =CHOOSE(MATCH(IF($U16="","Основний",$U16),{"Трафіковий","Основний","Маржинальний","Сезонний","Стратегічний"},0),0.18,0.21,0.26,0.25,0.3) | AE16: =CHOOSE(MATCH(IF($U16="","Основний",$U16),{"Трафіковий","Основний","Маржинальний","Сезонний","Стратегічний"},0),0.18,0.2,0.28,0.27,0.32) | AF16: =CHOOSE(MATCH(IF($U16="","Основний",$U16),{"Трафіковий","Основний","Маржинальний","Сезонний","Стратегічний"},0),0.15,0.175,0.22,0.21,0.25) | AG16: =CHOOSE(MATCH(IF($U16="","Основний",$U16),{"Трафіковий","Основний","Маржинальний","Сезонний","Стратегічний"},0),0.13,0.16,0.21,0.2,0.25) | AH16: =CHOOSE(MATCH(IF($U16="","Основний",$U16),{"Трафіковий","Основний","Маржинальний","Сезонний","Стратегічний"},0),0.15,0.18,0.23,0.22,0.27) | AI16: =CHOOSE(MATCH(IF($U16="","Основний",$U16),{"Трафіковий","Основний","Маржинальний","Сезонний","Стратегічний"},0),0.16,0.19,0.25,0.23,0.29) | AJ16: =CHOOSE(MATCH(IF($U16="","Основний",$U16),{"Трафіковий","Основний","Маржинальний","Сезонний","Стратегічний"},0),0.14,0.17,0.22,0.21,0.25) | AK16: =CHOOSE(MATCH(IF($U16="","Основний",$U16),{"Трафіковий","Основний","Маржинальний","Сезонний","Стратегічний"},0),0.15,0.18,0.23,0.22,0.27) | AL16: =CHOOSE(MATCH(IF($U16="","Основний",$U16),{"Трафіковий","Основний","Маржинальний","Сезонний","Стратегічний"},0),0.15,0.17,0.25,0.24,0.29) | AM16: =CHOOSE(MATCH(IF($U16="","Основний",$U16),{"Трафіковий","Основний","Маржинальний","Сезонний","Стратегічний"},0),0.12,0.145,0.19,0.18,0.22) | AN16: =CHOOSE(MATCH(IF($U16="","Основний",$U16),{"Трафіковий","Основний","Маржинальний","Сезонний","Стратегічний"},0),Settings!$B$78,Settings!$B$80,Settings!$B$82,Settings!$B$84,Settings!$B$86) | AO16: =CHOOSE(MATCH(IF($U16="","Основний",$U16),{"Трафіковий","Основний","Маржинальний","Сезонний","Стратегічний"},0),Settings!$C$78,Settings!$C$80,Settings!$C$82,Settings!$C$84,Settings!$C$86) | AP16: =CHOOSE(MATCH(IF($U16="","Основний",$U16),{"Трафіковий","Основний","Маржинальний","Сезонний","Стратегічний"},0),Settings!$D$78,Settings!$D$80,Settings!$D$82,Settings!$D$84,Settings!$D$86) | AQ16: =CHOOSE(MATCH(IF($U16="","Основний",$U16),{"Трафіковий","Основний","Маржинальний","Сезонний","Стратегічний"},0),Settings!$F$78,Settings!$F$80,Settings!$F$82,Settings!$F$84,Settings!$F$86) | AR16: =CHOOSE(MATCH(IF($U16="","Основний",$U16),{"Трафіковий","Основний","Маржинальний","Сезонний","Стратегічний"},0),Settings!$G$78,Settings!$G$80,Settings!$G$82,Settings!$G$84,Settings!$G$86) | AS16: =CHOOSE(MATCH(IF($U16="","Основний",$U16),{"Трафіковий","Основний","Маржинальний","Сезонний","Стратегічний"},0),Settings!$H$78,Settings!$H$80,Settings!$H$82,Settings!$H$84,Settings!$H$86) | AT16: =CHOOSE(MATCH(IF($U16="","Основний",$U16),{"Трафіковий","Основний","Маржинальний","Сезонний","Стратегічний"},0),Settings!$I$78,Settings!$I$80,Settings!$I$82,Settings!$I$84,Settings!$I$86) | AV16: 1.35
B17: P2316 | C17: LED RECHARGEABLE FLASHLIGHT 850LM | D17: Ліхтарі | E17: PC | F17: 17.101 | G17: 8513100000 | H17: 1.4 | I17: =IFERROR(F17*Settings!$B$2*H17*IF(AND(ISNUMBER(E17),E17>1),E17,1),"") | J17: =Settings!$B$66 | K17: =IFERROR(IF(T17="","",(T17*(1-AN17)*(1-Settings!$B$17)-I17)/(T17*(1-AN17)*(1-Settings!$B$17))),"") | L17: =IFERROR(IF(T17="","",(T17*(1-AO17)*(1-Settings!$C$17)-I17)/(T17*(1-AO17)*(1-Settings!$C$17))),"") | M17: =IFERROR(IF(T17="","",(T17*(1-AP17)*(1-Settings!$D$17)-I17)/(T17*(1-AP17)*(1-Settings!$D$17))),"") | N17: =IFERROR(IF(T17="","",(T17*(1-AQ17)*(1-Settings!$F$17)-I17)/(T17*(1-AQ17)*(1-Settings!$F$17))),"") | O17: =IFERROR(IF(T17="","",(T17*(1-AR17)*(1-Settings!$G$17)-I17)/(T17*(1-AR17)*(1-Settings!$G$17))),"") | P17: =IFERROR(IF(T17="","",(T17*(1-AS17)*(1-Settings!$H$17)-I17)/(T17*(1-AS17)*(1-Settings!$H$17))),"") | Q17: =IFERROR(IF(T17="","",(T17*(1-AT17)*(1-Settings!$I$68)*(1-Settings!$I$17)-I17)/(T17*(1-AT17)*(1-Settings!$I$68)*(1-Settings!$I$17))),"") | R17: =IFERROR(IF(OR(I17="",Z17>=1,Settings!$B$17>=1,AN17>=1),"",IF(MOD(ROUND(I17/(1-Z17)/(1-Settings!$B$17)/(1-AN17),0),10)=0,ROUND(I17/(1-Z17)/(1-Settings!$B$17)/(1-AN17),0)-1,IF(MOD(ROUND(I17/(1-Z17)/(1-Settings!$B$17)/(1-AN17),0),10)<=5,FLOOR(ROUND(I17/(1-Z17)/(1-Settings!$B$17)/(1-AN17),0),10)+6,FLOOR(ROUND(I17/(1-Z17)/(1-Settings!$B$17)/(1-AN17),0),10)+9))),"") | S17: 2330 | T17: =IF(S17<>"", IF(MOD(S17,10)=0,S17-1,IF(MOD(S17,10)<=5,FLOOR(S17,10)+6,FLOOR(S17,10)+9)), R17) | U17: Основний | X17: =IFERROR(IF(OR(V17="",W17="",T17=""),"", IF(T17>W17,"Дорогий",IF(T17<V17,"Дешевий","У ринку"))),"") | Z17: =CHOOSE(MATCH(IF($U17="","Основний",$U17),{"Трафіковий","Основний","Маржинальний","Сезонний","Стратегічний"},0),0.16,0.19,0.24,0.23,0.28) | AA17: =CHOOSE(MATCH(IF($U17="","Основний",$U17),{"Трафіковий","Основний","Маржинальний","Сезонний","Стратегічний"},0),0.18,0.21,0.26,0.25,0.3) | AB17: =CHOOSE(MATCH(IF($U17="","Основний",$U17),{"Трафіковий","Основний","Маржинальний","Сезонний","Стратегічний"},0),0.19,0.22,0.28,0.26,0.32) | AC17: =CHOOSE(MATCH(IF($U17="","Основний",$U17),{"Трафіковий","Основний","Маржинальний","Сезонний","Стратегічний"},0),0.17,0.2,0.25,0.24,0.28) | AD17: =CHOOSE(MATCH(IF($U17="","Основний",$U17),{"Трафіковий","Основний","Маржинальний","Сезонний","Стратегічний"},0),0.18,0.21,0.26,0.25,0.3) | AE17: =CHOOSE(MATCH(IF($U17="","Основний",$U17),{"Трафіковий","Основний","Маржинальний","Сезонний","Стратегічний"},0),0.18,0.2,0.28,0.27,0.32) | AF17: =CHOOSE(MATCH(IF($U17="","Основний",$U17),{"Трафіковий","Основний","Маржинальний","Сезонний","Стратегічний"},0),0.15,0.175,0.22,0.21,0.25) | AG17: =CHOOSE(MATCH(IF($U17="","Основний",$U17),{"Трафіковий","Основний","Маржинальний","Сезонний","Стратегічний"},0),0.13,0.16,0.21,0.2,0.25) | AH17: =CHOOSE(MATCH(IF($U17="","Основний",$U17),{"Трафіковий","Основний","Маржинальний","Сезонний","Стратегічний"},0),0.15,0.18,0.23,0.22,0.27) | AI17: =CHOOSE(MATCH(IF($U17="","Основний",$U17),{"Трафіковий","Основний","Маржинальний","Сезонний","Стратегічний"},0),0.16,0.19,0.25,0.23,0.29) | AJ17: =CHOOSE(MATCH(IF($U17="","Основний",$U17),{"Трафіковий","Основний","Маржинальний","Сезонний","Стратегічний"},0),0.14,0.17,0.22,0.21,0.25) | AK17: =CHOOSE(MATCH(IF($U17="","Основний",$U17),{"Трафіковий","Основний","Маржинальний","Сезонний","Стратегічний"},0),0.15,0.18,0.23,0.22,0.27) | AL17: =CHOOSE(MATCH(IF($U17="","Основний",$U17),{"Трафіковий","Основний","Маржинальний","Сезонний","Стратегічний"},0),0.15,0.17,0.25,0.24,0.29) | AM17: =CHOOSE(MATCH(IF($U17="","Основний",$U17),{"Трафіковий","Основний","Маржинальний","Сезонний","Стратегічний"},0),0.12,0.145,0.19,0.18,0.22) | AN17: =CHOOSE(MATCH(IF($U17="","Основний",$U17),{"Трафіковий","Основний","Маржинальний","Сезонний","Стратегічний"},0),Settings!$B$78,Settings!$B$80,Settings!$B$82,Settings!$B$84,Settings!$B$86) | AO17: =CHOOSE(MATCH(IF($U17="","Основний",$U17),{"Трафіковий","Основний","Маржинальний","Сезонний","Стратегічний"},0),Settings!$C$78,Settings!$C$80,Settings!$C$82,Settings!$C$84,Settings!$C$86) | AP17: =CHOOSE(MATCH(IF($U17="","Основний",$U17),{"Трафіковий","Основний","Маржинальний","Сезонний","Стратегічний"},0),Settings!$D$78,Settings!$D$80,Settings!$D$82,Settings!$D$84,Settings!$D$86) | AQ17: =CHOOSE(MATCH(IF($U17="","Основний",$U17),{"Трафіковий","Основний","Маржинальний","Сезонний","Стратегічний"},0),Settings!$F$78,Settings!$F$80,Settings!$F$82,Settings!$F$84,Settings!$F$86) | AR17: =CHOOSE(MATCH(IF($U17="","Основний",$U17),{"Трафіковий","Основний","Маржинальний","Сезонний","Стратегічний"},0),Settings!$G$78,Settings!$G$80,Settings!$G$82,Settings!$G$84,Settings!$G$86) | AS17: =CHOOSE(MATCH(IF($U17="","Основний",$U17),{"Трафіковий","Основний","Маржинальний","Сезонний","Стратегічний"},0),Settings!$H$78,Settings!$H$80,Settings!$H$82,Settings!$H$84,Settings!$H$86) | AT17: =CHOOSE(MATCH(IF($U17="","Основний",$U17),{"Трафіковий","Основний","Маржинальний","Сезонний","Стратегічний"},0),Settings!$I$78,Settings!$I$80,Settings!$I$82,Settings!$I$84,Settings!$I$86) | AV17: 1.35
B18: P2317 | C18: SMD+2×COB LED RECH. FLASHLIGHT 1000 LM 15 000 MAH | D18: Ліхтарі | E18: PC | F18: 25.969 | G18: 8513100000 | H18: 1.4 | I18: =IFERROR(F18*Settings!$B$2*H18*IF(AND(ISNUMBER(E18),E18>1),E18,1),"") | J18: =Settings!$B$66 | K18: =IFERROR(IF(T18="","",(T18*(1-AN18)*(1-Settings!$B$17)-I18)/(T18*(1-AN18)*(1-Settings!$B$17))),"") | L18: =IFERROR(IF(T18="","",(T18*(1-AO18)*(1-Settings!$C$17)-I18)/(T18*(1-AO18)*(1-Settings!$C$17))),"") | M18: =IFERROR(IF(T18="","",(T18*(1-AP18)*(1-Settings!$D$17)-I18)/(T18*(1-AP18)*(1-Settings!$D$17))),"") | N18: =IFERROR(IF(T18="","",(T18*(1-AQ18)*(1-Settings!$F$17)-I18)/(T18*(1-AQ18)*(1-Settings!$F$17))),"") | O18: =IFERROR(IF(T18="","",(T18*(1-AR18)*(1-Settings!$G$17)-I18)/(T18*(1-AR18)*(1-Settings!$G$17))),"") | P18: =IFERROR(IF(T18="","",(T18*(1-AS18)*(1-Settings!$H$17)-I18)/(T18*(1-AS18)*(1-Settings!$H$17))),"") | Q18: =IFERROR(IF(T18="","",(T18*(1-AT18)*(1-Settings!$I$68)*(1-Settings!$I$17)-I18)/(T18*(1-AT18)*(1-Settings!$I$68)*(1-Settings!$I$17))),"") | R18: =IFERROR(IF(OR(I18="",Z18>=1,Settings!$B$17>=1,AN18>=1),"",IF(MOD(ROUND(I18/(1-Z18)/(1-Settings!$B$17)/(1-AN18),0),10)=0,ROUND(I18/(1-Z18)/(1-Settings!$B$17)/(1-AN18),0)-1,IF(MOD(ROUND(I18/(1-Z18)/(1-Settings!$B$17)/(1-AN18),0),10)<=5,FLOOR(ROUND(I18/(1-Z18)/(1-Settings!$B$17)/(1-AN18),0),10)+6,FLOOR(ROUND(I18/(1-Z18)/(1-Settings!$B$17)/(1-AN18),0),10)+9))),"") | S18: 3460 | T18: =IF(S18<>"", IF(MOD(S18,10)=0,S18-1,IF(MOD(S18,10)<=5,FLOOR(S18,10)+6,FLOOR(S18,10)+9)), R18) | U18: Основний | X18: =IFERROR(IF(OR(V18="",W18="",T18=""),"", IF(T18>W18,"Дорогий",IF(T18<V18,"Дешевий","У ринку"))),"") | Z18: =CHOOSE(MATCH(IF($U18="","Основний",$U18),{"Трафіковий","Основний","Маржинальний","Сезонний","Стратегічний"},0),0.16,0.19,0.24,0.23,0.28) | AA18: =CHOOSE(MATCH(IF($U18="","Основний",$U18),{"Трафіковий","Основний","Маржинальний","Сезонний","Стратегічний"},0),0.18,0.21,0.26,0.25,0.3) | AB18: =CHOOSE(MATCH(IF($U18="","Основний",$U18),{"Трафіковий","Основний","Маржинальний","Сезонний","Стратегічний"},0),0.19,0.22,0.28,0.26,0.32) | AC18: =CHOOSE(MATCH(IF($U18="","Основний",$U18),{"Трафіковий","Основний","Маржинальний","Сезонний","Стратегічний"},0),0.17,0.2,0.25,0.24,0.28) | AD18: =CHOOSE(MATCH(IF($U18="","Основний",$U18),{"Трафіковий","Основний","Маржинальний","Сезонний","Стратегічний"},0),0.18,0.21,0.26,0.25,0.3) | AE18: =CHOOSE(MATCH(IF($U18="","Основний",$U18),{"Трафіковий","Основний","Маржинальний","Сезонний","Стратегічний"},0),0.18,0.2,0.28,0.27,0.32) | AF18: =CHOOSE(MATCH(IF($U18="","Основний",$U18),{"Трафіковий","Основний","Маржинальний","Сезонний","Стратегічний"},0),0.15,0.175,0.22,0.21,0.25) | AG18: =CHOOSE(MATCH(IF($U18="","Основний",$U18),{"Трафіковий","Основний","Маржинальний","Сезонний","Стратегічний"},0),0.13,0.16,0.21,0.2,0.25) | AH18: =CHOOSE(MATCH(IF($U18="","Основний",$U18),{"Трафіковий","Основний","Маржинальний","Сезонний","Стратегічний"},0),0.15,0.18,0.23,0.22,0.27) | AI18: =CHOOSE(MATCH(IF($U18="","Основний",$U18),{"Трафіковий","Основний","Маржинальний","Сезонний","Стратегічний"},0),0.16,0.19,0.25,0.23,0.29) | AJ18: =CHOOSE(MATCH(IF($U18="","Основний",$U18),{"Трафіковий","Основний","Маржинальний","Сезонний","Стратегічний"},0),0.14,0.17,0.22,0.21,0.25) | AK18: =CHOOSE(MATCH(IF($U18="","Основний",$U18),{"Трафіковий","Основний","Маржинальний","Сезонний","Стратегічний"},0),0.15,0.18,0.23,0.22,0.27) | AL18: =CHOOSE(MATCH(IF($U18="","Основний",$U18),{"Трафіковий","Основний","Маржинальний","Сезонний","Стратегічний"},0),0.15,0.17,0.25,0.24,0.29) | AM18: =CHOOSE(MATCH(IF($U18="","Основний",$U18),{"Трафіковий","Основний","Маржинальний","Сезонний","Стратегічний"},0),0.12,0.145,0.19,0.18,0.22) | AN18: =CHOOSE(MATCH(IF($U18="","Основний",$U18),{"Трафіковий","Основний","Маржинальний","Сезонний","Стратегічний"},0),Settings!$B$78,Settings!$B$80,Settings!$B$82,Settings!$B$84,Settings!$B$86) | AO18: =CHOOSE(MATCH(IF($U18="","Основний",$U18),{"Трафіковий","Основний","Маржинальний","Сезонний","Стратегічний"},0),Settings!$C$78,Settings!$C$80,Settings!$C$82,Settings!$C$84,Settings!$C$86) | AP18: =CHOOSE(MATCH(IF($U18="","Основний",$U18),{"Трафіковий","Основний","Маржинальний","Сезонний","Стратегічний"},0),Settings!$D$78,Settings!$D$80,Settings!$D$82,Settings!$D$84,Settings!$D$86) | AQ18: =CHOOSE(MATCH(IF($U18="","Основний",$U18),{"Трафіковий","Основний","Маржинальний","Сезонний","Стратегічний"},0),Settings!$F$78,Settings!$F$80,Settings!$F$82,Settings!$F$84,Settings!$F$86) | AR18: =CHOOSE(MATCH(IF($U18="","Основний",$U18),{"Трафіковий","Основний","Маржинальний","Сезонний","Стратегічний"},0),Settings!$G$78,Settings!$G$80,Settings!$G$82,Settings!$G$84,Settings!$G$86) | AS18: =CHOOSE(MATCH(IF($U18="","Основний",$U18),{"Трафіковий","Основний","Маржинальний","Сезонний","Стратегічний"},0),Settings!$H$78,Settings!$H$80,Settings!$H$82,Settings!$H$84,Settings!$H$86) | AT18: =CHOOSE(MATCH(IF($U18="","Основний",$U18),{"Трафіковий","Основний","Маржинальний","Сезонний","Стратегічний"},0),Settings!$I$78,Settings!$I$80,Settings!$I$82,Settings!$I$84,Settings!$I$86) | AV18: 1.35
B19: P3150 | C19: LED FLASHLIGHT ULTIBRIGHT 50 100lm 1×AAA | D19: Ліхтарі | E19: PC | F19: 7.272 | G19: 8513100000 | H19: 1.4 | I19: =IFERROR(F19*Settings!$B$2*H19*IF(AND(ISNUMBER(E19),E19>1),E19,1),"") | J19: =Settings!$B$66 | K19: =IFERROR(IF(T19="","",(T19*(1-AN19)*(1-Settings!$B$17)-I19)/(T19*(1-AN19)*(1-Settings!$B$17))),"") | L19: =IFERROR(IF(T19="","",(T19*(1-AO19)*(1-Settings!$C$17)-I19)/(T19*(1-AO19)*(1-Settings!$C$17))),"") | M19: =IFERROR(IF(T19="","",(T19*(1-AP19)*(1-Settings!$D$17)-I19)/(T19*(1-AP19)*(1-Settings!$D$17))),"") | N19: =IFERROR(IF(T19="","",(T19*(1-AQ19)*(1-Settings!$F$17)-I19)/(T19*(1-AQ19)*(1-Settings!$F$17))),"") | O19: =IFERROR(IF(T19="","",(T19*(1-AR19)*(1-Settings!$G$17)-I19)/(T19*(1-AR19)*(1-Settings!$G$17))),"") | P19: =IFERROR(IF(T19="","",(T19*(1-AS19)*(1-Settings!$H$17)-I19)/(T19*(1-AS19)*(1-Settings!$H$17))),"") | Q19: =IFERROR(IF(T19="","",(T19*(1-AT19)*(1-Settings!$I$68)*(1-Settings!$I$17)-I19)/(T19*(1-AT19)*(1-Settings!$I$68)*(1-Settings!$I$17))),"") | R19: =IFERROR(IF(OR(I19="",Z19>=1,Settings!$B$17>=1,AN19>=1),"",IF(MOD(ROUND(I19/(1-Z19)/(1-Settings!$B$17)/(1-AN19),0),10)=0,ROUND(I19/(1-Z19)/(1-Settings!$B$17)/(1-AN19),0)-1,IF(MOD(ROUND(I19/(1-Z19)/(1-Settings!$B$17)/(1-AN19),0),10)<=5,FLOOR(ROUND(I19/(1-Z19)/(1-Settings!$B$17)/(1-AN19),0),10)+6,FLOOR(ROUND(I19/(1-Z19)/(1-Settings!$B$17)/(1-AN19),0),10)+9))),"") | T19: =IF(S19<>"", IF(MOD(S19,10)=0,S19-1,IF(MOD(S19,10)<=5,FLOOR(S19,10)+6,FLOOR(S19,10)+9)), R19) | U19: Основний | X19: =IFERROR(IF(OR(V19="",W19="",T19=""),"", IF(T19>W19,"Дорогий",IF(T19<V19,"Дешевий","У ринку"))),"") | Z19: =CHOOSE(MATCH(IF($U19="","Основний",$U19),{"Трафіковий","Основний","Маржинальний","Сезонний","Стратегічний"},0),0.16,0.19,0.24,0.23,0.28) | AA19: =CHOOSE(MATCH(IF($U19="","Основний",$U19),{"Трафіковий","Основний","Маржинальний","Сезонний","Стратегічний"},0),0.18,0.21,0.26,0.25,0.3) | AB19: =CHOOSE(MATCH(IF($U19="","Основний",$U19),{"Трафіковий","Основний","Маржинальний","Сезонний","Стратегічний"},0),0.19,0.22,0.28,0.26,0.32) | AC19: =CHOOSE(MATCH(IF($U19="","Основний",$U19),{"Трафіковий","Основний","Маржинальний","Сезонний","Стратегічний"},0),0.17,0.2,0.25,0.24,0.28) | AD19: =CHOOSE(MATCH(IF($U19="","Основний",$U19),{"Трафіковий","Основний","Маржинальний","Сезонний","Стратегічний"},0),0.18,0.21,0.26,0.25,0.3) | AE19: =CHOOSE(MATCH(IF($U19="","Основний",$U19),{"Трафіковий","Основний","Маржинальний","Сезонний","Стратегічний"},0),0.18,0.2,0.28,0.27,0.32) | AF19: =CHOOSE(MATCH(IF($U19="","Основний",$U19),{"Трафіковий","Основний","Маржинальний","Сезонний","Стратегічний"},0),0.15,0.175,0.22,0.21,0.25) | AG19: =CHOOSE(MATCH(IF($U19="","Основний",$U19),{"Трафіковий","Основний","Маржинальний","Сезонний","Стратегічний"},0),0.13,0.16,0.21,0.2,0.25) | AH19: =CHOOSE(MATCH(IF($U19="","Основний",$U19),{"Трафіковий","Основний","Маржинальний","Сезонний","Стратегічний"},0),0.15,0.18,0.23,0.22,0.27) | AI19: =CHOOSE(MATCH(IF($U19="","Основний",$U19),{"Трафіковий","Основний","Маржинальний","Сезонний","Стратегічний"},0),0.16,0.19,0.25,0.23,0.29) | AJ19: =CHOOSE(MATCH(IF($U19="","Основний",$U19),{"Трафіковий","Основний","Маржинальний","Сезонний","Стратегічний"},0),0.14,0.17,0.22,0.21,0.25) | AK19: =CHOOSE(MATCH(IF($U19="","Основний",$U19),{"Трафіковий","Основний","Маржинальний","Сезонний","Стратегічний"},0),0.15,0.18,0.23,0.22,0.27) | AL19: =CHOOSE(MATCH(IF($U19="","Основний",$U19),{"Трафіковий","Основний","Маржинальний","Сезонний","Стратегічний"},0),0.15,0.17,0.25,0.24,0.29) | AM19: =CHOOSE(MATCH(IF($U19="","Основний",$U19),{"Трафіковий","Основний","Маржинальний","Сезонний","Стратегічний"},0),0.12,0.145,0.19,0.18,0.22) | AN19: =CHOOSE(MATCH(IF($U19="","Основний",$U19),{"Трафіковий","Основний","Маржинальний","Сезонний","Стратегічний"},0),Settings!$B$78,Settings!$B$80,Settings!$B$82,Settings!$B$84,Settings!$B$86) | AO19: =CHOOSE(MATCH(IF($U19="","Основний",$U19),{"Трафіковий","Основний","Маржинальний","Сезонний","Стратегічний"},0),Settings!$C$78,Settings!$C$80,Settings!$C$82,Settings!$C$84,Settings!$C$86) | AP19: =CHOOSE(MATCH(IF($U19="","Основний",$U19),{"Трафіковий","Основний","Маржинальний","Сезонний","Стратегічний"},0),Settings!$D$78,Settings!$D$80,Settings!$D$82,Settings!$D$84,Settings!$D$86) | AQ19: =CHOOSE(MATCH(IF($U19="","Основний",$U19),{"Трафіковий","Основний","Маржинальний","Сезонний","Стратегічний"},0),Settings!$F$78,Settings!$F$80,Settings!$F$82,Settings!$F$84,Settings!$F$86) | AR19: =CHOOSE(MATCH(IF($U19="","Основний",$U19),{"Трафіковий","Основний","Маржинальний","Сезонний","Стратегічний"},0),Settings!$G$78,Settings!$G$80,Settings!$G$82,Settings!$G$84,Settings!$G$86) | AS19: =CHOOSE(MATCH(IF($U19="","Основний",$U19),{"Трафіковий","Основний","Маржинальний","Сезонний","Стратегічний"},0),Settings!$H$78,Settings!$H$80,Settings!$H$82,Settings!$H$84,Settings!$H$86) | AT19: =CHOOSE(MATCH(IF($U19="","Основний",$U19),{"Трафіковий","Основний","Маржинальний","Сезонний","Стратегічний"},0),Settings!$I$78,Settings!$I$80,Settings!$I$82,Settings!$I$84,Settings!$I$86) | AV19: 1.35
B20: P3160 | C20: LED FLASHLIGHT ULTIBRIGHT 60 170lm 1×AA | D20: Ліхтарі | E20: PC | F20: 7.676 | G20: 8513100000 | H20: 1.4 | I20: =IFERROR(F20*Settings!$B$2*H20*IF(AND(ISNUMBER(E20),E20>1),E20,1),"") | J20: =Settings!$B$66 | K20: =IFERROR(IF(T20="","",(T20*(1-AN20)*(1-Settings!$B$17)-I20)/(T20*(1-AN20)*(1-Settings!$B$17))),"") | L20: =IFERROR(IF(T20="","",(T20*(1-AO20)*(1-Settings!$C$17)-I20)/(T20*(1-AO20)*(1-Settings!$C$17))),"") | M20: =IFERROR(IF(T20="","",(T20*(1-AP20)*(1-Settings!$D$17)-I20)/(T20*(1-AP20)*(1-Settings!$D$17))),"") | N20: =IFERROR(IF(T20="","",(T20*(1-AQ20)*(1-Settings!$F$17)-I20)/(T20*(1-AQ20)*(1-Settings!$F$17))),"") | O20: =IFERROR(IF(T20="","",(T20*(1-AR20)*(1-Settings!$G$17)-I20)/(T20*(1-AR20)*(1-Settings!$G$17))),"") | P20: =IFERROR(IF(T20="","",(T20*(1-AS20)*(1-Settings!$H$17)-I20)/(T20*(1-AS20)*(1-Settings!$H$17))),"") | Q20: =IFERROR(IF(T20="","",(T20*(1-AT20)*(1-Settings!$I$68)*(1-Settings!$I$17)-I20)/(T20*(1-AT20)*(1-Settings!$I$68)*(1-Settings!$I$17))),"") | R20: =IFERROR(IF(OR(I20="",Z20>=1,Settings!$B$17>=1,AN20>=1),"",IF(MOD(ROUND(I20/(1-Z20)/(1-Settings!$B$17)/(1-AN20),0),10)=0,ROUND(I20/(1-Z20)/(1-Settings!$B$17)/(1-AN20),0)-1,IF(MOD(ROUND(I20/(1-Z20)/(1-Settings!$B$17)/(1-AN20),0),10)<=5,FLOOR(ROUND(I20/(1-Z20)/(1-Settings!$B$17)/(1-AN20),0),10)+6,FLOOR(ROUND(I20/(1-Z20)/(1-Settings!$B$17)/(1-AN20),0),10)+9))),"") | S20: 1000 | T20: =IF(S20<>"", IF(MOD(S20,10)=0,S20-1,IF(MOD(S20,10)<=5,FLOOR(S20,10)+6,FLOOR(S20,10)+9)), R20) | U20: Основний | X20: =IFERROR(IF(OR(V20="",W20="",T20=""),"", IF(T20>W20,"Дорогий",IF(T20<V20,"Дешевий","У ринку"))),"") | Z20: =CHOOSE(MATCH(IF($U20="","Основний",$U20),{"Трафіковий","Основний","Маржинальний","Сезонний","Стратегічний"},0),0.16,0.19,0.24,0.23,0.28) | AA20: =CHOOSE(MATCH(IF($U20="","Основний",$U20),{"Трафіковий","Основний","Маржинальний","Сезонний","Стратегічний"},0),0.18,0.21,0.26,0.25,0.3) | AB20: =CHOOSE(MATCH(IF($U20="","Основний",$U20),{"Трафіковий","Основний","Маржинальний","Сезонний","Стратегічний"},0),0.19,0.22,0.28,0.26,0.32) | AC20: =CHOOSE(MATCH(IF($U20="","Основний",$U20),{"Трафіковий","Основний","Маржинальний","Сезонний","Стратегічний"},0),0.17,0.2,0.25,0.24,0.28) | AD20: =CHOOSE(MATCH(IF($U20="","Основний",$U20),{"Трафіковий","Основний","Маржинальний","Сезонний","Стратегічний"},0),0.18,0.21,0.26,0.25,0.3) | AE20: =CHOOSE(MATCH(IF($U20="","Основний",$U20),{"Трафіковий","Основний","Маржинальний","Сезонний","Стратегічний"},0),0.18,0.2,0.28,0.27,0.32) | AF20: =CHOOSE(MATCH(IF($U20="","Основний",$U20),{"Трафіковий","Основний","Маржинальний","Сезонний","Стратегічний"},0),0.15,0.175,0.22,0.21,0.25) | AG20: =CHOOSE(MATCH(IF($U20="","Основний",$U20),{"Трафіковий","Основний","Маржинальний","Сезонний","Стратегічний"},0),0.13,0.16,0.21,0.2,0.25) | AH20: =CHOOSE(MATCH(IF($U20="","Основний",$U20),{"Трафіковий","Основний","Маржинальний","Сезонний","Стратегічний"},0),0.15,0.18,0.23,0.22,0.27) | AI20: =CHOOSE(MATCH(IF($U20="","Основний",$U20),{"Трафіковий","Основний","Маржинальний","Сезонний","Стратегічний"},0),0.16,0.19,0.25,0.23,0.29) | AJ20: =CHOOSE(MATCH(IF($U20="","Основний",$U20),{"Трафіковий","Основний","Маржинальний","Сезонний","Стратегічний"},0),0.14,0.17,0.22,0.21,0.25) | AK20: =CHOOSE(MATCH(IF($U20="","Основний",$U20),{"Трафіковий","Основний","Маржинальний","Сезонний","Стратегічний"},0),0.15,0.18,0.23,0.22,0.27) | AL20: =CHOOSE(MATCH(IF($U20="","Основний",$U20),{"Трафіковий","Основний","Маржинальний","Сезонний","Стратегічний"},0),0.15,0.17,0.25,0.24,0.29) | AM20: =CHOOSE(MATCH(IF($U20="","Основний",$U20),{"Трафіковий","Основний","Маржинальний","Сезонний","Стратегічний"},0),0.12,0.145,0.19,0.18,0.22) | AN20: =CHOOSE(MATCH(IF($U20="","Основний",$U20),{"Трафіковий","Основний","Маржинальний","Сезонний","Стратегічний"},0),Settings!$B$78,Settings!$B$80,Settings!$B$82,Settings!$B$84,Settings!$B$86) | AO20: =CHOOSE(MATCH(IF($U20="","Основний",$U20),{"Трафіковий","Основний","Маржинальний","Сезонний","Стратегічний"},0),Settings!$C$78,Settings!$C$80,Settings!$C$82,Settings!$C$84,Settings!$C$86) | AP20: =CHOOSE(MATCH(IF($U20="","Основний",$U20),{"Трафіковий","Основний","Маржинальний","Сезонний","Стратегічний"},0),Settings!$D$78,Settings!$D$80,Settings!$D$82,Settings!$D$84,Settings!$D$86) | AQ20: =CHOOSE(MATCH(IF($U20="","Основний",$U20),{"Трафіковий","Основний","Маржинальний","Сезонний","Стратегічний"},0),Settings!$F$78,Settings!$F$80,Settings!$F$82,Settings!$F$84,Settings!$F$86) | AR20: =CHOOSE(MATCH(IF($U20="","Основний",$U20),{"Трафіковий","Основний","Маржинальний","Сезонний","Стратегічний"},0),Settings!$G$78,Settings!$G$80,Settings!$G$82,Settings!$G$84,Settings!$G$86) | AS20: =CHOOSE(MATCH(IF($U20="","Основний",$U20),{"Трафіковий","Основний","Маржинальний","Сезонний","Стратегічний"},0),Settings!$H$78,Settings!$H$80,Settings!$H$82,Settings!$H$84,Settings!$H$86) | AT20: =CHOOSE(MATCH(IF($U20="","Основний",$U20),{"Трафіковий","Основний","Маржинальний","Сезонний","Стратегічний"},0),Settings!$I$78,Settings!$I$80,Settings!$I$82,Settings!$I$84,Settings!$I$86) | AV20: 1.35
B21: P3170 | C21: LED FLASHLIGHT ULTIBRIGHT 70 340lm 3×AAA | D21: Ліхтарі | E21: PC | F21: 13.502 | G21: 8513100000 | H21: 1.4 | I21: =IFERROR(F21*Settings!$B$2*H21*IF(AND(ISNUMBER(E21),E21>1),E21,1),"") | J21: =Settings!$B$66 | K21: =IFERROR(IF(T21="","",(T21*(1-AN21)*(1-Settings!$B$17)-I21)/(T21*(1-AN21)*(1-Settings!$B$17))),"") | L21: =IFERROR(IF(T21="","",(T21*(1-AO21)*(1-Settings!$C$17)-I21)/(T21*(1-AO21)*(1-Settings!$C$17))),"") | M21: =IFERROR(IF(T21="","",(T21*(1-AP21)*(1-Settings!$D$17)-I21)/(T21*(1-AP21)*(1-Settings!$D$17))),"") | N21: =IFERROR(IF(T21="","",(T21*(1-AQ21)*(1-Settings!$F$17)-I21)/(T21*(1-AQ21)*(1-Settings!$F$17))),"") | O21: =IFERROR(IF(T21="","",(T21*(1-AR21)*(1-Settings!$G$17)-I21)/(T21*(1-AR21)*(1-Settings!$G$17))),"") | P21: =IFERROR(IF(T21="","",(T21*(1-AS21)*(1-Settings!$H$17)-I21)/(T21*(1-AS21)*(1-Settings!$H$17))),"") | Q21: =IFERROR(IF(T21="","",(T21*(1-AT21)*(1-Settings!$I$68)*(1-Settings!$I$17)-I21)/(T21*(1-AT21)*(1-Settings!$I$68)*(1-Settings!$I$17))),"") | R21: =IFERROR(IF(OR(I21="",Z21>=1,Settings!$B$17>=1,AN21>=1),"",IF(MOD(ROUND(I21/(1-Z21)/(1-Settings!$B$17)/(1-AN21),0),10)=0,ROUND(I21/(1-Z21)/(1-Settings!$B$17)/(1-AN21),0)-1,IF(MOD(ROUND(I21/(1-Z21)/(1-Settings!$B$17)/(1-AN21),0),10)<=5,FLOOR(ROUND(I21/(1-Z21)/(1-Settings!$B$17)/(1-AN21),0),10)+6,FLOOR(ROUND(I21/(1-Z21)/(1-Settings!$B$17)/(1-AN21),0),10)+9))),"") | S21: 1800 | T21: =IF(S21<>"", IF(MOD(S21,10)=0,S21-1,IF(MOD(S21,10)<=5,FLOOR(S21,10)+6,FLOOR(S21,10)+9)), R21) | U21: Основний | X21: =IFERROR(IF(OR(V21="",W21="",T21=""),"", IF(T21>W21,"Дорогий",IF(T21<V21,"Дешевий","У ринку"))),"") | Z21: =CHOOSE(MATCH(IF($U21="","Основний",$U21),{"Трафіковий","Основний","Маржинальний","Сезонний","Стратегічний"},0),0.16,0.19,0.24,0.23,0.28) | AA21: =CHOOSE(MATCH(IF($U21="","Основний",$U21),{"Трафіковий","Основний","Маржинальний","Сезонний","Стратегічний"},0),0.18,0.21,0.26,0.25,0.3) | AB21: =CHOOSE(MATCH(IF($U21="","Основний",$U21),{"Трафіковий","Основний","Маржинальний","Сезонний","Стратегічний"},0),0.19,0.22,0.28,0.26,0.32) | AC21: =CHOOSE(MATCH(IF($U21="","Основний",$U21),{"Трафіковий","Основний","Маржинальний","Сезонний","Стратегічний"},0),0.17,0.2,0.25,0.24,0.28) | AD21: =CHOOSE(MATCH(IF($U21="","Основний",$U21),{"Трафіковий","Основний","Маржинальний","Сезонний","Стратегічний"},0),0.18,0.21,0.26,0.25,0.3) | AE21: =CHOOSE(MATCH(IF($U21="","Основний",$U21),{"Трафіковий","Основний","Маржинальний","Сезонний","Стратегічний"},0),0.18,0.2,0.28,0.27,0.32) | AF21: =CHOOSE(MATCH(IF($U21="","Основний",$U21),{"Трафіковий","Основний","Маржинальний","Сезонний","Стратегічний"},0),0.15,0.175,0.22,0.21,0.25) | AG21: =CHOOSE(MATCH(IF($U21="","Основний",$U21),{"Трафіковий","Основний","Маржинальний","Сезонний","Стратегічний"},0),0.13,0.16,0.21,0.2,0.25) | AH21: =CHOOSE(MATCH(IF($U21="","Основний",$U21),{"Трафіковий","Основний","Маржинальний","Сезонний","Стратегічний"},0),0.15,0.18,0.23,0.22,0.27) | AI21: =CHOOSE(MATCH(IF($U21="","Основний",$U21),{"Трафіковий","Основний","Маржинальний","Сезонний","Стратегічний"},0),0.16,0.19,0.25,0.23,0.29) | AJ21: =CHOOSE(MATCH(IF($U21="","Основний",$U21),{"Трафіковий","Основний","Маржинальний","Сезонний","Стратегічний"},0),0.14,0.17,0.22,0.21,0.25) | AK21: =CHOOSE(MATCH(IF($U21="","Основний",$U21),{"Трафіковий","Основний","Маржинальний","Сезонний","Стратегічний"},0),0.15,0.18,0.23,0.22,0.27) | AL21: =CHOOSE(MATCH(IF($U21="","Основний",$U21),{"Трафіковий","Основний","Маржинальний","Сезонний","Стратегічний"},0),0.15,0.17,0.25,0.24,0.29) | AM21: =CHOOSE(MATCH(IF($U21="","Основний",$U21),{"Трафіковий","Основний","Маржинальний","Сезонний","Стратегічний"},0),0.12,0.145,0.19,0.18,0.22) | AN21: =CHOOSE(MATCH(IF($U21="","Основний",$U21),{"Трафіковий","Основний","Маржинальний","Сезонний","Стратегічний"},0),Settings!$B$78,Settings!$B$80,Settings!$B$82,Settings!$B$84,Settings!$B$86) | AO21: =CHOOSE(MATCH(IF($U21="","Основний",$U21),{"Трафіковий","Основний","Маржинальний","Сезонний","Стратегічний"},0),Settings!$C$78,Settings!$C$80,Settings!$C$82,Settings!$C$84,Settings!$C$86) | AP21: =CHOOSE(MATCH(IF($U21="","Основний",$U21),{"Трафіковий","Основний","Маржинальний","Сезонний","Стратегічний"},0),Settings!$D$78,Settings!$D$80,Settings!$D$82,Settings!$D$84,Settings!$D$86) | AQ21: =CHOOSE(MATCH(IF($U21="","Основний",$U21),{"Трафіковий","Основний","Маржинальний","Сезонний","Стратегічний"},0),Settings!$F$78,Settings!$F$80,Settings!$F$82,Settings!$F$84,Settings!$F$86) | AR21: =CHOOSE(MATCH(IF($U21="","Основний",$U21),{"Трафіковий","Основний","Маржинальний","Сезонний","Стратегічний"},0),Settings!$G$78,Settings!$G$80,Settings!$G$82,Settings!$G$84,Settings!$G$86) | AS21: =CHOOSE(MATCH(IF($U21="","Основний",$U21),{"Трафіковий","Основний","Маржинальний","Сезонний","Стратегічний"},0),Settings!$H$78,Settings!$H$80,Settings!$H$82,Settings!$H$84,Settings!$H$86) | AT21: =CHOOSE(MATCH(IF($U21="","Основний",$U21),{"Трафіковий","Основний","Маржинальний","Сезонний","Стратегічний"},0),Settings!$I$78,Settings!$I$80,Settings!$I$82,Settings!$I$84,Settings!$I$86) | AV21: 1.35
B22: P3180 | C22: LED RECH. FLASHLIGHT ULTIBRIGHT 80 600lm 2600mAh | D22: Ліхтарі | E22: PC | F22: 23.711 | G22: 8513100000 | H22: 1.4 | I22: =IFERROR(F22*Settings!$B$2*H22*IF(AND(ISNUMBER(E22),E22>1),E22,1),"") | J22: =Settings!$B$66 | K22: =IFERROR(IF(T22="","",(T22*(1-AN22)*(1-Settings!$B$17)-I22)/(T22*(1-AN22)*(1-Settings!$B$17))),"") | L22: =IFERROR(IF(T22="","",(T22*(1-AO22)*(1-Settings!$C$17)-I22)/(T22*(1-AO22)*(1-Settings!$C$17))),"") | M22: =IFERROR(IF(T22="","",(T22*(1-AP22)*(1-Settings!$D$17)-I22)/(T22*(1-AP22)*(1-Settings!$D$17))),"") | N22: =IFERROR(IF(T22="","",(T22*(1-AQ22)*(1-Settings!$F$17)-I22)/(T22*(1-AQ22)*(1-Settings!$F$17))),"") | O22: =IFERROR(IF(T22="","",(T22*(1-AR22)*(1-Settings!$G$17)-I22)/(T22*(1-AR22)*(1-Settings!$G$17))),"") | P22: =IFERROR(IF(T22="","",(T22*(1-AS22)*(1-Settings!$H$17)-I22)/(T22*(1-AS22)*(1-Settings!$H$17))),"") | Q22: =IFERROR(IF(T22="","",(T22*(1-AT22)*(1-Settings!$I$68)*(1-Settings!$I$17)-I22)/(T22*(1-AT22)*(1-Settings!$I$68)*(1-Settings!$I$17))),"") | R22: =IFERROR(IF(OR(I22="",Z22>=1,Settings!$B$17>=1,AN22>=1),"",IF(MOD(ROUND(I22/(1-Z22)/(1-Settings!$B$17)/(1-AN22),0),10)=0,ROUND(I22/(1-Z22)/(1-Settings!$B$17)/(1-AN22),0)-1,IF(MOD(ROUND(I22/(1-Z22)/(1-Settings!$B$17)/(1-AN22),0),10)<=5,FLOOR(ROUND(I22/(1-Z22)/(1-Settings!$B$17)/(1-AN22),0),10)+6,FLOOR(ROUND(I22/(1-Z22)/(1-Settings!$B$17)/(1-AN22),0),10)+9))),"") | S22: 3000 | T22: =IF(S22<>"", IF(MOD(S22,10)=0,S22-1,IF(MOD(S22,10)<=5,FLOOR(S22,10)+6,FLOOR(S22,10)+9)), R22) | U22: Основний | X22: =IFERROR(IF(OR(V22="",W22="",T22=""),"", IF(T22>W22,"Дорогий",IF(T22<V22,"Дешевий","У ринку"))),"") | Z22: =CHOOSE(MATCH(IF($U22="","Основний",$U22),{"Трафіковий","Основний","Маржинальний","Сезонний","Стратегічний"},0),0.16,0.19,0.24,0.23,0.28) | AA22: =CHOOSE(MATCH(IF($U22="","Основний",$U22),{"Трафіковий","Основний","Маржинальний","Сезонний","Стратегічний"},0),0.18,0.21,0.26,0.25,0.3) | AB22: =CHOOSE(MATCH(IF($U22="","Основний",$U22),{"Трафіковий","Основний","Маржинальний","Сезонний","Стратегічний"},0),0.19,0.22,0.28,0.26,0.32) | AC22: =CHOOSE(MATCH(IF($U22="","Основний",$U22),{"Трафіковий","Основний","Маржинальний","Сезонний","Стратегічний"},0),0.17,0.2,0.25,0.24,0.28) | AD22: =CHOOSE(MATCH(IF($U22="","Основний",$U22),{"Трафіковий","Основний","Маржинальний","Сезонний","Стратегічний"},0),0.18,0.21,0.26,0.25,0.3) | AE22: =CHOOSE(MATCH(IF($U22="","Основний",$U22),{"Трафіковий","Основний","Маржинальний","Сезонний","Стратегічний"},0),0.18,0.2,0.28,0.27,0.32) | AF22: =CHOOSE(MATCH(IF($U22="","Основний",$U22),{"Трафіковий","Основний","Маржинальний","Сезонний","Стратегічний"},0),0.15,0.175,0.22,0.21,0.25) | AG22: =CHOOSE(MATCH(IF($U22="","Основний",$U22),{"Трафіковий","Основний","Маржинальний","Сезонний","Стратегічний"},0),0.13,0.16,0.21,0.2,0.25) | AH22: =CHOOSE(MATCH(IF($U22="","Основний",$U22),{"Трафіковий","Основний","Маржинальний","Сезонний","Стратегічний"},0),0.15,0.18,0.23,0.22,0.27) | AI22: =CHOOSE(MATCH(IF($U22="","Основний",$U22),{"Трафіковий","Основний","Маржинальний","Сезонний","Стратегічний"},0),0.16,0.19,0.25,0.23,0.29) | AJ22: =CHOOSE(MATCH(IF($U22="","Основний",$U22),{"Трафіковий","Основний","Маржинальний","Сезонний","Стратегічний"},0),0.14,0.17,0.22,0.21,0.25) | AK22: =CHOOSE(MATCH(IF($U22="","Основний",$U22),{"Трафіковий","Основний","Маржинальний","Сезонний","Стратегічний"},0),0.15,0.18,0.23,0.22,0.27) | AL22: =CHOOSE(MATCH(IF($U22="","Основний",$U22),{"Трафіковий","Основний","Маржинальний","Сезонний","Стратегічний"},0),0.15,0.17,0.25,0.24,0.29) | AM22: =CHOOSE(MATCH(IF($U22="","Основний",$U22),{"Трафіковий","Основний","Маржинальний","Сезонний","Стратегічний"},0),0.12,0.145,0.19,0.18,0.22) | AN22: =CHOOSE(MATCH(IF($U22="","Основний",$U22),{"Трафіковий","Основний","Маржинальний","Сезонний","Стратегічний"},0),Settings!$B$78,Settings!$B$80,Settings!$B$82,Settings!$B$84,Settings!$B$86) | AO22: =CHOOSE(MATCH(IF($U22="","Основний",$U22),{"Трафіковий","Основний","Маржинальний","Сезонний","Стратегічний"},0),Settings!$C$78,Settings!$C$80,Settings!$C$82,Settings!$C$84,Settings!$C$86) | AP22: =CHOOSE(MATCH(IF($U22="","Основний",$U22),{"Трафіковий","Основний","Маржинальний","Сезонний","Стратегічний"},0),Settings!$D$78,Settings!$D$80,Settings!$D$82,Settings!$D$84,Settings!$D$86) | AQ22: =CHOOSE(MATCH(IF($U22="","Основний",$U22),{"Трафіковий","Основний","Маржинальний","Сезонний","Стратегічний"},0),Settings!$F$78,Settings!$F$80,Settings!$F$82,Settings!$F$84,Settings!$F$86) | AR22: =CHOOSE(MATCH(IF($U22="","Основний",$U22),{"Трафіковий","Основний","Маржинальний","Сезонний","Стратегічний"},0),Settings!$G$78,Settings!$G$80,Settings!$G$82,Settings!$G$84,Settings!$G$86) | AS22: =CHOOSE(MATCH(IF($U22="","Основний",$U22),{"Трафіковий","Основний","Маржинальний","Сезонний","Стратегічний"},0),Settings!$H$78,Settings!$H$80,Settings!$H$82,Settings!$H$84,Settings!$H$86) | AT22: =CHOOSE(MATCH(IF($U22="","Основний",$U22),{"Трафіковий","Основний","Маржинальний","Сезонний","Стратегічний"},0),Settings!$I$78,Settings!$I$80,Settings!$I$82,Settings!$I$84,Settings!$I$86) | AV22: 1.35
B23: P3190 | C23: LED RECH. FLASHLIGHT ULTIBRIGHT 90 1200lm 5000mAh | D23: Ліхтарі | E23: PC | F23: 30.143 | G23: 8513100000 | H23: 1.4 | I23: =IFERROR(F23*Settings!$B$2*H23*IF(AND(ISNUMBER(E23),E23>1),E23,1),"") | J23: =Settings!$B$66 | K23: =IFERROR(IF(T23="","",(T23*(1-AN23)*(1-Settings!$B$17)-I23)/(T23*(1-AN23)*(1-Settings!$B$17))),"") | L23: =IFERROR(IF(T23="","",(T23*(1-AO23)*(1-Settings!$C$17)-I23)/(T23*(1-AO23)*(1-Settings!$C$17))),"") | M23: =IFERROR(IF(T23="","",(T23*(1-AP23)*(1-Settings!$D$17)-I23)/(T23*(1-AP23)*(1-Settings!$D$17))),"") | N23: =IFERROR(IF(T23="","",(T23*(1-AQ23)*(1-Settings!$F$17)-I23)/(T23*(1-AQ23)*(1-Settings!$F$17))),"") | O23: =IFERROR(IF(T23="","",(T23*(1-AR23)*(1-Settings!$G$17)-I23)/(T23*(1-AR23)*(1-Settings!$G$17))),"") | P23: =IFERROR(IF(T23="","",(T23*(1-AS23)*(1-Settings!$H$17)-I23)/(T23*(1-AS23)*(1-Settings!$H$17))),"") | Q23: =IFERROR(IF(T23="","",(T23*(1-AT23)*(1-Settings!$I$68)*(1-Settings!$I$17)-I23)/(T23*(1-AT23)*(1-Settings!$I$68)*(1-Settings!$I$17))),"") | R23: =IFERROR(IF(OR(I23="",Z23>=1,Settings!$B$17>=1,AN23>=1),"",IF(MOD(ROUND(I23/(1-Z23)/(1-Settings!$B$17)/(1-AN23),0),10)=0,ROUND(I23/(1-Z23)/(1-Settings!$B$17)/(1-AN23),0)-1,IF(MOD(ROUND(I23/(1-Z23)/(1-Settings!$B$17)/(1-AN23),0),10)<=5,FLOOR(ROUND(I23/(1-Z23)/(1-Settings!$B$17)/(1-AN23),0),10)+6,FLOOR(ROUND(I23/(1-Z23)/(1-Settings!$B$17)/(1-AN23),0),10)+9))),"") | S23: 3600 | T23: =IF(S23<>"", IF(MOD(S23,10)=0,S23-1,IF(MOD(S23,10)<=5,FLOOR(S23,10)+6,FLOOR(S23,10)+9)), R23) | U23: Основний | X23: =IFERROR(IF(OR(V23="",W23="",T23=""),"", IF(T23>W23,"Дорогий",IF(T23<V23,"Дешевий","У ринку"))),"") | Z23: =CHOOSE(MATCH(IF($U23="","Основний",$U23),{"Трафіковий","Основний","Маржинальний","Сезонний","Стратегічний"},0),0.16,0.19,0.24,0.23,0.28) | AA23: =CHOOSE(MATCH(IF($U23="","Основний",$U23),{"Трафіковий","Основний","Маржинальний","Сезонний","Стратегічний"},0),0.18,0.21,0.26,0.25,0.3) | AB23: =CHOOSE(MATCH(IF($U23="","Основний",$U23),{"Трафіковий","Основний","Маржинальний","Сезонний","Стратегічний"},0),0.19,0.22,0.28,0.26,0.32) | AC23: =CHOOSE(MATCH(IF($U23="","Основний",$U23),{"Трафіковий","Основний","Маржинальний","Сезонний","Стратегічний"},0),0.17,0.2,0.25,0.24,0.28) | AD23: =CHOOSE(MATCH(IF($U23="","Основний",$U23),{"Трафіковий","Основний","Маржинальний","Сезонний","Стратегічний"},0),0.18,0.21,0.26,0.25,0.3) | AE23: =CHOOSE(MATCH(IF($U23="","Основний",$U23),{"Трафіковий","Основний","Маржинальний","Сезонний","Стратегічний"},0),0.18,0.2,0.28,0.27,0.32) | AF23: =CHOOSE(MATCH(IF($U23="","Основний",$U23),{"Трафіковий","Основний","Маржинальний","Сезонний","Стратегічний"},0),0.15,0.175,0.22,0.21,0.25) | AG23: =CHOOSE(MATCH(IF($U23="","Основний",$U23),{"Трафіковий","Основний","Маржинальний","Сезонний","Стратегічний"},0),0.13,0.16,0.21,0.2,0.25) | AH23: =CHOOSE(MATCH(IF($U23="","Основний",$U23),{"Трафіковий","Основний","Маржинальний","Сезонний","Стратегічний"},0),0.15,0.18,0.23,0.22,0.27) | AI23: =CHOOSE(MATCH(IF($U23="","Основний",$U23),{"Трафіковий","Основний","Маржинальний","Сезонний","Стратегічний"},0),0.16,0.19,0.25,0.23,0.29) | AJ23: =CHOOSE(MATCH(IF($U23="","Основний",$U23),{"Трафіковий","Основний","Маржинальний","Сезонний","Стратегічний"},0),0.14,0.17,0.22,0.21,0.25) | AK23: =CHOOSE(MATCH(IF($U23="","Основний",$U23),{"Трафіковий","Основний","Маржинальний","Сезонний","Стратегічний"},0),0.15,0.18,0.23,0.22,0.27) | AL23: =CHOOSE(MATCH(IF($U23="","Основний",$U23),{"Трафіковий","Основний","Маржинальний","Сезонний","Стратегічний"},0),0.15,0.17,0.25,0.24,0.29) | AM23: =CHOOSE(MATCH(IF($U23="","Основний",$U23),{"Трафіковий","Основний","Маржинальний","Сезонний","Стратегічний"},0),0.12,0.145,0.19,0.18,0.22) | AN23: =CHOOSE(MATCH(IF($U23="","Основний",$U23),{"Трафіковий","Основний","Маржинальний","Сезонний","Стратегічний"},0),Settings!$B$78,Settings!$B$80,Settings!$B$82,Settings!$B$84,Settings!$B$86) | AO23: =CHOOSE(MATCH(IF($U23="","Основний",$U23),{"Трафіковий","Основний","Маржинальний","Сезонний","Стратегічний"},0),Settings!$C$78,Settings!$C$80,Settings!$C$82,Settings!$C$84,Settings!$C$86) | AP23: =CHOOSE(MATCH(IF($U23="","Основний",$U23),{"Трафіковий","Основний","Маржинальний","Сезонний","Стратегічний"},0),Settings!$D$78,Settings!$D$80,Settings!$D$82,Settings!$D$84,Settings!$D$86) | AQ23: =CHOOSE(MATCH(IF($U23="","Основний",$U23),{"Трафіковий","Основний","Маржинальний","Сезонний","Стратегічний"},0),Settings!$F$78,Settings!$F$80,Settings!$F$82,Settings!$F$84,Settings!$F$86) | AR23: =CHOOSE(MATCH(IF($U23="","Основний",$U23),{"Трафіковий","Основний","Маржинальний","Сезонний","Стратегічний"},0),Settings!$G$78,Settings!$G$80,Settings!$G$82,Settings!$G$84,Settings!$G$86) | AS23: =CHOOSE(MATCH(IF($U23="","Основний",$U23),{"Трафіковий","Основний","Маржинальний","Сезонний","Стратегічний"},0),Settings!$H$78,Settings!$H$80,Settings!$H$82,Settings!$H$84,Settings!$H$86) | AT23: =CHOOSE(MATCH(IF($U23="","Основний",$U23),{"Трафіковий","Основний","Маржинальний","Сезонний","Стратегічний"},0),Settings!$I$78,Settings!$I$80,Settings!$I$82,Settings!$I$84,Settings!$I$86) | AV23: 1.35
B24: P3116 | C24: LED RECHARGEABLE METAL FLASHLIGHT 600 lm–2 000mAh | D24: Ліхтарі | E24: PC | F24: 14.249 | G24: 8513100000 | H24: 1.4 | I24: =IFERROR(F24*Settings!$B$2*H24*IF(AND(ISNUMBER(E24),E24>1),E24,1),"") | J24: =Settings!$B$66 | K24: =IFERROR(IF(T24="","",(T24*(1-AN24)*(1-Settings!$B$17)-I24)/(T24*(1-AN24)*(1-Settings!$B$17))),"") | L24: =IFERROR(IF(T24="","",(T24*(1-AO24)*(1-Settings!$C$17)-I24)/(T24*(1-AO24)*(1-Settings!$C$17))),"") | M24: =IFERROR(IF(T24="","",(T24*(1-AP24)*(1-Settings!$D$17)-I24)/(T24*(1-AP24)*(1-Settings!$D$17))),"") | N24: =IFERROR(IF(T24="","",(T24*(1-AQ24)*(1-Settings!$F$17)-I24)/(T24*(1-AQ24)*(1-Settings!$F$17))),"") | O24: =IFERROR(IF(T24="","",(T24*(1-AR24)*(1-Settings!$G$17)-I24)/(T24*(1-AR24)*(1-Settings!$G$17))),"") | P24: =IFERROR(IF(T24="","",(T24*(1-AS24)*(1-Settings!$H$17)-I24)/(T24*(1-AS24)*(1-Settings!$H$17))),"") | Q24: =IFERROR(IF(T24="","",(T24*(1-AT24)*(1-Settings!$I$68)*(1-Settings!$I$17)-I24)/(T24*(1-AT24)*(1-Settings!$I$68)*(1-Settings!$I$17))),"") | R24: =IFERROR(IF(OR(I24="",Z24>=1,Settings!$B$17>=1,AN24>=1),"",IF(MOD(ROUND(I24/(1-Z24)/(1-Settings!$B$17)/(1-AN24),0),10)=0,ROUND(I24/(1-Z24)/(1-Settings!$B$17)/(1-AN24),0)-1,IF(MOD(ROUND(I24/(1-Z24)/(1-Settings!$B$17)/(1-AN24),0),10)<=5,FLOOR(ROUND(I24/(1-Z24)/(1-Settings!$B$17)/(1-AN24),0),10)+6,FLOOR(ROUND(I24/(1-Z24)/(1-Settings!$B$17)/(1-AN24),0),10)+9))),"") | S24: 1800 | T24: =IF(S24<>"", IF(MOD(S24,10)=0,S24-1,IF(MOD(S24,10)<=5,FLOOR(S24,10)+6,FLOOR(S24,10)+9)), R24) | U24: Основний | X24: =IFERROR(IF(OR(V24="",W24="",T24=""),"", IF(T24>W24,"Дорогий",IF(T24<V24,"Дешевий","У ринку"))),"") | Z24: =CHOOSE(MATCH(IF($U24="","Основний",$U24),{"Трафіковий","Основний","Маржинальний","Сезонний","Стратегічний"},0),0.16,0.19,0.24,0.23,0.28) | AA24: =CHOOSE(MATCH(IF($U24="","Основний",$U24),{"Трафіковий","Основний","Маржинальний","Сезонний","Стратегічний"},0),0.18,0.21,0.26,0.25,0.3) | AB24: =CHOOSE(MATCH(IF($U24="","Основний",$U24),{"Трафіковий","Основний","Маржинальний","Сезонний","Стратегічний"},0),0.19,0.22,0.28,0.26,0.32) | AC24: =CHOOSE(MATCH(IF($U24="","Основний",$U24),{"Трафіковий","Основний","Маржинальний","Сезонний","Стратегічний"},0),0.17,0.2,0.25,0.24,0.28) | AD24: =CHOOSE(MATCH(IF($U24="","Основний",$U24),{"Трафіковий","Основний","Маржинальний","Сезонний","Стратегічний"},0),0.18,0.21,0.26,0.25,0.3) | AE24: =CHOOSE(MATCH(IF($U24="","Основний",$U24),{"Трафіковий","Основний","Маржинальний","Сезонний","Стратегічний"},0),0.18,0.2,0.28,0.27,0.32) | AF24: =CHOOSE(MATCH(IF($U24="","Основний",$U24),{"Трафіковий","Основний","Маржинальний","Сезонний","Стратегічний"},0),0.15,0.175,0.22,0.21,0.25) | AG24: =CHOOSE(MATCH(IF($U24="","Основний",$U24),{"Трафіковий","Основний","Маржинальний","Сезонний","Стратегічний"},0),0.13,0.16,0.21,0.2,0.25) | AH24: =CHOOSE(MATCH(IF($U24="","Основний",$U24),{"Трафіковий","Основний","Маржинальний","Сезонний","Стратегічний"},0),0.15,0.18,0.23,0.22,0.27) | AI24: =CHOOSE(MATCH(IF($U24="","Основний",$U24),{"Трафіковий","Основний","Маржинальний","Сезонний","Стратегічний"},0),0.16,0.19,0.25,0.23,0.29) | AJ24: =CHOOSE(MATCH(IF($U24="","Основний",$U24),{"Трафіковий","Основний","Маржинальний","Сезонний","Стратегічний"},0),0.14,0.17,0.22,0.21,0.25) | AK24: =CHOOSE(MATCH(IF($U24="","Основний",$U24),{"Трафіковий","Основний","Маржинальний","Сезонний","Стратегічний"},0),0.15,0.18,0.23,0.22,0.27) | AL24: =CHOOSE(MATCH(IF($U24="","Основний",$U24),{"Трафіковий","Основний","Маржинальний","Сезонний","Стратегічний"},0),0.15,0.17,0.25,0.24,0.29) | AM24: =CHOOSE(MATCH(IF($U24="","Основний",$U24),{"Трафіковий","Основний","Маржинальний","Сезонний","Стратегічний"},0),0.12,0.145,0.19,0.18,0.22) | AN24: =CHOOSE(MATCH(IF($U24="","Основний",$U24),{"Трафіковий","Основний","Маржинальний","Сезонний","Стратегічний"},0),Settings!$B$78,Settings!$B$80,Settings!$B$82,Settings!$B$84,Settings!$B$86) | AO24: =CHOOSE(MATCH(IF($U24="","Основний",$U24),{"Трафіковий","Основний","Маржинальний","Сезонний","Стратегічний"},0),Settings!$C$78,Settings!$C$80,Settings!$C$82,Settings!$C$84,Settings!$C$86) | AP24: =CHOOSE(MATCH(IF($U24="","Основний",$U24),{"Трафіковий","Основний","Маржинальний","Сезонний","Стратегічний"},0),Settings!$D$78,Settings!$D$80,Settings!$D$82,Settings!$D$84,Settings!$D$86) | AQ24: =CHOOSE(MATCH(IF($U24="","Основний",$U24),{"Трафіковий","Основний","Маржинальний","Сезонний","Стратегічний"},0),Settings!$F$78,Settings!$F$80,Settings!$F$82,Settings!$F$84,Settings!$F$86) | AR24: =CHOOSE(MATCH(IF($U24="","Основний",$U24),{"Трафіковий","Основний","Маржинальний","Сезонний","Стратегічний"},0),Settings!$G$78,Settings!$G$80,Settings!$G$82,Settings!$G$84,Settings!$G$86) | AS24: =CHOOSE(MATCH(IF($U24="","Основний",$U24),{"Трафіковий","Основний","Маржинальний","Сезонний","Стратегічний"},0),Settings!$H$78,Settings!$H$80,Settings!$H$82,Settings!$H$84,Settings!$H$86) | AT24: =CHOOSE(MATCH(IF($U24="","Основний",$U24),{"Трафіковий","Основний","Маржинальний","Сезонний","Стратегічний"},0),Settings!$I$78,Settings!$I$80,Settings!$I$82,Settings!$I$84,Settings!$I$86) | AV24: 1.35
A25: NEW | B25: P3118 | C25: LED RECHARGEABLE METAL FLASHLIGHT 600lm,1200mAh | D25: Ліхтарі | E25: PC | F25: 7.712 | G25: 8513100000 | H25: 1.4 | I25: =IFERROR(F25*Settings!$B$2*H25*IF(AND(ISNUMBER(E25),E25>1),E25,1),"") | J25: =Settings!$B$66 | K25: =IFERROR(IF(T25="","",(T25*(1-AN25)*(1-Settings!$B$17)-I25)/(T25*(1-AN25)*(1-Settings!$B$17))),"") | L25: =IFERROR(IF(T25="","",(T25*(1-AO25)*(1-Settings!$C$17)-I25)/(T25*(1-AO25)*(1-Settings!$C$17))),"") | M25: =IFERROR(IF(T25="","",(T25*(1-AP25)*(1-Settings!$D$17)-I25)/(T25*(1-AP25)*(1-Settings!$D$17))),"") | N25: =IFERROR(IF(T25="","",(T25*(1-AQ25)*(1-Settings!$F$17)-I25)/(T25*(1-AQ25)*(1-Settings!$F$17))),"") | O25: =IFERROR(IF(T25="","",(T25*(1-AR25)*(1-Settings!$G$17)-I25)/(T25*(1-AR25)*(1-Settings!$G$17))),"") | P25: =IFERROR(IF(T25="","",(T25*(1-AS25)*(1-Settings!$H$17)-I25)/(T25*(1-AS25)*(1-Settings!$H$17))),"") | Q25: =IFERROR(IF(T25="","",(T25*(1-AT25)*(1-Settings!$I$68)*(1-Settings!$I$17)-I25)/(T25*(1-AT25)*(1-Settings!$I$68)*(1-Settings!$I$17))),"") | R25: =IFERROR(IF(OR(I25="",Z25>=1,Settings!$B$17>=1,AN25>=1),"",IF(MOD(ROUND(I25/(1-Z25)/(1-Settings!$B$17)/(1-AN25),0),10)=0,ROUND(I25/(1-Z25)/(1-Settings!$B$17)/(1-AN25),0)-1,IF(MOD(ROUND(I25/(1-Z25)/(1-Settings!$B$17)/(1-AN25),0),10)<=5,FLOOR(ROUND(I25/(1-Z25)/(1-Settings!$B$17)/(1-AN25),0),10)+6,FLOOR(ROUND(I25/(1-Z25)/(1-Settings!$B$17)/(1-AN25),0),10)+9))),"") | S25: 1000 | T25: =IF(S25<>"", IF(MOD(S25,10)=0,S25-1,IF(MOD(S25,10)<=5,FLOOR(S25,10)+6,FLOOR(S25,10)+9)), R25) | U25: Основний | X25: =IFERROR(IF(OR(V25="",W25="",T25=""),"", IF(T25>W25,"Дорогий",IF(T25<V25,"Дешевий","У ринку"))),"") | Z25: =CHOOSE(MATCH(IF($U25="","Основний",$U25),{"Трафіковий","Основний","Маржинальний","Сезонний","Стратегічний"},0),0.16,0.19,0.24,0.23,0.28) | AA25: =CHOOSE(MATCH(IF($U25="","Основний",$U25),{"Трафіковий","Основний","Маржинальний","Сезонний","Стратегічний"},0),0.18,0.21,0.26,0.25,0.3) | AB25: =CHOOSE(MATCH(IF($U25="","Основний",$U25),{"Трафіковий","Основний","Маржинальний","Сезонний","Стратегічний"},0),0.19,0.22,0.28,0.26,0.32) | AC25: =CHOOSE(MATCH(IF($U25="","Основний",$U25),{"Трафіковий","Основний","Маржинальний","Сезонний","Стратегічний"},0),0.17,0.2,0.25,0.24,0.28) | AD25: =CHOOSE(MATCH(IF($U25="","Основний",$U25),{"Трафіковий","Основний","Маржинальний","Сезонний","Стратегічний"},0),0.18,0.21,0.26,0.25,0.3) | AE25: =CHOOSE(MATCH(IF($U25="","Основний",$U25),{"Трафіковий","Основний","Маржинальний","Сезонний","Стратегічний"},0),0.18,0.2,0.28,0.27,0.32) | AF25: =CHOOSE(MATCH(IF($U25="","Основний",$U25),{"Трафіковий","Основний","Маржинальний","Сезонний","Стратегічний"},0),0.15,0.175,0.22,0.21,0.25) | AG25: =CHOOSE(MATCH(IF($U25="","Основний",$U25),{"Трафіковий","Основний","Маржинальний","Сезонний","Стратегічний"},0),0.13,0.16,0.21,0.2,0.25) | AH25: =CHOOSE(MATCH(IF($U25="","Основний",$U25),{"Трафіковий","Основний","Маржинальний","Сезонний","Стратегічний"},0),0.15,0.18,0.23,0.22,0.27) | AI25: =CHOOSE(MATCH(IF($U25="","Основний",$U25),{"Трафіковий","Основний","Маржинальний","Сезонний","Стратегічний"},0),0.16,0.19,0.25,0.23,0.29) | AJ25: =CHOOSE(MATCH(IF($U25="","Основний",$U25),{"Трафіковий","Основний","Маржинальний","Сезонний","Стратегічний"},0),0.14,0.17,0.22,0.21,0.25) | AK25: =CHOOSE(MATCH(IF($U25="","Основний",$U25),{"Трафіковий","Основний","Маржинальний","Сезонний","Стратегічний"},0),0.15,0.18,0.23,0.22,0.27) | AL25: =CHOOSE(MATCH(IF($U25="","Основний",$U25),{"Трафіковий","Основний","Маржинальний","Сезонний","Стратегічний"},0),0.15,0.17,0.25,0.24,0.29) | AM25: =CHOOSE(MATCH(IF($U25="","Основний",$U25),{"Трафіковий","Основний","Маржинальний","Сезонний","Стратегічний"},0),0.12,0.145,0.19,0.18,0.22) | AN25: =CHOOSE(MATCH(IF($U25="","Основний",$U25),{"Трафіковий","Основний","Маржинальний","Сезонний","Стратегічний"},0),Settings!$B$78,Settings!$B$80,Settings!$B$82,Settings!$B$84,Settings!$B$86) | AO25: =CHOOSE(MATCH(IF($U25="","Основний",$U25),{"Трафіковий","Основний","Маржинальний","Сезонний","Стратегічний"},0),Settings!$C$78,Settings!$C$80,Settings!$C$82,Settings!$C$84,Settings!$C$86) | AP25: =CHOOSE(MATCH(IF($U25="","Основний",$U25),{"Трафіковий","Основний","Маржинальний","Сезонний","Стратегічний"},0),Settings!$D$78,Settings!$D$80,Settings!$D$82,Settings!$D$84,Settings!$D$86) | AQ25: =CHOOSE(MATCH(IF($U25="","Основний",$U25),{"Трафіковий","Основний","Маржинальний","Сезонний","Стратегічний"},0),Settings!$F$78,Settings!$F$80,Settings!$F$82,Settings!$F$84,Settings!$F$86) | AR25: =CHOOSE(MATCH(IF($U25="","Основний",$U25),{"Трафіковий","Основний","Маржинальний","Сезонний","Стратегічний"},0),Settings!$G$78,Settings!$G$80,Settings!$G$82,Settings!$G$84,Settings!$G$86) | AS25: =CHOOSE(MATCH(IF($U25="","Основний",$U25),{"Трафіковий","Основний","Маржинальний","Сезонний","Стратегічний"},0),Settings!$H$78,Settings!$H$80,Settings!$H$82,Settings!$H$84,Settings!$H$86) | AT25: =CHOOSE(MATCH(IF($U25="","Основний",$U25),{"Трафіковий","Основний","Маржинальний","Сезонний","Стратегічний"},0),Settings!$I$78,Settings!$I$80,Settings!$I$82,Settings!$I$84,Settings!$I$86) | AV25: 1.35
A26: NEW | B26: P3120 | C26: LED RECHAR. METAL FLASHLIGHT SMALL 350 lm, 700mAh | D26: Ліхтарі | E26: PC | F26: 6.551 | G26: 8513100000 | H26: 1.4 | I26: =IFERROR(F26*Settings!$B$2*H26*IF(AND(ISNUMBER(E26),E26>1),E26,1),"") | J26: =Settings!$B$66 | K26: =IFERROR(IF(T26="","",(T26*(1-AN26)*(1-Settings!$B$17)-I26)/(T26*(1-AN26)*(1-Settings!$B$17))),"") | L26: =IFERROR(IF(T26="","",(T26*(1-AO26)*(1-Settings!$C$17)-I26)/(T26*(1-AO26)*(1-Settings!$C$17))),"") | M26: =IFERROR(IF(T26="","",(T26*(1-AP26)*(1-Settings!$D$17)-I26)/(T26*(1-AP26)*(1-Settings!$D$17))),"") | N26: =IFERROR(IF(T26="","",(T26*(1-AQ26)*(1-Settings!$F$17)-I26)/(T26*(1-AQ26)*(1-Settings!$F$17))),"") | O26: =IFERROR(IF(T26="","",(T26*(1-AR26)*(1-Settings!$G$17)-I26)/(T26*(1-AR26)*(1-Settings!$G$17))),"") | P26: =IFERROR(IF(T26="","",(T26*(1-AS26)*(1-Settings!$H$17)-I26)/(T26*(1-AS26)*(1-Settings!$H$17))),"") | Q26: =IFERROR(IF(T26="","",(T26*(1-AT26)*(1-Settings!$I$68)*(1-Settings!$I$17)-I26)/(T26*(1-AT26)*(1-Settings!$I$68)*(1-Settings!$I$17))),"") | R26: =IFERROR(IF(OR(I26="",Z26>=1,Settings!$B$17>=1,AN26>=1),"",IF(MOD(ROUND(I26/(1-Z26)/(1-Settings!$B$17)/(1-AN26),0),10)=0,ROUND(I26/(1-Z26)/(1-Settings!$B$17)/(1-AN26),0)-1,IF(MOD(ROUND(I26/(1-Z26)/(1-Settings!$B$17)/(1-AN26),0),10)<=5,FLOOR(ROUND(I26/(1-Z26)/(1-Settings!$B$17)/(1-AN26),0),10)+6,FLOOR(ROUND(I26/(1-Z26)/(1-Settings!$B$17)/(1-AN26),0),10)+9))),"") | S26: 850 | T26: =IF(S26<>"", IF(MOD(S26,10)=0,S26-1,IF(MOD(S26,10)<=5,FLOOR(S26,10)+6,FLOOR(S26,10)+9)), R26) | U26: Основний | X26: =IFERROR(IF(OR(V26="",W26="",T26=""),"", IF(T26>W26,"Дорогий",IF(T26<V26,"Дешевий","У ринку"))),"") | Z26: =CHOOSE(MATCH(IF($U26="","Основний",$U26),{"Трафіковий","Основний","Маржинальний","Сезонний","Стратегічний"},0),0.16,0.19,0.24,0.23,0.28) | AA26: =CHOOSE(MATCH(IF($U26="","Основний",$U26),{"Трафіковий","Основний","Маржинальний","Сезонний","Стратегічний"},0),0.18,0.21,0.26,0.25,0.3) | AB26: =CHOOSE(MATCH(IF($U26="","Основний",$U26),{"Трафіковий","Основний","Маржинальний","Сезонний","Стратегічний"},0),0.19,0.22,0.28,0.26,0.32) | AC26: =CHOOSE(MATCH(IF($U26="","Основний",$U26),{"Трафіковий","Основний","Маржинальний","Сезонний","Стратегічний"},0),0.17,0.2,0.25,0.24,0.28) | AD26: =CHOOSE(MATCH(IF($U26="","Основний",$U26),{"Трафіковий","Основний","Маржинальний","Сезонний","Стратегічний"},0),0.18,0.21,0.26,0.25,0.3) | AE26: =CHOOSE(MATCH(IF($U26="","Основний",$U26),{"Трафіковий","Основний","Маржинальний","Сезонний","Стратегічний"},0),0.18,0.2,0.28,0.27,0.32) | AF26: =CHOOSE(MATCH(IF($U26="","Основний",$U26),{"Трафіковий","Основний","Маржинальний","Сезонний","Стратегічний"},0),0.15,0.175,0.22,0.21,0.25) | AG26: =CHOOSE(MATCH(IF($U26="","Основний",$U26),{"Трафіковий","Основний","Маржинальний","Сезонний","Стратегічний"},0),0.13,0.16,0.21,0.2,0.25) | AH26: =CHOOSE(MATCH(IF($U26="","Основний",$U26),{"Трафіковий","Основний","Маржинальний","Сезонний","Стратегічний"},0),0.15,0.18,0.23,0.22,0.27) | AI26: =CHOOSE(MATCH(IF($U26="","Основний",$U26),{"Трафіковий","Основний","Маржинальний","Сезонний","Стратегічний"},0),0.16,0.19,0.25,0.23,0.29) | AJ26: =CHOOSE(MATCH(IF($U26="","Основний",$U26),{"Трафіковий","Основний","Маржинальний","Сезонний","Стратегічний"},0),0.14,0.17,0.22,0.21,0.25) | AK26: =CHOOSE(MATCH(IF($U26="","Основний",$U26),{"Трафіковий","Основний","Маржинальний","Сезонний","Стратегічний"},0),0.15,0.18,0.23,0.22,0.27) | AL26: =CHOOSE(MATCH(IF($U26="","Основний",$U26),{"Трафіковий","Основний","Маржинальний","Сезонний","Стратегічний"},0),0.15,0.17,0.25,0.24,0.29) | AM26: =CHOOSE(MATCH(IF($U26="","Основний",$U26),{"Трафіковий","Основний","Маржинальний","Сезонний","Стратегічний"},0),0.12,0.145,0.19,0.18,0.22) | AN26: =CHOOSE(MATCH(IF($U26="","Основний",$U26),{"Трафіковий","Основний","Маржинальний","Сезонний","Стратегічний"},0),Settings!$B$78,Settings!$B$80,Settings!$B$82,Settings!$B$84,Settings!$B$86) | AO26: =CHOOSE(MATCH(IF($U26="","Основний",$U26),{"Трафіковий","Основний","Маржинальний","Сезонний","Стратегічний"},0),Settings!$C$78,Settings!$C$80,Settings!$C$82,Settings!$C$84,Settings!$C$86) | AP26: =CHOOSE(MATCH(IF($U26="","Основний",$U26),{"Трафіковий","Основний","Маржинальний","Сезонний","Стратегічний"},0),Settings!$D$78,Settings!$D$80,Settings!$D$82,Settings!$D$84,Settings!$D$86) | AQ26: =CHOOSE(MATCH(IF($U26="","Основний",$U26),{"Трафіковий","Основний","Маржинальний","Сезонний","Стратегічний"},0),Settings!$F$78,Settings!$F$80,Settings!$F$82,Settings!$F$84,Settings!$F$86) | AR26: =CHOOSE(MATCH(IF($U26="","Основний",$U26),{"Трафіковий","Основний","Маржинальний","Сезонний","Стратегічний"},0),Settings!$G$78,Settings!$G$80,Settings!$G$82,Settings!$G$84,Settings!$G$86) | AS26: =CHOOSE(MATCH(IF($U26="","Основний",$U26),{"Трафіковий","Основний","Маржинальний","Сезонний","Стратегічний"},0),Settings!$H$78,Settings!$H$80,Settings!$H$82,Settings!$H$84,Settings!$H$86) | AT26: =CHOOSE(MATCH(IF($U26="","Основний",$U26),{"Трафіковий","Основний","Маржинальний","Сезонний","Стратегічний"},0),Settings!$I$78,Settings!$I$80,Settings!$I$82,Settings!$I$84,Settings!$I$86) | AV26: 1.35
A27: NEW | B27: P3121 | C27: LED RECHAR.METAL FLASHLIGHT MED 1300lm,2200mAh | D27: Ліхтарі | E27: PC | F27: 9.323 | G27: 8513100000 | H27: 1.4 | I27: =IFERROR(F27*Settings!$B$2*H27*IF(AND(ISNUMBER(E27),E27>1),E27,1),"") | J27: =Settings!$B$66 | K27: =IFERROR(IF(T27="","",(T27*(1-AN27)*(1-Settings!$B$17)-I27)/(T27*(1-AN27)*(1-Settings!$B$17))),"") | L27: =IFERROR(IF(T27="","",(T27*(1-AO27)*(1-Settings!$C$17)-I27)/(T27*(1-AO27)*(1-Settings!$C$17))),"") | M27: =IFERROR(IF(T27="","",(T27*(1-AP27)*(1-Settings!$D$17)-I27)/(T27*(1-AP27)*(1-Settings!$D$17))),"") | N27: =IFERROR(IF(T27="","",(T27*(1-AQ27)*(1-Settings!$F$17)-I27)/(T27*(1-AQ27)*(1-Settings!$F$17))),"") | O27: =IFERROR(IF(T27="","",(T27*(1-AR27)*(1-Settings!$G$17)-I27)/(T27*(1-AR27)*(1-Settings!$G$17))),"") | P27: =IFERROR(IF(T27="","",(T27*(1-AS27)*(1-Settings!$H$17)-I27)/(T27*(1-AS27)*(1-Settings!$H$17))),"") | Q27: =IFERROR(IF(T27="","",(T27*(1-AT27)*(1-Settings!$I$68)*(1-Settings!$I$17)-I27)/(T27*(1-AT27)*(1-Settings!$I$68)*(1-Settings!$I$17))),"") | R27: =IFERROR(IF(OR(I27="",Z27>=1,Settings!$B$17>=1,AN27>=1),"",IF(MOD(ROUND(I27/(1-Z27)/(1-Settings!$B$17)/(1-AN27),0),10)=0,ROUND(I27/(1-Z27)/(1-Settings!$B$17)/(1-AN27),0)-1,IF(MOD(ROUND(I27/(1-Z27)/(1-Settings!$B$17)/(1-AN27),0),10)<=5,FLOOR(ROUND(I27/(1-Z27)/(1-Settings!$B$17)/(1-AN27),0),10)+6,FLOOR(ROUND(I27/(1-Z27)/(1-Settings!$B$17)/(1-AN27),0),10)+9))),"") | S27: 1200 | T27: =IF(S27<>"", IF(MOD(S27,10)=0,S27-1,IF(MOD(S27,10)<=5,FLOOR(S27,10)+6,FLOOR(S27,10)+9)), R27) | U27: Основний | X27: =IFERROR(IF(OR(V27="",W27="",T27=""),"", IF(T27>W27,"Дорогий",IF(T27<V27,"Дешевий","У ринку"))),"") | Z27: =CHOOSE(MATCH(IF($U27="","Основний",$U27),{"Трафіковий","Основний","Маржинальний","Сезонний","Стратегічний"},0),0.16,0.19,0.24,0.23,0.28) | AA27: =CHOOSE(MATCH(IF($U27="","Основний",$U27),{"Трафіковий","Основний","Маржинальний","Сезонний","Стратегічний"},0),0.18,0.21,0.26,0.25,0.3) | AB27: =CHOOSE(MATCH(IF($U27="","Основний",$U27),{"Трафіковий","Основний","Маржинальний","Сезонний","Стратегічний"},0),0.19,0.22,0.28,0.26,0.32) | AC27: =CHOOSE(MATCH(IF($U27="","Основний",$U27),{"Трафіковий","Основний","Маржинальний","Сезонний","Стратегічний"},0),0.17,0.2,0.25,0.24,0.28) | AD27: =CHOOSE(MATCH(IF($U27="","Основний",$U27),{"Трафіковий","Основний","Маржинальний","Сезонний","Стратегічний"},0),0.18,0.21,0.26,0.25,0.3) | AE27: =CHOOSE(MATCH(IF($U27="","Основний",$U27),{"Трафіковий","Основний","Маржинальний","Сезонний","Стратегічний"},0),0.18,0.2,0.28,0.27,0.32) | AF27: =CHOOSE(MATCH(IF($U27="","Основний",$U27),{"Трафіковий","Основний","Маржинальний","Сезонний","Стратегічний"},0),0.15,0.175,0.22,0.21,0.25) | AG27: =CHOOSE(MATCH(IF($U27="","Основний",$U27),{"Трафіковий","Основний","Маржинальний","Сезонний","Стратегічний"},0),0.13,0.16,0.21,0.2,0.25) | AH27: =CHOOSE(MATCH(IF($U27="","Основний",$U27),{"Трафіковий","Основний","Маржинальний","Сезонний","Стратегічний"},0),0.15,0.18,0.23,0.22,0.27) | AI27: =CHOOSE(MATCH(IF($U27="","Основний",$U27),{"Трафіковий","Основний","Маржинальний","Сезонний","Стратегічний"},0),0.16,0.19,0.25,0.23,0.29) | AJ27: =CHOOSE(MATCH(IF($U27="","Основний",$U27),{"Трафіковий","Основний","Маржинальний","Сезонний","Стратегічний"},0),0.14,0.17,0.22,0.21,0.25) | AK27: =CHOOSE(MATCH(IF($U27="","Основний",$U27),{"Трафіковий","Основний","Маржинальний","Сезонний","Стратегічний"},0),0.15,0.18,0.23,0.22,0.27) | AL27: =CHOOSE(MATCH(IF($U27="","Основний",$U27),{"Трафіковий","Основний","Маржинальний","Сезонний","Стратегічний"},0),0.15,0.17,0.25,0.24,0.29) | AM27: =CHOOSE(MATCH(IF($U27="","Основний",$U27),{"Трафіковий","Основний","Маржинальний","Сезонний","Стратегічний"},0),0.12,0.145,0.19,0.18,0.22) | AN27: =CHOOSE(MATCH(IF($U27="","Основний",$U27),{"Трафіковий","Основний","Маржинальний","Сезонний","Стратегічний"},0),Settings!$B$78,Settings!$B$80,Settings!$B$82,Settings!$B$84,Settings!$B$86) | AO27: =CHOOSE(MATCH(IF($U27="","Основний",$U27),{"Трафіковий","Основний","Маржинальний","Сезонний","Стратегічний"},0),Settings!$C$78,Settings!$C$80,Settings!$C$82,Settings!$C$84,Settings!$C$86) | AP27: =CHOOSE(MATCH(IF($U27="","Основний",$U27),{"Трафіковий","Основний","Маржинальний","Сезонний","Стратегічний"},0),Settings!$D$78,Settings!$D$80,Settings!$D$82,Settings!$D$84,Settings!$D$86) | AQ27: =CHOOSE(MATCH(IF($U27="","Основний",$U27),{"Трафіковий","Основний","Маржинальний","Сезонний","Стратегічний"},0),Settings!$F$78,Settings!$F$80,Settings!$F$82,Settings!$F$84,Settings!$F$86) | AR27: =CHOOSE(MATCH(IF($U27="","Основний",$U27),{"Трафіковий","Основний","Маржинальний","Сезонний","Стратегічний"},0),Settings!$G$78,Settings!$G$80,Settings!$G$82,Settings!$G$84,Settings!$G$86) | AS27: =CHOOSE(MATCH(IF($U27="","Основний",$U27),{"Трафіковий","Основний","Маржинальний","Сезонний","Стратегічний"},0),Settings!$H$78,Settings!$H$80,Settings!$H$82,Settings!$H$84,Settings!$H$86) | AT27: =CHOOSE(MATCH(IF($U27="","Основний",$U27),{"Трафіковий","Основний","Маржинальний","Сезонний","Стратегічний"},0),Settings!$I$78,Settings!$I$80,Settings!$I$82,Settings!$I$84,Settings!$I$86) | AV27: 1.35
A28: NEW | B28: P3122 | C28: LED RECHAR.METAL FLASHLIGHT LARGE 3000lm, 5 000mAh | D28: Ліхтарі | E28: PC | F28: 16.781 | G28: 8513100000 | H28: 1.4 | I28: =IFERROR(F28*Settings!$B$2*H28*IF(AND(ISNUMBER(E28),E28>1),E28,1),"") | J28: =Settings!$B$66 | K28: =IFERROR(IF(T28="","",(T28*(1-AN28)*(1-Settings!$B$17)-I28)/(T28*(1-AN28)*(1-Settings!$B$17))),"") | L28: =IFERROR(IF(T28="","",(T28*(1-AO28)*(1-Settings!$C$17)-I28)/(T28*(1-AO28)*(1-Settings!$C$17))),"") | M28: =IFERROR(IF(T28="","",(T28*(1-AP28)*(1-Settings!$D$17)-I28)/(T28*(1-AP28)*(1-Settings!$D$17))),"") | N28: =IFERROR(IF(T28="","",(T28*(1-AQ28)*(1-Settings!$F$17)-I28)/(T28*(1-AQ28)*(1-Settings!$F$17))),"") | O28: =IFERROR(IF(T28="","",(T28*(1-AR28)*(1-Settings!$G$17)-I28)/(T28*(1-AR28)*(1-Settings!$G$17))),"") | P28: =IFERROR(IF(T28="","",(T28*(1-AS28)*(1-Settings!$H$17)-I28)/(T28*(1-AS28)*(1-Settings!$H$17))),"") | Q28: =IFERROR(IF(T28="","",(T28*(1-AT28)*(1-Settings!$I$68)*(1-Settings!$I$17)-I28)/(T28*(1-AT28)*(1-Settings!$I$68)*(1-Settings!$I$17))),"") | R28: =IFERROR(IF(OR(I28="",Z28>=1,Settings!$B$17>=1,AN28>=1),"",IF(MOD(ROUND(I28/(1-Z28)/(1-Settings!$B$17)/(1-AN28),0),10)=0,ROUND(I28/(1-Z28)/(1-Settings!$B$17)/(1-AN28),0)-1,IF(MOD(ROUND(I28/(1-Z28)/(1-Settings!$B$17)/(1-AN28),0),10)<=5,FLOOR(ROUND(I28/(1-Z28)/(1-Settings!$B$17)/(1-AN28),0),10)+6,FLOOR(ROUND(I28/(1-Z28)/(1-Settings!$B$17)/(1-AN28),0),10)+9))),"") | S28: 2160 | T28: =IF(S28<>"", IF(MOD(S28,10)=0,S28-1,IF(MOD(S28,10)<=5,FLOOR(S28,10)+6,FLOOR(S28,10)+9)), R28) | U28: Основний | X28: =IFERROR(IF(OR(V28="",W28="",T28=""),"", IF(T28>W28,"Дорогий",IF(T28<V28,"Дешевий","У ринку"))),"") | Z28: =CHOOSE(MATCH(IF($U28="","Основний",$U28),{"Трафіковий","Основний","Маржинальний","Сезонний","Стратегічний"},0),0.16,0.19,0.24,0.23,0.28) | AA28: =CHOOSE(MATCH(IF($U28="","Основний",$U28),{"Трафіковий","Основний","Маржинальний","Сезонний","Стратегічний"},0),0.18,0.21,0.26,0.25,0.3) | AB28: =CHOOSE(MATCH(IF($U28="","Основний",$U28),{"Трафіковий","Основний","Маржинальний","Сезонний","Стратегічний"},0),0.19,0.22,0.28,0.26,0.32) | AC28: =CHOOSE(MATCH(IF($U28="","Основний",$U28),{"Трафіковий","Основний","Маржинальний","Сезонний","Стратегічний"},0),0.17,0.2,0.25,0.24,0.28) | AD28: =CHOOSE(MATCH(IF($U28="","Основний",$U28),{"Трафіковий","Основний","Маржинальний","Сезонний","Стратегічний"},0),0.18,0.21,0.26,0.25,0.3) | AE28: =CHOOSE(MATCH(IF($U28="","Основний",$U28),{"Трафіковий","Основний","Маржинальний","Сезонний","Стратегічний"},0),0.18,0.2,0.28,0.27,0.32) | AF28: =CHOOSE(MATCH(IF($U28="","Основний",$U28),{"Трафіковий","Основний","Маржинальний","Сезонний","Стратегічний"},0),0.15,0.175,0.22,0.21,0.25) | AG28: =CHOOSE(MATCH(IF($U28="","Основний",$U28),{"Трафіковий","Основний","Маржинальний","Сезонний","Стратегічний"},0),0.13,0.16,0.21,0.2,0.25) | AH28: =CHOOSE(MATCH(IF($U28="","Основний",$U28),{"Трафіковий","Основний","Маржинальний","Сезонний","Стратегічний"},0),0.15,0.18,0.23,0.22,0.27) | AI28: =CHOOSE(MATCH(IF($U28="","Основний",$U28),{"Трафіковий","Основний","Маржинальний","Сезонний","Стратегічний"},0),0.16,0.19,0.25,0.23,0.29) | AJ28: =CHOOSE(MATCH(IF($U28="","Основний",$U28),{"Трафіковий","Основний","Маржинальний","Сезонний","Стратегічний"},0),0.14,0.17,0.22,0.21,0.25) | AK28: =CHOOSE(MATCH(IF($U28="","Основний",$U28),{"Трафіковий","Основний","Маржинальний","Сезонний","Стратегічний"},0),0.15,0.18,0.23,0.22,0.27) | AL28: =CHOOSE(MATCH(IF($U28="","Основний",$U28),{"Трафіковий","Основний","Маржинальний","Сезонний","Стратегічний"},0),0.15,0.17,0.25,0.24,0.29) | AM28: =CHOOSE(MATCH(IF($U28="","Основний",$U28),{"Трафіковий","Основний","Маржинальний","Сезонний","Стратегічний"},0),0.12,0.145,0.19,0.18,0.22) | AN28: =CHOOSE(MATCH(IF($U28="","Основний",$U28),{"Трафіковий","Основний","Маржинальний","Сезонний","Стратегічний"},0),Settings!$B$78,Settings!$B$80,Settings!$B$82,Settings!$B$84,Settings!$B$86) | AO28: =CHOOSE(MATCH(IF($U28="","Основний",$U28),{"Трафіковий","Основний","Маржинальний","Сезонний","Стратегічний"},0),Settings!$C$78,Settings!$C$80,Settings!$C$82,Settings!$C$84,Settings!$C$86) | AP28: =CHOOSE(MATCH(IF($U28="","Основний",$U28),{"Трафіковий","Основний","Маржинальний","Сезонний","Стратегічний"},0),Settings!$D$78,Settings!$D$80,Settings!$D$82,Settings!$D$84,Settings!$D$86) | AQ28: =CHOOSE(MATCH(IF($U28="","Основний",$U28),{"Трафіковий","Основний","Маржинальний","Сезонний","Стратегічний"},0),Settings!$F$78,Settings!$F$80,Settings!$F$82,Settings!$F$84,Settings!$F$86) | AR28: =CHOOSE(MATCH(IF($U28="","Основний",$U28),{"Трафіковий","Основний","Маржинальний","Сезонний","Стратегічний"},0),Settings!$G$78,Settings!$G$80,Settings!$G$82,Settings!$G$84,Settings!$G$86) | AS28: =CHOOSE(MATCH(IF($U28="","Основний",$U28),{"Трафіковий","Основний","Маржинальний","Сезонний","Стратегічний"},0),Settings!$H$78,Settings!$H$80,Settings!$H$82,Settings!$H$84,Settings!$H$86) | AT28: =CHOOSE(MATCH(IF($U28="","Основний",$U28),{"Трафіковий","Основний","Маржинальний","Сезонний","Стратегічний"},0),Settings!$I$78,Settings!$I$80,Settings!$I$82,Settings!$I$84,Settings!$I$86) | AV28: 1.35
A29: NEW | B29: P3214 | C29: LED + COB LED RECH. FLASHLIGHT 150 lm 1200mAh box | D29: Ліхтарі | E29: PC | F29: 3.591 | G29: 8513100000 | H29: 1.4 | I29: =IFERROR(F29*Settings!$B$2*H29*IF(AND(ISNUMBER(E29),E29>1),E29,1),"") | J29: =Settings!$B$66 | K29: =IFERROR(IF(T29="","",(T29*(1-AN29)*(1-Settings!$B$17)-I29)/(T29*(1-AN29)*(1-Settings!$B$17))),"") | L29: =IFERROR(IF(T29="","",(T29*(1-AO29)*(1-Settings!$C$17)-I29)/(T29*(1-AO29)*(1-Settings!$C$17))),"") | M29: =IFERROR(IF(T29="","",(T29*(1-AP29)*(1-Settings!$D$17)-I29)/(T29*(1-AP29)*(1-Settings!$D$17))),"") | N29: =IFERROR(IF(T29="","",(T29*(1-AQ29)*(1-Settings!$F$17)-I29)/(T29*(1-AQ29)*(1-Settings!$F$17))),"") | O29: =IFERROR(IF(T29="","",(T29*(1-AR29)*(1-Settings!$G$17)-I29)/(T29*(1-AR29)*(1-Settings!$G$17))),"") | P29: =IFERROR(IF(T29="","",(T29*(1-AS29)*(1-Settings!$H$17)-I29)/(T29*(1-AS29)*(1-Settings!$H$17))),"") | Q29: =IFERROR(IF(T29="","",(T29*(1-AT29)*(1-Settings!$I$68)*(1-Settings!$I$17)-I29)/(T29*(1-AT29)*(1-Settings!$I$68)*(1-Settings!$I$17))),"") | R29: =IFERROR(IF(OR(I29="",Z29>=1,Settings!$B$17>=1,AN29>=1),"",IF(MOD(ROUND(I29/(1-Z29)/(1-Settings!$B$17)/(1-AN29),0),10)=0,ROUND(I29/(1-Z29)/(1-Settings!$B$17)/(1-AN29),0)-1,IF(MOD(ROUND(I29/(1-Z29)/(1-Settings!$B$17)/(1-AN29),0),10)<=5,FLOOR(ROUND(I29/(1-Z29)/(1-Settings!$B$17)/(1-AN29),0),10)+6,FLOOR(ROUND(I29/(1-Z29)/(1-Settings!$B$17)/(1-AN29),0),10)+9))),"") | T29: =IF(S29<>"", IF(MOD(S29,10)=0,S29-1,IF(MOD(S29,10)<=5,FLOOR(S29,10)+6,FLOOR(S29,10)+9)), R29) | U29: Основний | X29: =IFERROR(IF(OR(V29="",W29="",T29=""),"", IF(T29>W29,"Дорогий",IF(T29<V29,"Дешевий","У ринку"))),"") | Z29: =CHOOSE(MATCH(IF($U29="","Основний",$U29),{"Трафіковий","Основний","Маржинальний","Сезонний","Стратегічний"},0),0.16,0.19,0.24,0.23,0.28) | AA29: =CHOOSE(MATCH(IF($U29="","Основний",$U29),{"Трафіковий","Основний","Маржинальний","Сезонний","Стратегічний"},0),0.18,0.21,0.26,0.25,0.3) | AB29: =CHOOSE(MATCH(IF($U29="","Основний",$U29),{"Трафіковий","Основний","Маржинальний","Сезонний","Стратегічний"},0),0.19,0.22,0.28,0.26,0.32) | AC29: =CHOOSE(MATCH(IF($U29="","Основний",$U29),{"Трафіковий","Основний","Маржинальний","Сезонний","Стратегічний"},0),0.17,0.2,0.25,0.24,0.28) | AD29: =CHOOSE(MATCH(IF($U29="","Основний",$U29),{"Трафіковий","Основний","Маржинальний","Сезонний","Стратегічний"},0),0.18,0.21,0.26,0.25,0.3) | AE29: =CHOOSE(MATCH(IF($U29="","Основний",$U29),{"Трафіковий","Основний","Маржинальний","Сезонний","Стратегічний"},0),0.18,0.2,0.28,0.27,0.32) | AF29: =CHOOSE(MATCH(IF($U29="","Основний",$U29),{"Трафіковий","Основний","Маржинальний","Сезонний","Стратегічний"},0),0.15,0.175,0.22,0.21,0.25) | AG29: =CHOOSE(MATCH(IF($U29="","Основний",$U29),{"Трафіковий","Основний","Маржинальний","Сезонний","Стратегічний"},0),0.13,0.16,0.21,0.2,0.25) | AH29: =CHOOSE(MATCH(IF($U29="","Основний",$U29),{"Трафіковий","Основний","Маржинальний","Сезонний","Стратегічний"},0),0.15,0.18,0.23,0.22,0.27) | AI29: =CHOOSE(MATCH(IF($U29="","Основний",$U29),{"Трафіковий","Основний","Маржинальний","Сезонний","Стратегічний"},0),0.16,0.19,0.25,0.23,0.29) | AJ29: =CHOOSE(MATCH(IF($U29="","Основний",$U29),{"Трафіковий","Основний","Маржинальний","Сезонний","Стратегічний"},0),0.14,0.17,0.22,0.21,0.25) | AK29: =CHOOSE(MATCH(IF($U29="","Основний",$U29),{"Трафіковий","Основний","Маржинальний","Сезонний","Стратегічний"},0),0.15,0.18,0.23,0.22,0.27) | AL29: =CHOOSE(MATCH(IF($U29="","Основний",$U29),{"Трафіковий","Основний","Маржинальний","Сезонний","Стратегічний"},0),0.15,0.17,0.25,0.24,0.29) | AM29: =CHOOSE(MATCH(IF($U29="","Основний",$U29),{"Трафіковий","Основний","Маржинальний","Сезонний","Стратегічний"},0),0.12,0.145,0.19,0.18,0.22) | AN29: =CHOOSE(MATCH(IF($U29="","Основний",$U29),{"Трафіковий","Основний","Маржинальний","Сезонний","Стратегічний"},0),Settings!$B$78,Settings!$B$80,Settings!$B$82,Settings!$B$84,Settings!$B$86) | AO29: =CHOOSE(MATCH(IF($U29="","Основний",$U29),{"Трафіковий","Основний","Маржинальний","Сезонний","Стратегічний"},0),Settings!$C$78,Settings!$C$80,Settings!$C$82,Settings!$C$84,Settings!$C$86) | AP29: =CHOOSE(MATCH(IF($U29="","Основний",$U29),{"Трафіковий","Основний","Маржинальний","Сезонний","Стратегічний"},0),Settings!$D$78,Settings!$D$80,Settings!$D$82,Settings!$D$84,Settings!$D$86) | AQ29: =CHOOSE(MATCH(IF($U29="","Основний",$U29),{"Трафіковий","Основний","Маржинальний","Сезонний","Стратегічний"},0),Settings!$F$78,Settings!$F$80,Settings!$F$82,Settings!$F$84,Settings!$F$86) | AR29: =CHOOSE(MATCH(IF($U29="","Основний",$U29),{"Трафіковий","Основний","Маржинальний","Сезонний","Стратегічний"},0),Settings!$G$78,Settings!$G$80,Settings!$G$82,Settings!$G$84,Settings!$G$86) | AS29: =CHOOSE(MATCH(IF($U29="","Основний",$U29),{"Трафіковий","Основний","Маржинальний","Сезонний","Стратегічний"},0),Settings!$H$78,Settings!$H$80,Settings!$H$82,Settings!$H$84,Settings!$H$86) | AT29: =CHOOSE(MATCH(IF($U29="","Основний",$U29),{"Трафіковий","Основний","Маржинальний","Сезонний","Стратегічний"},0),Settings!$I$78,Settings!$I$80,Settings!$I$82,Settings!$I$84,Settings!$I$86) | AV29: 1.35
A30: NEW | B30: P3215 | C30: LED+SMD LED RECH. FLASHLIGHT 80 lm 800mAh | D30: Ліхтарі | E30: PC | F30: 2.327 | G30: 8513100000 | H30: 1.4 | I30: =IFERROR(F30*Settings!$B$2*H30*IF(AND(ISNUMBER(E30),E30>1),E30,1),"") | J30: =Settings!$B$66 | K30: =IFERROR(IF(T30="","",(T30*(1-AN30)*(1-Settings!$B$17)-I30)/(T30*(1-AN30)*(1-Settings!$B$17))),"") | L30: =IFERROR(IF(T30="","",(T30*(1-AO30)*(1-Settings!$C$17)-I30)/(T30*(1-AO30)*(1-Settings!$C$17))),"") | M30: =IFERROR(IF(T30="","",(T30*(1-AP30)*(1-Settings!$D$17)-I30)/(T30*(1-AP30)*(1-Settings!$D$17))),"") | N30: =IFERROR(IF(T30="","",(T30*(1-AQ30)*(1-Settings!$F$17)-I30)/(T30*(1-AQ30)*(1-Settings!$F$17))),"") | O30: =IFERROR(IF(T30="","",(T30*(1-AR30)*(1-Settings!$G$17)-I30)/(T30*(1-AR30)*(1-Settings!$G$17))),"") | P30: =IFERROR(IF(T30="","",(T30*(1-AS30)*(1-Settings!$H$17)-I30)/(T30*(1-AS30)*(1-Settings!$H$17))),"") | Q30: =IFERROR(IF(T30="","",(T30*(1-AT30)*(1-Settings!$I$68)*(1-Settings!$I$17)-I30)/(T30*(1-AT30)*(1-Settings!$I$68)*(1-Settings!$I$17))),"") | R30: =IFERROR(IF(OR(I30="",Z30>=1,Settings!$B$17>=1,AN30>=1),"",IF(MOD(ROUND(I30/(1-Z30)/(1-Settings!$B$17)/(1-AN30),0),10)=0,ROUND(I30/(1-Z30)/(1-Settings!$B$17)/(1-AN30),0)-1,IF(MOD(ROUND(I30/(1-Z30)/(1-Settings!$B$17)/(1-AN30),0),10)<=5,FLOOR(ROUND(I30/(1-Z30)/(1-Settings!$B$17)/(1-AN30),0),10)+6,FLOOR(ROUND(I30/(1-Z30)/(1-Settings!$B$17)/(1-AN30),0),10)+9))),"") | S30: 320 | T30: =IF(S30<>"", IF(MOD(S30,10)=0,S30-1,IF(MOD(S30,10)<=5,FLOOR(S30,10)+6,FLOOR(S30,10)+9)), R30) | U30: Основний | X30: =IFERROR(IF(OR(V30="",W30="",T30=""),"", IF(T30>W30,"Дорогий",IF(T30<V30,"Дешевий","У ринку"))),"") | Z30: =CHOOSE(MATCH(IF($U30="","Основний",$U30),{"Трафіковий","Основний","Маржинальний","Сезонний","Стратегічний"},0),0.16,0.19,0.24,0.23,0.28) | AA30: =CHOOSE(MATCH(IF($U30="","Основний",$U30),{"Трафіковий","Основний","Маржинальний","Сезонний","Стратегічний"},0),0.18,0.21,0.26,0.25,0.3) | AB30: =CHOOSE(MATCH(IF($U30="","Основний",$U30),{"Трафіковий","Основний","Маржинальний","Сезонний","Стратегічний"},0),0.19,0.22,0.28,0.26,0.32) | AC30: =CHOOSE(MATCH(IF($U30="","Основний",$U30),{"Трафіковий","Основний","Маржинальний","Сезонний","Стратегічний"},0),0.17,0.2,0.25,0.24,0.28) | AD30: =CHOOSE(MATCH(IF($U30="","Основний",$U30),{"Трафіковий","Основний","Маржинальний","Сезонний","Стратегічний"},0),0.18,0.21,0.26,0.25,0.3) | AE30: =CHOOSE(MATCH(IF($U30="","Основний",$U30),{"Трафіковий","Основний","Маржинальний","Сезонний","Стратегічний"},0),0.18,0.2,0.28,0.27,0.32) | AF30: =CHOOSE(MATCH(IF($U30="","Основний",$U30),{"Трафіковий","Основний","Маржинальний","Сезонний","Стратегічний"},0),0.15,0.175,0.22,0.21,0.25) | AG30: =CHOOSE(MATCH(IF($U30="","Основний",$U30),{"Трафіковий","Основний","Маржинальний","Сезонний","Стратегічний"},0),0.13,0.16,0.21,0.2,0.25) | AH30: =CHOOSE(MATCH(IF($U30="","Основний",$U30),{"Трафіковий","Основний","Маржинальний","Сезонний","Стратегічний"},0),0.15,0.18,0.23,0.22,0.27) | AI30: =CHOOSE(MATCH(IF($U30="","Основний",$U30),{"Трафіковий","Основний","Маржинальний","Сезонний","Стратегічний"},0),0.16,0.19,0.25,0.23,0.29) | AJ30: =CHOOSE(MATCH(IF($U30="","Основний",$U30),{"Трафіковий","Основний","Маржинальний","Сезонний","Стратегічний"},0),0.14,0.17,0.22,0.21,0.25) | AK30: =CHOOSE(MATCH(IF($U30="","Основний",$U30),{"Трафіковий","Основний","Маржинальний","Сезонний","Стратегічний"},0),0.15,0.18,0.23,0.22,0.27) | AL30: =CHOOSE(MATCH(IF($U30="","Основний",$U30),{"Трафіковий","Основний","Маржинальний","Сезонний","Стратегічний"},0),0.15,0.17,0.25,0.24,0.29) | AM30: =CHOOSE(MATCH(IF($U30="","Основний",$U30),{"Трафіковий","Основний","Маржинальний","Сезонний","Стратегічний"},0),0.12,0.145,0.19,0.18,0.22) | AN30: =CHOOSE(MATCH(IF($U30="","Основний",$U30),{"Трафіковий","Основний","Маржинальний","Сезонний","Стратегічний"},0),Settings!$B$78,Settings!$B$80,Settings!$B$82,Settings!$B$84,Settings!$B$86) | AO30: =CHOOSE(MATCH(IF($U30="","Основний",$U30),{"Трафіковий","Основний","Маржинальний","Сезонний","Стратегічний"},0),Settings!$C$78,Settings!$C$80,Settings!$C$82,Settings!$C$84,Settings!$C$86) | AP30: =CHOOSE(MATCH(IF($U30="","Основний",$U30),{"Трафіковий","Основний","Маржинальний","Сезонний","Стратегічний"},0),Settings!$D$78,Settings!$D$80,Settings!$D$82,Settings!$D$84,Settings!$D$86) | AQ30: =CHOOSE(MATCH(IF($U30="","Основний",$U30),{"Трафіковий","Основний","Маржинальний","Сезонний","Стратегічний"},0),Settings!$F$78,Settings!$F$80,Settings!$F$82,Settings!$F$84,Settings!$F$86) | AR30: =CHOOSE(MATCH(IF($U30="","Основний",$U30),{"Трафіковий","Основний","Маржинальний","Сезонний","Стратегічний"},0),Settings!$G$78,Settings!$G$80,Settings!$G$82,Settings!$G$84,Settings!$G$86) | AS30: =CHOOSE(MATCH(IF($U30="","Основний",$U30),{"Трафіковий","Основний","Маржинальний","Сезонний","Стратегічний"},0),Settings!$H$78,Settings!$H$80,Settings!$H$82,Settings!$H$84,Settings!$H$86) | AT30: =CHOOSE(MATCH(IF($U30="","Основний",$U30),{"Трафіковий","Основний","Маржинальний","Сезонний","Стратегічний"},0),Settings!$I$78,Settings!$I$80,Settings!$I$82,Settings!$I$84,Settings!$I$86) | AV30: 1.35
A31: NEW | B31: P4720 | C31: LED+COB LED RECH. PLASTIC FLASHLIGHT 120LM 10PCS | D31: Ліхтарі | E31: PC | F31: 2.61 | G31: 8513100000 | H31: 1.4 | I31: =IFERROR(F31*Settings!$B$2*H31*IF(AND(ISNUMBER(E31),E31>1),E31,1),"") | J31: =Settings!$B$66 | K31: =IFERROR(IF(T31="","",(T31*(1-AN31)*(1-Settings!$B$17)-I31)/(T31*(1-AN31)*(1-Settings!$B$17))),"") | L31: =IFERROR(IF(T31="","",(T31*(1-AO31)*(1-Settings!$C$17)-I31)/(T31*(1-AO31)*(1-Settings!$C$17))),"") | M31: =IFERROR(IF(T31="","",(T31*(1-AP31)*(1-Settings!$D$17)-I31)/(T31*(1-AP31)*(1-Settings!$D$17))),"") | N31: =IFERROR(IF(T31="","",(T31*(1-AQ31)*(1-Settings!$F$17)-I31)/(T31*(1-AQ31)*(1-Settings!$F$17))),"") | O31: =IFERROR(IF(T31="","",(T31*(1-AR31)*(1-Settings!$G$17)-I31)/(T31*(1-AR31)*(1-Settings!$G$17))),"") | P31: =IFERROR(IF(T31="","",(T31*(1-AS31)*(1-Settings!$H$17)-I31)/(T31*(1-AS31)*(1-Settings!$H$17))),"") | Q31: =IFERROR(IF(T31="","",(T31*(1-AT31)*(1-Settings!$I$68)*(1-Settings!$I$17)-I31)/(T31*(1-AT31)*(1-Settings!$I$68)*(1-Settings!$I$17))),"") | R31: =IFERROR(IF(OR(I31="",Z31>=1,Settings!$B$17>=1,AN31>=1),"",IF(MOD(ROUND(I31/(1-Z31)/(1-Settings!$B$17)/(1-AN31),0),10)=0,ROUND(I31/(1-Z31)/(1-Settings!$B$17)/(1-AN31),0)-1,IF(MOD(ROUND(I31/(1-Z31)/(1-Settings!$B$17)/(1-AN31),0),10)<=5,FLOOR(ROUND(I31/(1-Z31)/(1-Settings!$B$17)/(1-AN31),0),10)+6,FLOOR(ROUND(I31/(1-Z31)/(1-Settings!$B$17)/(1-AN31),0),10)+9))),"") | S31: 365 | T31: =IF(S31<>"", IF(MOD(S31,10)=0,S31-1,IF(MOD(S31,10)<=5,FLOOR(S31,10)+6,FLOOR(S31,10)+9)), R31) | U31: Основний | X31: =IFERROR(IF(OR(V31="",W31="",T31=""),"", IF(T31>W31,"Дорогий",IF(T31<V31,"Дешевий","У ринку"))),"") | Z31: =CHOOSE(MATCH(IF($U31="","Основний",$U31),{"Трафіковий","Основний","Маржинальний","Сезонний","Стратегічний"},0),0.16,0.19,0.24,0.23,0.28) | AA31: =CHOOSE(MATCH(IF($U31="","Основний",$U31),{"Трафіковий","Основний","Маржинальний","Сезонний","Стратегічний"},0),0.18,0.21,0.26,0.25,0.3) | AB31: =CHOOSE(MATCH(IF($U31="","Основний",$U31),{"Трафіковий","Основний","Маржинальний","Сезонний","Стратегічний"},0),0.19,0.22,0.28,0.26,0.32) | AC31: =CHOOSE(MATCH(IF($U31="","Основний",$U31),{"Трафіковий","Основний","Маржинальний","Сезонний","Стратегічний"},0),0.17,0.2,0.25,0.24,0.28) | AD31: =CHOOSE(MATCH(IF($U31="","Основний",$U31),{"Трафіковий","Основний","Маржинальний","Сезонний","Стратегічний"},0),0.18,0.21,0.26,0.25,0.3) | AE31: =CHOOSE(MATCH(IF($U31="","Основний",$U31),{"Трафіковий","Основний","Маржинальний","Сезонний","Стратегічний"},0),0.18,0.2,0.28,0.27,0.32) | AF31: =CHOOSE(MATCH(IF($U31="","Основний",$U31),{"Трафіковий","Основний","Маржинальний","Сезонний","Стратегічний"},0),0.15,0.175,0.22,0.21,0.25) | AG31: =CHOOSE(MATCH(IF($U31="","Основний",$U31),{"Трафіковий","Основний","Маржинальний","Сезонний","Стратегічний"},0),0.13,0.16,0.21,0.2,0.25) | AH31: =CHOOSE(MATCH(IF($U31="","Основний",$U31),{"Трафіковий","Основний","Маржинальний","Сезонний","Стратегічний"},0),0.15,0.18,0.23,0.22,0.27) | AI31: =CHOOSE(MATCH(IF($U31="","Основний",$U31),{"Трафіковий","Основний","Маржинальний","Сезонний","Стратегічний"},0),0.16,0.19,0.25,0.23,0.29) | AJ31: =CHOOSE(MATCH(IF($U31="","Основний",$U31),{"Трафіковий","Основний","Маржинальний","Сезонний","Стратегічний"},0),0.14,0.17,0.22,0.21,0.25) | AK31: =CHOOSE(MATCH(IF($U31="","Основний",$U31),{"Трафіковий","Основний","Маржинальний","Сезонний","Стратегічний"},0),0.15,0.18,0.23,0.22,0.27) | AL31: =CHOOSE(MATCH(IF($U31="","Основний",$U31),{"Трафіковий","Основний","Маржинальний","Сезонний","Стратегічний"},0),0.15,0.17,0.25,0.24,0.29) | AM31: =CHOOSE(MATCH(IF($U31="","Основний",$U31),{"Трафіковий","Основний","Маржинальний","Сезонний","Стратегічний"},0),0.12,0.145,0.19,0.18,0.22) | AN31: =CHOOSE(MATCH(IF($U31="","Основний",$U31),{"Трафіковий","Основний","Маржинальний","Сезонний","Стратегічний"},0),Settings!$B$78,Settings!$B$80,Settings!$B$82,Settings!$B$84,Settings!$B$86) | AO31: =CHOOSE(MATCH(IF($U31="","Основний",$U31),{"Трафіковий","Основний","Маржинальний","Сезонний","Стратегічний"},0),Settings!$C$78,Settings!$C$80,Settings!$C$82,Settings!$C$84,Settings!$C$86) | AP31: =CHOOSE(MATCH(IF($U31="","Основний",$U31),{"Трафіковий","Основний","Маржинальний","Сезонний","Стратегічний"},0),Settings!$D$78,Settings!$D$80,Settings!$D$82,Settings!$D$84,Settings!$D$86) | AQ31: =CHOOSE(MATCH(IF($U31="","Основний",$U31),{"Трафіковий","Основний","Маржинальний","Сезонний","Стратегічний"},0),Settings!$F$78,Settings!$F$80,Settings!$F$82,Settings!$F$84,Settings!$F$86) | AR31: =CHOOSE(MATCH(IF($U31="","Основний",$U31),{"Трафіковий","Основний","Маржинальний","Сезонний","Стратегічний"},0),Settings!$G$78,Settings!$G$80,Settings!$G$82,Settings!$G$84,Settings!$G$86) | AS31: =CHOOSE(MATCH(IF($U31="","Основний",$U31),{"Трафіковий","Основний","Маржинальний","Сезонний","Стратегічний"},0),Settings!$H$78,Settings!$H$80,Settings!$H$82,Settings!$H$84,Settings!$H$86) | AT31: =CHOOSE(MATCH(IF($U31="","Основний",$U31),{"Трафіковий","Основний","Маржинальний","Сезонний","Стратегічний"},0),Settings!$I$78,Settings!$I$80,Settings!$I$82,Settings!$I$84,Settings!$I$86) | AV31: 1.35
B32: P3115 | C32: LED METAL FLASHLIGHT 500 lm - 4×AAA | D32: Ліхтарі | E32: PC | F32: 6.542 | G32: 8513100000 | H32: 1.4 | I32: =IFERROR(F32*Settings!$B$2*H32*IF(AND(ISNUMBER(E32),E32>1),E32,1),"") | J32: =Settings!$B$66 | K32: =IFERROR(IF(T32="","",(T32*(1-AN32)*(1-Settings!$B$17)-I32)/(T32*(1-AN32)*(1-Settings!$B$17))),"") | L32: =IFERROR(IF(T32="","",(T32*(1-AO32)*(1-Settings!$C$17)-I32)/(T32*(1-AO32)*(1-Settings!$C$17))),"") | M32: =IFERROR(IF(T32="","",(T32*(1-AP32)*(1-Settings!$D$17)-I32)/(T32*(1-AP32)*(1-Settings!$D$17))),"") | N32: =IFERROR(IF(T32="","",(T32*(1-AQ32)*(1-Settings!$F$17)-I32)/(T32*(1-AQ32)*(1-Settings!$F$17))),"") | O32: =IFERROR(IF(T32="","",(T32*(1-AR32)*(1-Settings!$G$17)-I32)/(T32*(1-AR32)*(1-Settings!$G$17))),"") | P32: =IFERROR(IF(T32="","",(T32*(1-AS32)*(1-Settings!$H$17)-I32)/(T32*(1-AS32)*(1-Settings!$H$17))),"") | Q32: =IFERROR(IF(T32="","",(T32*(1-AT32)*(1-Settings!$I$68)*(1-Settings!$I$17)-I32)/(T32*(1-AT32)*(1-Settings!$I$68)*(1-Settings!$I$17))),"") | R32: =IFERROR(IF(OR(I32="",Z32>=1,Settings!$B$17>=1,AN32>=1),"",IF(MOD(ROUND(I32/(1-Z32)/(1-Settings!$B$17)/(1-AN32),0),10)=0,ROUND(I32/(1-Z32)/(1-Settings!$B$17)/(1-AN32),0)-1,IF(MOD(ROUND(I32/(1-Z32)/(1-Settings!$B$17)/(1-AN32),0),10)<=5,FLOOR(ROUND(I32/(1-Z32)/(1-Settings!$B$17)/(1-AN32),0),10)+6,FLOOR(ROUND(I32/(1-Z32)/(1-Settings!$B$17)/(1-AN32),0),10)+9))),"") | S32: 800 | T32: =IF(S32<>"", IF(MOD(S32,10)=0,S32-1,IF(MOD(S32,10)<=5,FLOOR(S32,10)+6,FLOOR(S32,10)+9)), R32) | U32: Основний | X32: =IFERROR(IF(OR(V32="",W32="",T32=""),"", IF(T32>W32,"Дорогий",IF(T32<V32,"Дешевий","У ринку"))),"") | Z32: =CHOOSE(MATCH(IF($U32="","Основний",$U32),{"Трафіковий","Основний","Маржинальний","Сезонний","Стратегічний"},0),0.16,0.19,0.24,0.23,0.28) | AA32: =CHOOSE(MATCH(IF($U32="","Основний",$U32),{"Трафіковий","Основний","Маржинальний","Сезонний","Стратегічний"},0),0.18,0.21,0.26,0.25,0.3) | AB32: =CHOOSE(MATCH(IF($U32="","Основний",$U32),{"Трафіковий","Основний","Маржинальний","Сезонний","Стратегічний"},0),0.19,0.22,0.28,0.26,0.32) | AC32: =CHOOSE(MATCH(IF($U32="","Основний",$U32),{"Трафіковий","Основний","Маржинальний","Сезонний","Стратегічний"},0),0.17,0.2,0.25,0.24,0.28) | AD32: =CHOOSE(MATCH(IF($U32="","Основний",$U32),{"Трафіковий","Основний","Маржинальний","Сезонний","Стратегічний"},0),0.18,0.21,0.26,0.25,0.3) | AE32: =CHOOSE(MATCH(IF($U32="","Основний",$U32),{"Трафіковий","Основний","Маржинальний","Сезонний","Стратегічний"},0),0.18,0.2,0.28,0.27,0.32) | AF32: =CHOOSE(MATCH(IF($U32="","Основний",$U32),{"Трафіковий","Основний","Маржинальний","Сезонний","Стратегічний"},0),0.15,0.175,0.22,0.21,0.25) | AG32: =CHOOSE(MATCH(IF($U32="","Основний",$U32),{"Трафіковий","Основний","Маржинальний","Сезонний","Стратегічний"},0),0.13,0.16,0.21,0.2,0.25) | AH32: =CHOOSE(MATCH(IF($U32="","Основний",$U32),{"Трафіковий","Основний","Маржинальний","Сезонний","Стратегічний"},0),0.15,0.18,0.23,0.22,0.27) | AI32: =CHOOSE(MATCH(IF($U32="","Основний",$U32),{"Трафіковий","Основний","Маржинальний","Сезонний","Стратегічний"},0),0.16,0.19,0.25,0.23,0.29) | AJ32: =CHOOSE(MATCH(IF($U32="","Основний",$U32),{"Трафіковий","Основний","Маржинальний","Сезонний","Стратегічний"},0),0.14,0.17,0.22,0.21,0.25) | AK32: =CHOOSE(MATCH(IF($U32="","Основний",$U32),{"Трафіковий","Основний","Маржинальний","Сезонний","Стратегічний"},0),0.15,0.18,0.23,0.22,0.27) | AL32: =CHOOSE(MATCH(IF($U32="","Основний",$U32),{"Трафіковий","Основний","Маржинальний","Сезонний","Стратегічний"},0),0.15,0.17,0.25,0.24,0.29) | AM32: =CHOOSE(MATCH(IF($U32="","Основний",$U32),{"Трафіковий","Основний","Маржинальний","Сезонний","Стратегічний"},0),0.12,0.145,0.19,0.18,0.22) | AN32: =CHOOSE(MATCH(IF($U32="","Основний",$U32),{"Трафіковий","Основний","Маржинальний","Сезонний","Стратегічний"},0),Settings!$B$78,Settings!$B$80,Settings!$B$82,Settings!$B$84,Settings!$B$86) | AO32: =CHOOSE(MATCH(IF($U32="","Основний",$U32),{"Трафіковий","Основний","Маржинальний","Сезонний","Стратегічний"},0),Settings!$C$78,Settings!$C$80,Settings!$C$82,Settings!$C$84,Settings!$C$86) | AP32: =CHOOSE(MATCH(IF($U32="","Основний",$U32),{"Трафіковий","Основний","Маржинальний","Сезонний","Стратегічний"},0),Settings!$D$78,Settings!$D$80,Settings!$D$82,Settings!$D$84,Settings!$D$86) | AQ32: =CHOOSE(MATCH(IF($U32="","Основний",$U32),{"Трафіковий","Основний","Маржинальний","Сезонний","Стратегічний"},0),Settings!$F$78,Settings!$F$80,Settings!$F$82,Settings!$F$84,Settings!$F$86) | AR32: =CHOOSE(MATCH(IF($U32="","Основний",$U32),{"Трафіковий","Основний","Маржинальний","Сезонний","Стратегічний"},0),Settings!$G$78,Settings!$G$80,Settings!$G$82,Settings!$G$84,Settings!$G$86) | AS32: =CHOOSE(MATCH(IF($U32="","Основний",$U32),{"Трафіковий","Основний","Маржинальний","Сезонний","Стратегічний"},0),Settings!$H$78,Settings!$H$80,Settings!$H$82,Settings!$H$84,Settings!$H$86) | AT32: =CHOOSE(MATCH(IF($U32="","Основний",$U32),{"Трафіковий","Основний","Маржинальний","Сезонний","Стратегічний"},0),Settings!$I$78,Settings!$I$80,Settings!$I$82,Settings!$I$84,Settings!$I$86) | AV32: 1.35
B33: P3114 | C33: LED METAL FLASHLIGHT 330 lm - 3×AAA | D33: Ліхтарі | E33: PC | F33: 6.371 | G33: 8513100000 | H33: 1.4 | I33: =IFERROR(F33*Settings!$B$2*H33*IF(AND(ISNUMBER(E33),E33>1),E33,1),"") | J33: =Settings!$B$66 | K33: =IFERROR(IF(T33="","",(T33*(1-AN33)*(1-Settings!$B$17)-I33)/(T33*(1-AN33)*(1-Settings!$B$17))),"") | L33: =IFERROR(IF(T33="","",(T33*(1-AO33)*(1-Settings!$C$17)-I33)/(T33*(1-AO33)*(1-Settings!$C$17))),"") | M33: =IFERROR(IF(T33="","",(T33*(1-AP33)*(1-Settings!$D$17)-I33)/(T33*(1-AP33)*(1-Settings!$D$17))),"") | N33: =IFERROR(IF(T33="","",(T33*(1-AQ33)*(1-Settings!$F$17)-I33)/(T33*(1-AQ33)*(1-Settings!$F$17))),"") | O33: =IFERROR(IF(T33="","",(T33*(1-AR33)*(1-Settings!$G$17)-I33)/(T33*(1-AR33)*(1-Settings!$G$17))),"") | P33: =IFERROR(IF(T33="","",(T33*(1-AS33)*(1-Settings!$H$17)-I33)/(T33*(1-AS33)*(1-Settings!$H$17))),"") | Q33: =IFERROR(IF(T33="","",(T33*(1-AT33)*(1-Settings!$I$68)*(1-Settings!$I$17)-I33)/(T33*(1-AT33)*(1-Settings!$I$68)*(1-Settings!$I$17))),"") | R33: =IFERROR(IF(OR(I33="",Z33>=1,Settings!$B$17>=1,AN33>=1),"",IF(MOD(ROUND(I33/(1-Z33)/(1-Settings!$B$17)/(1-AN33),0),10)=0,ROUND(I33/(1-Z33)/(1-Settings!$B$17)/(1-AN33),0)-1,IF(MOD(ROUND(I33/(1-Z33)/(1-Settings!$B$17)/(1-AN33),0),10)<=5,FLOOR(ROUND(I33/(1-Z33)/(1-Settings!$B$17)/(1-AN33),0),10)+6,FLOOR(ROUND(I33/(1-Z33)/(1-Settings!$B$17)/(1-AN33),0),10)+9))),"") | S33: 780 | T33: =IF(S33<>"", IF(MOD(S33,10)=0,S33-1,IF(MOD(S33,10)<=5,FLOOR(S33,10)+6,FLOOR(S33,10)+9)), R33) | U33: Основний | X33: =IFERROR(IF(OR(V33="",W33="",T33=""),"", IF(T33>W33,"Дорогий",IF(T33<V33,"Дешевий","У ринку"))),"") | Z33: =CHOOSE(MATCH(IF($U33="","Основний",$U33),{"Трафіковий","Основний","Маржинальний","Сезонний","Стратегічний"},0),0.16,0.19,0.24,0.23,0.28) | AA33: =CHOOSE(MATCH(IF($U33="","Основний",$U33),{"Трафіковий","Основний","Маржинальний","Сезонний","Стратегічний"},0),0.18,0.21,0.26,0.25,0.3) | AB33: =CHOOSE(MATCH(IF($U33="","Основний",$U33),{"Трафіковий","Основний","Маржинальний","Сезонний","Стратегічний"},0),0.19,0.22,0.28,0.26,0.32) | AC33: =CHOOSE(MATCH(IF($U33="","Основний",$U33),{"Трафіковий","Основний","Маржинальний","Сезонний","Стратегічний"},0),0.17,0.2,0.25,0.24,0.28) | AD33: =CHOOSE(MATCH(IF($U33="","Основний",$U33),{"Трафіковий","Основний","Маржинальний","Сезонний","Стратегічний"},0),0.18,0.21,0.26,0.25,0.3) | AE33: =CHOOSE(MATCH(IF($U33="","Основний",$U33),{"Трафіковий","Основний","Маржинальний","Сезонний","Стратегічний"},0),0.18,0.2,0.28,0.27,0.32) | AF33: =CHOOSE(MATCH(IF($U33="","Основний",$U33),{"Трафіковий","Основний","Маржинальний","Сезонний","Стратегічний"},0),0.15,0.175,0.22,0.21,0.25) | AG33: =CHOOSE(MATCH(IF($U33="","Основний",$U33),{"Трафіковий","Основний","Маржинальний","Сезонний","Стратегічний"},0),0.13,0.16,0.21,0.2,0.25) | AH33: =CHOOSE(MATCH(IF($U33="","Основний",$U33),{"Трафіковий","Основний","Маржинальний","Сезонний","Стратегічний"},0),0.15,0.18,0.23,0.22,0.27) | AI33: =CHOOSE(MATCH(IF($U33="","Основний",$U33),{"Трафіковий","Основний","Маржинальний","Сезонний","Стратегічний"},0),0.16,0.19,0.25,0.23,0.29) | AJ33: =CHOOSE(MATCH(IF($U33="","Основний",$U33),{"Трафіковий","Основний","Маржинальний","Сезонний","Стратегічний"},0),0.14,0.17,0.22,0.21,0.25) | AK33: =CHOOSE(MATCH(IF($U33="","Основний",$U33),{"Трафіковий","Основний","Маржинальний","Сезонний","Стратегічний"},0),0.15,0.18,0.23,0.22,0.27) | AL33: =CHOOSE(MATCH(IF($U33="","Основний",$U33),{"Трафіковий","Основний","Маржинальний","Сезонний","Стратегічний"},0),0.15,0.17,0.25,0.24,0.29) | AM33: =CHOOSE(MATCH(IF($U33="","Основний",$U33),{"Трафіковий","Основний","Маржинальний","Сезонний","Стратегічний"},0),0.12,0.145,0.19,0.18,0.22) | AN33: =CHOOSE(MATCH(IF($U33="","Основний",$U33),{"Трафіковий","Основний","Маржинальний","Сезонний","Стратегічний"},0),Settings!$B$78,Settings!$B$80,Settings!$B$82,Settings!$B$84,Settings!$B$86) | AO33: =CHOOSE(MATCH(IF($U33="","Основний",$U33),{"Трафіковий","Основний","Маржинальний","Сезонний","Стратегічний"},0),Settings!$C$78,Settings!$C$80,Settings!$C$82,Settings!$C$84,Settings!$C$86) | AP33: =CHOOSE(MATCH(IF($U33="","Основний",$U33),{"Трафіковий","Основний","Маржинальний","Сезонний","Стратегічний"},0),Settings!$D$78,Settings!$D$80,Settings!$D$82,Settings!$D$84,Settings!$D$86) | AQ33: =CHOOSE(MATCH(IF($U33="","Основний",$U33),{"Трафіковий","Основний","Маржинальний","Сезонний","Стратегічний"},0),Settings!$F$78,Settings!$F$80,Settings!$F$82,Settings!$F$84,Settings!$F$86) | AR33: =CHOOSE(MATCH(IF($U33="","Основний",$U33),{"Трафіковий","Основний","Маржинальний","Сезонний","Стратегічний"},0),Settings!$G$78,Settings!$G$80,Settings!$G$82,Settings!$G$84,Settings!$G$86) | AS33: =CHOOSE(MATCH(IF($U33="","Основний",$U33),{"Трафіковий","Основний","Маржинальний","Сезонний","Стратегічний"},0),Settings!$H$78,Settings!$H$80,Settings!$H$82,Settings!$H$84,Settings!$H$86) | AT33: =CHOOSE(MATCH(IF($U33="","Основний",$U33),{"Трафіковий","Основний","Маржинальний","Сезонний","Стратегічний"},0),Settings!$I$78,Settings!$I$80,Settings!$I$82,Settings!$I$84,Settings!$I$86) | AV33: 1.35
B34: P3113 | C34: LED METAL FLASHLIGHT 120 lm - 2×AAA | D34: Ліхтарі | E34: PC | F34: 5.174 | G34: 8513100000 | H34: 1.4 | I34: =IFERROR(F34*Settings!$B$2*H34*IF(AND(ISNUMBER(E34),E34>1),E34,1),"") | J34: =Settings!$B$66 | K34: =IFERROR(IF(T34="","",(T34*(1-AN34)*(1-Settings!$B$17)-I34)/(T34*(1-AN34)*(1-Settings!$B$17))),"") | L34: =IFERROR(IF(T34="","",(T34*(1-AO34)*(1-Settings!$C$17)-I34)/(T34*(1-AO34)*(1-Settings!$C$17))),"") | M34: =IFERROR(IF(T34="","",(T34*(1-AP34)*(1-Settings!$D$17)-I34)/(T34*(1-AP34)*(1-Settings!$D$17))),"") | N34: =IFERROR(IF(T34="","",(T34*(1-AQ34)*(1-Settings!$F$17)-I34)/(T34*(1-AQ34)*(1-Settings!$F$17))),"") | O34: =IFERROR(IF(T34="","",(T34*(1-AR34)*(1-Settings!$G$17)-I34)/(T34*(1-AR34)*(1-Settings!$G$17))),"") | P34: =IFERROR(IF(T34="","",(T34*(1-AS34)*(1-Settings!$H$17)-I34)/(T34*(1-AS34)*(1-Settings!$H$17))),"") | Q34: =IFERROR(IF(T34="","",(T34*(1-AT34)*(1-Settings!$I$68)*(1-Settings!$I$17)-I34)/(T34*(1-AT34)*(1-Settings!$I$68)*(1-Settings!$I$17))),"") | R34: =IFERROR(IF(OR(I34="",Z34>=1,Settings!$B$17>=1,AN34>=1),"",IF(MOD(ROUND(I34/(1-Z34)/(1-Settings!$B$17)/(1-AN34),0),10)=0,ROUND(I34/(1-Z34)/(1-Settings!$B$17)/(1-AN34),0)-1,IF(MOD(ROUND(I34/(1-Z34)/(1-Settings!$B$17)/(1-AN34),0),10)<=5,FLOOR(ROUND(I34/(1-Z34)/(1-Settings!$B$17)/(1-AN34),0),10)+6,FLOOR(ROUND(I34/(1-Z34)/(1-Settings!$B$17)/(1-AN34),0),10)+9))),"") | S34: 660 | T34: =IF(S34<>"", IF(MOD(S34,10)=0,S34-1,IF(MOD(S34,10)<=5,FLOOR(S34,10)+6,FLOOR(S34,10)+9)), R34) | U34: Основний | X34: =IFERROR(IF(OR(V34="",W34="",T34=""),"", IF(T34>W34,"Дорогий",IF(T34<V34,"Дешевий","У ринку"))),"") | Z34: =CHOOSE(MATCH(IF($U34="","Основний",$U34),{"Трафіковий","Основний","Маржинальний","Сезонний","Стратегічний"},0),0.16,0.19,0.24,0.23,0.28) | AA34: =CHOOSE(MATCH(IF($U34="","Основний",$U34),{"Трафіковий","Основний","Маржинальний","Сезонний","Стратегічний"},0),0.18,0.21,0.26,0.25,0.3) | AB34: =CHOOSE(MATCH(IF($U34="","Основний",$U34),{"Трафіковий","Основний","Маржинальний","Сезонний","Стратегічний"},0),0.19,0.22,0.28,0.26,0.32) | AC34: =CHOOSE(MATCH(IF($U34="","Основний",$U34),{"Трафіковий","Основний","Маржинальний","Сезонний","Стратегічний"},0),0.17,0.2,0.25,0.24,0.28) | AD34: =CHOOSE(MATCH(IF($U34="","Основний",$U34),{"Трафіковий","Основний","Маржинальний","Сезонний","Стратегічний"},0),0.18,0.21,0.26,0.25,0.3) | AE34: =CHOOSE(MATCH(IF($U34="","Основний",$U34),{"Трафіковий","Основний","Маржинальний","Сезонний","Стратегічний"},0),0.18,0.2,0.28,0.27,0.32) | AF34: =CHOOSE(MATCH(IF($U34="","Основний",$U34),{"Трафіковий","Основний","Маржинальний","Сезонний","Стратегічний"},0),0.15,0.175,0.22,0.21,0.25) | AG34: =CHOOSE(MATCH(IF($U34="","Основний",$U34),{"Трафіковий","Основний","Маржинальний","Сезонний","Стратегічний"},0),0.13,0.16,0.21,0.2,0.25) | AH34: =CHOOSE(MATCH(IF($U34="","Основний",$U34),{"Трафіковий","Основний","Маржинальний","Сезонний","Стратегічний"},0),0.15,0.18,0.23,0.22,0.27) | AI34: =CHOOSE(MATCH(IF($U34="","Основний",$U34),{"Трафіковий","Основний","Маржинальний","Сезонний","Стратегічний"},0),0.16,0.19,0.25,0.23,0.29) | AJ34: =CHOOSE(MATCH(IF($U34="","Основний",$U34),{"Трафіковий","Основний","Маржинальний","Сезонний","Стратегічний"},0),0.14,0.17,0.22,0.21,0.25) | AK34: =CHOOSE(MATCH(IF($U34="","Основний",$U34),{"Трафіковий","Основний","Маржинальний","Сезонний","Стратегічний"},0),0.15,0.18,0.23,0.22,0.27) | AL34: =CHOOSE(MATCH(IF($U34="","Основний",$U34),{"Трафіковий","Основний","Маржинальний","Сезонний","Стратегічний"},0),0.15,0.17,0.25,0.24,0.29) | AM34: =CHOOSE(MATCH(IF($U34="","Основний",$U34),{"Трафіковий","Основний","Маржинальний","Сезонний","Стратегічний"},0),0.12,0.145,0.19,0.18,0.22) | AN34: =CHOOSE(MATCH(IF($U34="","Основний",$U34),{"Трафіковий","Основний","Маржинальний","Сезонний","Стратегічний"},0),Settings!$B$78,Settings!$B$80,Settings!$B$82,Settings!$B$84,Settings!$B$86) | AO34: =CHOOSE(MATCH(IF($U34="","Основний",$U34),{"Трафіковий","Основний","Маржинальний","Сезонний","Стратегічний"},0),Settings!$C$78,Settings!$C$80,Settings!$C$82,Settings!$C$84,Settings!$C$86) | AP34: =CHOOSE(MATCH(IF($U34="","Основний",$U34),{"Трафіковий","Основний","Маржинальний","Сезонний","Стратегічний"},0),Settings!$D$78,Settings!$D$80,Settings!$D$82,Settings!$D$84,Settings!$D$86) | AQ34: =CHOOSE(MATCH(IF($U34="","Основний",$U34),{"Трафіковий","Основний","Маржинальний","Сезонний","Стратегічний"},0),Settings!$F$78,Settings!$F$80,Settings!$F$82,Settings!$F$84,Settings!$F$86) | AR34: =CHOOSE(MATCH(IF($U34="","Основний",$U34),{"Трафіковий","Основний","Маржинальний","Сезонний","Стратегічний"},0),Settings!$G$78,Settings!$G$80,Settings!$G$82,Settings!$G$84,Settings!$G$86) | AS34: =CHOOSE(MATCH(IF($U34="","Основний",$U34),{"Трафіковий","Основний","Маржинальний","Сезонний","Стратегічний"},0),Settings!$H$78,Settings!$H$80,Settings!$H$82,Settings!$H$84,Settings!$H$86) | AT34: =CHOOSE(MATCH(IF($U34="","Основний",$U34),{"Трафіковий","Основний","Маржинальний","Сезонний","Стратегічний"},0),Settings!$I$78,Settings!$I$80,Settings!$I$82,Settings!$I$84,Settings!$I$86) | AV34: 1.35
A35: SELL OUT | B35: P3112 | C35: 360° COB LED METAL FLASHLIGHT 270 lm - 2×AA | D35: Ліхтарі | E35: PC | F35: 7.582 | G35: 8513100000 | H35: 1.4 | I35: =IFERROR(F35*Settings!$B$2*H35*IF(AND(ISNUMBER(E35),E35>1),E35,1),"") | J35: =Settings!$B$66 | K35: =IFERROR(IF(T35="","",(T35*(1-AN35)*(1-Settings!$B$17)-I35)/(T35*(1-AN35)*(1-Settings!$B$17))),"") | L35: =IFERROR(IF(T35="","",(T35*(1-AO35)*(1-Settings!$C$17)-I35)/(T35*(1-AO35)*(1-Settings!$C$17))),"") | M35: =IFERROR(IF(T35="","",(T35*(1-AP35)*(1-Settings!$D$17)-I35)/(T35*(1-AP35)*(1-Settings!$D$17))),"") | N35: =IFERROR(IF(T35="","",(T35*(1-AQ35)*(1-Settings!$F$17)-I35)/(T35*(1-AQ35)*(1-Settings!$F$17))),"") | O35: =IFERROR(IF(T35="","",(T35*(1-AR35)*(1-Settings!$G$17)-I35)/(T35*(1-AR35)*(1-Settings!$G$17))),"") | P35: =IFERROR(IF(T35="","",(T35*(1-AS35)*(1-Settings!$H$17)-I35)/(T35*(1-AS35)*(1-Settings!$H$17))),"") | Q35: =IFERROR(IF(T35="","",(T35*(1-AT35)*(1-Settings!$I$68)*(1-Settings!$I$17)-I35)/(T35*(1-AT35)*(1-Settings!$I$68)*(1-Settings!$I$17))),"") | R35: =IFERROR(IF(OR(I35="",Z35>=1,Settings!$B$17>=1,AN35>=1),"",IF(MOD(ROUND(I35/(1-Z35)/(1-Settings!$B$17)/(1-AN35),0),10)=0,ROUND(I35/(1-Z35)/(1-Settings!$B$17)/(1-AN35),0)-1,IF(MOD(ROUND(I35/(1-Z35)/(1-Settings!$B$17)/(1-AN35),0),10)<=5,FLOOR(ROUND(I35/(1-Z35)/(1-Settings!$B$17)/(1-AN35),0),10)+6,FLOOR(ROUND(I35/(1-Z35)/(1-Settings!$B$17)/(1-AN35),0),10)+9))),"") | S35: 850 | T35: =IF(S35<>"", IF(MOD(S35,10)=0,S35-1,IF(MOD(S35,10)<=5,FLOOR(S35,10)+6,FLOOR(S35,10)+9)), R35) | U35: Основний | X35: =IFERROR(IF(OR(V35="",W35="",T35=""),"", IF(T35>W35,"Дорогий",IF(T35<V35,"Дешевий","У ринку"))),"") | Z35: =CHOOSE(MATCH(IF($U35="","Основний",$U35),{"Трафіковий","Основний","Маржинальний","Сезонний","Стратегічний"},0),0.16,0.19,0.24,0.23,0.28) | AA35: =CHOOSE(MATCH(IF($U35="","Основний",$U35),{"Трафіковий","Основний","Маржинальний","Сезонний","Стратегічний"},0),0.18,0.21,0.26,0.25,0.3) | AB35: =CHOOSE(MATCH(IF($U35="","Основний",$U35),{"Трафіковий","Основний","Маржинальний","Сезонний","Стратегічний"},0),0.19,0.22,0.28,0.26,0.32) | AC35: =CHOOSE(MATCH(IF($U35="","Основний",$U35),{"Трафіковий","Основний","Маржинальний","Сезонний","Стратегічний"},0),0.17,0.2,0.25,0.24,0.28) | AD35: =CHOOSE(MATCH(IF($U35="","Основний",$U35),{"Трафіковий","Основний","Маржинальний","Сезонний","Стратегічний"},0),0.18,0.21,0.26,0.25,0.3) | AE35: =CHOOSE(MATCH(IF($U35="","Основний",$U35),{"Трафіковий","Основний","Маржинальний","Сезонний","Стратегічний"},0),0.18,0.2,0.28,0.27,0.32) | AF35: =CHOOSE(MATCH(IF($U35="","Основний",$U35),{"Трафіковий","Основний","Маржинальний","Сезонний","Стратегічний"},0),0.15,0.175,0.22,0.21,0.25) | AG35: =CHOOSE(MATCH(IF($U35="","Основний",$U35),{"Трафіковий","Основний","Маржинальний","Сезонний","Стратегічний"},0),0.13,0.16,0.21,0.2,0.25) | AH35: =CHOOSE(MATCH(IF($U35="","Основний",$U35),{"Трафіковий","Основний","Маржинальний","Сезонний","Стратегічний"},0),0.15,0.18,0.23,0.22,0.27) | AI35: =CHOOSE(MATCH(IF($U35="","Основний",$U35),{"Трафіковий","Основний","Маржинальний","Сезонний","Стратегічний"},0),0.16,0.19,0.25,0.23,0.29) | AJ35: =CHOOSE(MATCH(IF($U35="","Основний",$U35),{"Трафіковий","Основний","Маржинальний","Сезонний","Стратегічний"},0),0.14,0.17,0.22,0.21,0.25) | AK35: =CHOOSE(MATCH(IF($U35="","Основний",$U35),{"Трафіковий","Основний","Маржинальний","Сезонний","Стратегічний"},0),0.15,0.18,0.23,0.22,0.27) | AL35: =CHOOSE(MATCH(IF($U35="","Основний",$U35),{"Трафіковий","Основний","Маржинальний","Сезонний","Стратегічний"},0),0.15,0.17,0.25,0.24,0.29) | AM35: =CHOOSE(MATCH(IF($U35="","Основний",$U35),{"Трафіковий","Основний","Маржинальний","Сезонний","Стратегічний"},0),0.12,0.145,0.19,0.18,0.22) | AN35: =CHOOSE(MATCH(IF($U35="","Основний",$U35),{"Трафіковий","Основний","Маржинальний","Сезонний","Стратегічний"},0),Settings!$B$78,Settings!$B$80,Settings!$B$82,Settings!$B$84,Settings!$B$86) | AO35: =CHOOSE(MATCH(IF($U35="","Основний",$U35),{"Трафіковий","Основний","Маржинальний","Сезонний","Стратегічний"},0),Settings!$C$78,Settings!$C$80,Settings!$C$82,Settings!$C$84,Settings!$C$86) | AP35: =CHOOSE(MATCH(IF($U35="","Основний",$U35),{"Трафіковий","Основний","Маржинальний","Сезонний","Стратегічний"},0),Settings!$D$78,Settings!$D$80,Settings!$D$82,Settings!$D$84,Settings!$D$86) | AQ35: =CHOOSE(MATCH(IF($U35="","Основний",$U35),{"Трафіковий","Основний","Маржинальний","Сезонний","Стратегічний"},0),Settings!$F$78,Settings!$F$80,Settings!$F$82,Settings!$F$84,Settings!$F$86) | AR35: =CHOOSE(MATCH(IF($U35="","Основний",$U35),{"Трафіковий","Основний","Маржинальний","Сезонний","Стратегічний"},0),Settings!$G$78,Settings!$G$80,Settings!$G$82,Settings!$G$84,Settings!$G$86) | AS35: =CHOOSE(MATCH(IF($U35="","Основний",$U35),{"Трафіковий","Основний","Маржинальний","Сезонний","Стратегічний"},0),Settings!$H$78,Settings!$H$80,Settings!$H$82,Settings!$H$84,Settings!$H$86) | AT35: =CHOOSE(MATCH(IF($U35="","Основний",$U35),{"Трафіковий","Основний","Маржинальний","Сезонний","Стратегічний"},0),Settings!$I$78,Settings!$I$80,Settings!$I$82,Settings!$I$84,Settings!$I$86) | AV35: 1.35
B36: P3111 | C36: METAL 5W + 3W COB FLASHLIGHT WITH FOCUS | D36: Ліхтарі | E36: PC | F36: 6.044 | G36: 8513100000 | H36: 1.4 | I36: =IFERROR(F36*Settings!$B$2*H36*IF(AND(ISNUMBER(E36),E36>1),E36,1),"") | J36: =Settings!$B$66 | K36: =IFERROR(IF(T36="","",(T36*(1-AN36)*(1-Settings!$B$17)-I36)/(T36*(1-AN36)*(1-Settings!$B$17))),"") | L36: =IFERROR(IF(T36="","",(T36*(1-AO36)*(1-Settings!$C$17)-I36)/(T36*(1-AO36)*(1-Settings!$C$17))),"") | M36: =IFERROR(IF(T36="","",(T36*(1-AP36)*(1-Settings!$D$17)-I36)/(T36*(1-AP36)*(1-Settings!$D$17))),"") | N36: =IFERROR(IF(T36="","",(T36*(1-AQ36)*(1-Settings!$F$17)-I36)/(T36*(1-AQ36)*(1-Settings!$F$17))),"") | O36: =IFERROR(IF(T36="","",(T36*(1-AR36)*(1-Settings!$G$17)-I36)/(T36*(1-AR36)*(1-Settings!$G$17))),"") | P36: =IFERROR(IF(T36="","",(T36*(1-AS36)*(1-Settings!$H$17)-I36)/(T36*(1-AS36)*(1-Settings!$H$17))),"") | Q36: =IFERROR(IF(T36="","",(T36*(1-AT36)*(1-Settings!$I$68)*(1-Settings!$I$17)-I36)/(T36*(1-AT36)*(1-Settings!$I$68)*(1-Settings!$I$17))),"") | R36: =IFERROR(IF(OR(I36="",Z36>=1,Settings!$B$17>=1,AN36>=1),"",IF(MOD(ROUND(I36/(1-Z36)/(1-Settings!$B$17)/(1-AN36),0),10)=0,ROUND(I36/(1-Z36)/(1-Settings!$B$17)/(1-AN36),0)-1,IF(MOD(ROUND(I36/(1-Z36)/(1-Settings!$B$17)/(1-AN36),0),10)<=5,FLOOR(ROUND(I36/(1-Z36)/(1-Settings!$B$17)/(1-AN36),0),10)+6,FLOOR(ROUND(I36/(1-Z36)/(1-Settings!$B$17)/(1-AN36),0),10)+9))),"") | S36: 800 | T36: =IF(S36<>"", IF(MOD(S36,10)=0,S36-1,IF(MOD(S36,10)<=5,FLOOR(S36,10)+6,FLOOR(S36,10)+9)), R36) | U36: Основний | X36: =IFERROR(IF(OR(V36="",W36="",T36=""),"", IF(T36>W36,"Дорогий",IF(T36<V36,"Дешевий","У ринку"))),"") | Z36: =CHOOSE(MATCH(IF($U36="","Основний",$U36),{"Трафіковий","Основний","Маржинальний","Сезонний","Стратегічний"},0),0.16,0.19,0.24,0.23,0.28) | AA36: =CHOOSE(MATCH(IF($U36="","Основний",$U36),{"Трафіковий","Основний","Маржинальний","Сезонний","Стратегічний"},0),0.18,0.21,0.26,0.25,0.3) | AB36: =CHOOSE(MATCH(IF($U36="","Основний",$U36),{"Трафіковий","Основний","Маржинальний","Сезонний","Стратегічний"},0),0.19,0.22,0.28,0.26,0.32) | AC36: =CHOOSE(MATCH(IF($U36="","Основний",$U36),{"Трафіковий","Основний","Маржинальний","Сезонний","Стратегічний"},0),0.17,0.2,0.25,0.24,0.28) | AD36: =CHOOSE(MATCH(IF($U36="","Основний",$U36),{"Трафіковий","Основний","Маржинальний","Сезонний","Стратегічний"},0),0.18,0.21,0.26,0.25,0.3) | AE36: =CHOOSE(MATCH(IF($U36="","Основний",$U36),{"Трафіковий","Основний","Маржинальний","Сезонний","Стратегічний"},0),0.18,0.2,0.28,0.27,0.32) | AF36: =CHOOSE(MATCH(IF($U36="","Основний",$U36),{"Трафіковий","Основний","Маржинальний","Сезонний","Стратегічний"},0),0.15,0.175,0.22,0.21,0.25) | AG36: =CHOOSE(MATCH(IF($U36="","Основний",$U36),{"Трафіковий","Основний","Маржинальний","Сезонний","Стратегічний"},0),0.13,0.16,0.21,0.2,0.25) | AH36: =CHOOSE(MATCH(IF($U36="","Основний",$U36),{"Трафіковий","Основний","Маржинальний","Сезонний","Стратегічний"},0),0.15,0.18,0.23,0.22,0.27) | AI36: =CHOOSE(MATCH(IF($U36="","Основний",$U36),{"Трафіковий","Основний","Маржинальний","Сезонний","Стратегічний"},0),0.16,0.19,0.25,0.23,0.29) | AJ36: =CHOOSE(MATCH(IF($U36="","Основний",$U36),{"Трафіковий","Основний","Маржинальний","Сезонний","Стратегічний"},0),0.14,0.17,0.22,0.21,0.25) | AK36: =CHOOSE(MATCH(IF($U36="","Основний",$U36),{"Трафіковий","Основний","Маржинальний","Сезонний","Стратегічний"},0),0.15,0.18,0.23,0.22,0.27) | AL36: =CHOOSE(MATCH(IF($U36="","Основний",$U36),{"Трафіковий","Основний","Маржинальний","Сезонний","Стратегічний"},0),0.15,0.17,0.25,0.24,0.29) | AM36: =CHOOSE(MATCH(IF($U36="","Основний",$U36),{"Трафіковий","Основний","Маржинальний","Сезонний","Стратегічний"},0),0.12,0.145,0.19,0.18,0.22) | AN36: =CHOOSE(MATCH(IF($U36="","Основний",$U36),{"Трафіковий","Основний","Маржинальний","Сезонний","Стратегічний"},0),Settings!$B$78,Settings!$B$80,Settings!$B$82,Settings!$B$84,Settings!$B$86) | AO36: =CHOOSE(MATCH(IF($U36="","Основний",$U36),{"Трафіковий","Основний","Маржинальний","Сезонний","Стратегічний"},0),Settings!$C$78,Settings!$C$80,Settings!$C$82,Settings!$C$84,Settings!$C$86) | AP36: =CHOOSE(MATCH(IF($U36="","Основний",$U36),{"Трафіковий","Основний","Маржинальний","Сезонний","Стратегічний"},0),Settings!$D$78,Settings!$D$80,Settings!$D$82,Settings!$D$84,Settings!$D$86) | AQ36: =CHOOSE(MATCH(IF($U36="","Основний",$U36),{"Трафіковий","Основний","Маржинальний","Сезонний","Стратегічний"},0),Settings!$F$78,Settings!$F$80,Settings!$F$82,Settings!$F$84,Settings!$F$86) | AR36: =CHOOSE(MATCH(IF($U36="","Основний",$U36),{"Трафіковий","Основний","Маржинальний","Сезонний","Стратегічний"},0),Settings!$G$78,Settings!$G$80,Settings!$G$82,Settings!$G$84,Settings!$G$86) | AS36: =CHOOSE(MATCH(IF($U36="","Основний",$U36),{"Трафіковий","Основний","Маржинальний","Сезонний","Стратегічний"},0),Settings!$H$78,Settings!$H$80,Settings!$H$82,Settings!$H$84,Settings!$H$86) | AT36: =CHOOSE(MATCH(IF($U36="","Основний",$U36),{"Трафіковий","Основний","Маржинальний","Сезонний","Стратегічний"},0),Settings!$I$78,Settings!$I$80,Settings!$I$82,Settings!$I$84,Settings!$I$86) | AV36: 1.35
B37: P4704 | C37: LED FLASH. COB LED 3W 3×AAA | D37: Ліхтарі | E37: PC | F37: 2.222 | G37: 8513100000 | H37: 1.4 | I37: =IFERROR(F37*Settings!$B$2*H37*IF(AND(ISNUMBER(E37),E37>1),E37,1),"") | J37: =Settings!$B$66 | K37: =IFERROR(IF(T37="","",(T37*(1-AN37)*(1-Settings!$B$17)-I37)/(T37*(1-AN37)*(1-Settings!$B$17))),"") | L37: =IFERROR(IF(T37="","",(T37*(1-AO37)*(1-Settings!$C$17)-I37)/(T37*(1-AO37)*(1-Settings!$C$17))),"") | M37: =IFERROR(IF(T37="","",(T37*(1-AP37)*(1-Settings!$D$17)-I37)/(T37*(1-AP37)*(1-Settings!$D$17))),"") | N37: =IFERROR(IF(T37="","",(T37*(1-AQ37)*(1-Settings!$F$17)-I37)/(T37*(1-AQ37)*(1-Settings!$F$17))),"") | O37: =IFERROR(IF(T37="","",(T37*(1-AR37)*(1-Settings!$G$17)-I37)/(T37*(1-AR37)*(1-Settings!$G$17))),"") | P37: =IFERROR(IF(T37="","",(T37*(1-AS37)*(1-Settings!$H$17)-I37)/(T37*(1-AS37)*(1-Settings!$H$17))),"") | Q37: =IFERROR(IF(T37="","",(T37*(1-AT37)*(1-Settings!$I$68)*(1-Settings!$I$17)-I37)/(T37*(1-AT37)*(1-Settings!$I$68)*(1-Settings!$I$17))),"") | R37: =IFERROR(IF(OR(I37="",Z37>=1,Settings!$B$17>=1,AN37>=1),"",IF(MOD(ROUND(I37/(1-Z37)/(1-Settings!$B$17)/(1-AN37),0),10)=0,ROUND(I37/(1-Z37)/(1-Settings!$B$17)/(1-AN37),0)-1,IF(MOD(ROUND(I37/(1-Z37)/(1-Settings!$B$17)/(1-AN37),0),10)<=5,FLOOR(ROUND(I37/(1-Z37)/(1-Settings!$B$17)/(1-AN37),0),10)+6,FLOOR(ROUND(I37/(1-Z37)/(1-Settings!$B$17)/(1-AN37),0),10)+9))),"") | T37: =IF(S37<>"", IF(MOD(S37,10)=0,S37-1,IF(MOD(S37,10)<=5,FLOOR(S37,10)+6,FLOOR(S37,10)+9)), R37) | U37: Основний | X37: =IFERROR(IF(OR(V37="",W37="",T37=""),"", IF(T37>W37,"Дорогий",IF(T37<V37,"Дешевий","У ринку"))),"") | Z37: =CHOOSE(MATCH(IF($U37="","Основний",$U37),{"Трафіковий","Основний","Маржинальний","Сезонний","Стратегічний"},0),0.16,0.19,0.24,0.23,0.28) | AA37: =CHOOSE(MATCH(IF($U37="","Основний",$U37),{"Трафіковий","Основний","Маржинальний","Сезонний","Стратегічний"},0),0.18,0.21,0.26,0.25,0.3) | AB37: =CHOOSE(MATCH(IF($U37="","Основний",$U37),{"Трафіковий","Основний","Маржинальний","Сезонний","Стратегічний"},0),0.19,0.22,0.28,0.26,0.32) | AC37: =CHOOSE(MATCH(IF($U37="","Основний",$U37),{"Трафіковий","Основний","Маржинальний","Сезонний","Стратегічний"},0),0.17,0.2,0.25,0.24,0.28) | AD37: =CHOOSE(MATCH(IF($U37="","Основний",$U37),{"Трафіковий","Основний","Маржинальний","Сезонний","Стратегічний"},0),0.18,0.21,0.26,0.25,0.3) | AE37: =CHOOSE(MATCH(IF($U37="","Основний",$U37),{"Трафіковий","Основний","Маржинальний","Сезонний","Стратегічний"},0),0.18,0.2,0.28,0.27,0.32) | AF37: =CHOOSE(MATCH(IF($U37="","Основний",$U37),{"Трафіковий","Основний","Маржинальний","Сезонний","Стратегічний"},0),0.15,0.175,0.22,0.21,0.25) | AG37: =CHOOSE(MATCH(IF($U37="","Основний",$U37),{"Трафіковий","Основний","Маржинальний","Сезонний","Стратегічний"},0),0.13,0.16,0.21,0.2,0.25) | AH37: =CHOOSE(MATCH(IF($U37="","Основний",$U37),{"Трафіковий","Основний","Маржинальний","Сезонний","Стратегічний"},0),0.15,0.18,0.23,0.22,0.27) | AI37: =CHOOSE(MATCH(IF($U37="","Основний",$U37),{"Трафіковий","Основний","Маржинальний","Сезонний","Стратегічний"},0),0.16,0.19,0.25,0.23,0.29) | AJ37: =CHOOSE(MATCH(IF($U37="","Основний",$U37),{"Трафіковий","Основний","Маржинальний","Сезонний","Стратегічний"},0),0.14,0.17,0.22,0.21,0.25) | AK37: =CHOOSE(MATCH(IF($U37="","Основний",$U37),{"Трафіковий","Основний","Маржинальний","Сезонний","Стратегічний"},0),0.15,0.18,0.23,0.22,0.27) | AL37: =CHOOSE(MATCH(IF($U37="","Основний",$U37),{"Трафіковий","Основний","Маржинальний","Сезонний","Стратегічний"},0),0.15,0.17,0.25,0.24,0.29) | AM37: =CHOOSE(MATCH(IF($U37="","Основний",$U37),{"Трафіковий","Основний","Маржинальний","Сезонний","Стратегічний"},0),0.12,0.145,0.19,0.18,0.22) | AN37: =CHOOSE(MATCH(IF($U37="","Основний",$U37),{"Трафіковий","Основний","Маржинальний","Сезонний","Стратегічний"},0),Settings!$B$78,Settings!$B$80,Settings!$B$82,Settings!$B$84,Settings!$B$86) | AO37: =CHOOSE(MATCH(IF($U37="","Основний",$U37),{"Трафіковий","Основний","Маржинальний","Сезонний","Стратегічний"},0),Settings!$C$78,Settings!$C$80,Settings!$C$82,Settings!$C$84,Settings!$C$86) | AP37: =CHOOSE(MATCH(IF($U37="","Основний",$U37),{"Трафіковий","Основний","Маржинальний","Сезонний","Стратегічний"},0),Settings!$D$78,Settings!$D$80,Settings!$D$82,Settings!$D$84,Settings!$D$86) | AQ37: =CHOOSE(MATCH(IF($U37="","Основний",$U37),{"Трафіковий","Основний","Маржинальний","Сезонний","Стратегічний"},0),Settings!$F$78,Settings!$F$80,Settings!$F$82,Settings!$F$84,Settings!$F$86) | AR37: =CHOOSE(MATCH(IF($U37="","Основний",$U37),{"Трафіковий","Основний","Маржинальний","Сезонний","Стратегічний"},0),Settings!$G$78,Settings!$G$80,Settings!$G$82,Settings!$G$84,Settings!$G$86) | AS37: =CHOOSE(MATCH(IF($U37="","Основний",$U37),{"Трафіковий","Основний","Маржинальний","Сезонний","Стратегічний"},0),Settings!$H$78,Settings!$H$80,Settings!$H$82,Settings!$H$84,Settings!$H$86) | AT37: =CHOOSE(MATCH(IF($U37="","Основний",$U37),{"Трафіковий","Основний","Маржинальний","Сезонний","Стратегічний"},0),Settings!$I$78,Settings!$I$80,Settings!$I$82,Settings!$I$84,Settings!$I$86) | AV37: 1.35
B38: P4705 | C38: FLASHL.COB LED 3W 3×AAA 12PCS | D38: Ліхтарі | E38: PC | F38: 2.517 | G38: 8513100000 | H38: 1.4 | I38: =IFERROR(F38*Settings!$B$2*H38*IF(AND(ISNUMBER(E38),E38>1),E38,1),"") | J38: =Settings!$B$66 | K38: =IFERROR(IF(T38="","",(T38*(1-AN38)*(1-Settings!$B$17)-I38)/(T38*(1-AN38)*(1-Settings!$B$17))),"") | L38: =IFERROR(IF(T38="","",(T38*(1-AO38)*(1-Settings!$C$17)-I38)/(T38*(1-AO38)*(1-Settings!$C$17))),"") | M38: =IFERROR(IF(T38="","",(T38*(1-AP38)*(1-Settings!$D$17)-I38)/(T38*(1-AP38)*(1-Settings!$D$17))),"") | N38: =IFERROR(IF(T38="","",(T38*(1-AQ38)*(1-Settings!$F$17)-I38)/(T38*(1-AQ38)*(1-Settings!$F$17))),"") | O38: =IFERROR(IF(T38="","",(T38*(1-AR38)*(1-Settings!$G$17)-I38)/(T38*(1-AR38)*(1-Settings!$G$17))),"") | P38: =IFERROR(IF(T38="","",(T38*(1-AS38)*(1-Settings!$H$17)-I38)/(T38*(1-AS38)*(1-Settings!$H$17))),"") | Q38: =IFERROR(IF(T38="","",(T38*(1-AT38)*(1-Settings!$I$68)*(1-Settings!$I$17)-I38)/(T38*(1-AT38)*(1-Settings!$I$68)*(1-Settings!$I$17))),"") | R38: =IFERROR(IF(OR(I38="",Z38>=1,Settings!$B$17>=1,AN38>=1),"",IF(MOD(ROUND(I38/(1-Z38)/(1-Settings!$B$17)/(1-AN38),0),10)=0,ROUND(I38/(1-Z38)/(1-Settings!$B$17)/(1-AN38),0)-1,IF(MOD(ROUND(I38/(1-Z38)/(1-Settings!$B$17)/(1-AN38),0),10)<=5,FLOOR(ROUND(I38/(1-Z38)/(1-Settings!$B$17)/(1-AN38),0),10)+6,FLOOR(ROUND(I38/(1-Z38)/(1-Settings!$B$17)/(1-AN38),0),10)+9))),"") | T38: =IF(S38<>"", IF(MOD(S38,10)=0,S38-1,IF(MOD(S38,10)<=5,FLOOR(S38,10)+6,FLOOR(S38,10)+9)), R38) | U38: Основний | X38: =IFERROR(IF(OR(V38="",W38="",T38=""),"", IF(T38>W38,"Дорогий",IF(T38<V38,"Дешевий","У ринку"))),"") | Z38: =CHOOSE(MATCH(IF($U38="","Основний",$U38),{"Трафіковий","Основний","Маржинальний","Сезонний","Стратегічний"},0),0.16,0.19,0.24,0.23,0.28) | AA38: =CHOOSE(MATCH(IF($U38="","Основний",$U38),{"Трафіковий","Основний","Маржинальний","Сезонний","Стратегічний"},0),0.18,0.21,0.26,0.25,0.3) | AB38: =CHOOSE(MATCH(IF($U38="","Основний",$U38),{"Трафіковий","Основний","Маржинальний","Сезонний","Стратегічний"},0),0.19,0.22,0.28,0.26,0.32) | AC38: =CHOOSE(MATCH(IF($U38="","Основний",$U38),{"Трафіковий","Основний","Маржинальний","Сезонний","Стратегічний"},0),0.17,0.2,0.25,0.24,0.28) | AD38: =CHOOSE(MATCH(IF($U38="","Основний",$U38),{"Трафіковий","Основний","Маржинальний","Сезонний","Стратегічний"},0),0.18,0.21,0.26,0.25,0.3) | AE38: =CHOOSE(MATCH(IF($U38="","Основний",$U38),{"Трафіковий","Основний","Маржинальний","Сезонний","Стратегічний"},0),0.18,0.2,0.28,0.27,0.32) | AF38: =CHOOSE(MATCH(IF($U38="","Основний",$U38),{"Трафіковий","Основний","Маржинальний","Сезонний","Стратегічний"},0),0.15,0.175,0.22,0.21,0.25) | AG38: =CHOOSE(MATCH(IF($U38="","Основний",$U38),{"Трафіковий","Основний","Маржинальний","Сезонний","Стратегічний"},0),0.13,0.16,0.21,0.2,0.25) | AH38: =CHOOSE(MATCH(IF($U38="","Основний",$U38),{"Трафіковий","Основний","Маржинальний","Сезонний","Стратегічний"},0),0.15,0.18,0.23,0.22,0.27) | AI38: =CHOOSE(MATCH(IF($U38="","Основний",$U38),{"Трафіковий","Основний","Маржинальний","Сезонний","Стратегічний"},0),0.16,0.19,0.25,0.23,0.29) | AJ38: =CHOOSE(MATCH(IF($U38="","Основний",$U38),{"Трафіковий","Основний","Маржинальний","Сезонний","Стратегічний"},0),0.14,0.17,0.22,0.21,0.25) | AK38: =CHOOSE(MATCH(IF($U38="","Основний",$U38),{"Трафіковий","Основний","Маржинальний","Сезонний","Стратегічний"},0),0.15,0.18,0.23,0.22,0.27) | AL38: =CHOOSE(MATCH(IF($U38="","Основний",$U38),{"Трафіковий","Основний","Маржинальний","Сезонний","Стратегічний"},0),0.15,0.17,0.25,0.24,0.29) | AM38: =CHOOSE(MATCH(IF($U38="","Основний",$U38),{"Трафіковий","Основний","Маржинальний","Сезонний","Стратегічний"},0),0.12,0.145,0.19,0.18,0.22) | AN38: =CHOOSE(MATCH(IF($U38="","Основний",$U38),{"Трафіковий","Основний","Маржинальний","Сезонний","Стратегічний"},0),Settings!$B$78,Settings!$B$80,Settings!$B$82,Settings!$B$84,Settings!$B$86) | AO38: =CHOOSE(MATCH(IF($U38="","Основний",$U38),{"Трафіковий","Основний","Маржинальний","Сезонний","Стратегічний"},0),Settings!$C$78,Settings!$C$80,Settings!$C$82,Settings!$C$84,Settings!$C$86) | AP38: =CHOOSE(MATCH(IF($U38="","Основний",$U38),{"Трафіковий","Основний","Маржинальний","Сезонний","Стратегічний"},0),Settings!$D$78,Settings!$D$80,Settings!$D$82,Settings!$D$84,Settings!$D$86) | AQ38: =CHOOSE(MATCH(IF($U38="","Основний",$U38),{"Трафіковий","Основний","Маржинальний","Сезонний","Стратегічний"},0),Settings!$F$78,Settings!$F$80,Settings!$F$82,Settings!$F$84,Settings!$F$86) | AR38: =CHOOSE(MATCH(IF($U38="","Основний",$U38),{"Трафіковий","Основний","Маржинальний","Сезонний","Стратегічний"},0),Settings!$G$78,Settings!$G$80,Settings!$G$82,Settings!$G$84,Settings!$G$86) | AS38: =CHOOSE(MATCH(IF($U38="","Основний",$U38),{"Трафіковий","Основний","Маржинальний","Сезонний","Стратегічний"},0),Settings!$H$78,Settings!$H$80,Settings!$H$82,Settings!$H$84,Settings!$H$86) | AT38: =CHOOSE(MATCH(IF($U38="","Основний",$U38),{"Трафіковий","Основний","Маржинальний","Сезонний","Стратегічний"},0),Settings!$I$78,Settings!$I$80,Settings!$I$82,Settings!$I$84,Settings!$I$86) | AV38: 1.35
B39: P3894 | C39: LED TORCH 3W COB 3×AAA | D39: Ліхтарі | E39: PC | F39: 1.554 | G39: 8513100000 | H39: 1.4 | I39: =IFERROR(F39*Settings!$B$2*H39*IF(AND(ISNUMBER(E39),E39>1),E39,1),"") | J39: =Settings!$B$66 | K39: =IFERROR(IF(T39="","",(T39*(1-AN39)*(1-Settings!$B$17)-I39)/(T39*(1-AN39)*(1-Settings!$B$17))),"") | L39: =IFERROR(IF(T39="","",(T39*(1-AO39)*(1-Settings!$C$17)-I39)/(T39*(1-AO39)*(1-Settings!$C$17))),"") | M39: =IFERROR(IF(T39="","",(T39*(1-AP39)*(1-Settings!$D$17)-I39)/(T39*(1-AP39)*(1-Settings!$D$17))),"") | N39: =IFERROR(IF(T39="","",(T39*(1-AQ39)*(1-Settings!$F$17)-I39)/(T39*(1-AQ39)*(1-Settings!$F$17))),"") | O39: =IFERROR(IF(T39="","",(T39*(1-AR39)*(1-Settings!$G$17)-I39)/(T39*(1-AR39)*(1-Settings!$G$17))),"") | P39: =IFERROR(IF(T39="","",(T39*(1-AS39)*(1-Settings!$H$17)-I39)/(T39*(1-AS39)*(1-Settings!$H$17))),"") | Q39: =IFERROR(IF(T39="","",(T39*(1-AT39)*(1-Settings!$I$68)*(1-Settings!$I$17)-I39)/(T39*(1-AT39)*(1-Settings!$I$68)*(1-Settings!$I$17))),"") | R39: =IFERROR(IF(OR(I39="",Z39>=1,Settings!$B$17>=1,AN39>=1),"",IF(MOD(ROUND(I39/(1-Z39)/(1-Settings!$B$17)/(1-AN39),0),10)=0,ROUND(I39/(1-Z39)/(1-Settings!$B$17)/(1-AN39),0)-1,IF(MOD(ROUND(I39/(1-Z39)/(1-Settings!$B$17)/(1-AN39),0),10)<=5,FLOOR(ROUND(I39/(1-Z39)/(1-Settings!$B$17)/(1-AN39),0),10)+6,FLOOR(ROUND(I39/(1-Z39)/(1-Settings!$B$17)/(1-AN39),0),10)+9))),"") | T39: =IF(S39<>"", IF(MOD(S39,10)=0,S39-1,IF(MOD(S39,10)<=5,FLOOR(S39,10)+6,FLOOR(S39,10)+9)), R39) | U39: Основний | X39: =IFERROR(IF(OR(V39="",W39="",T39=""),"", IF(T39>W39,"Дорогий",IF(T39<V39,"Дешевий","У ринку"))),"") | Z39: =CHOOSE(MATCH(IF($U39="","Основний",$U39),{"Трафіковий","Основний","Маржинальний","Сезонний","Стратегічний"},0),0.16,0.19,0.24,0.23,0.28) | AA39: =CHOOSE(MATCH(IF($U39="","Основний",$U39),{"Трафіковий","Основний","Маржинальний","Сезонний","Стратегічний"},0),0.18,0.21,0.26,0.25,0.3) | AB39: =CHOOSE(MATCH(IF($U39="","Основний",$U39),{"Трафіковий","Основний","Маржинальний","Сезонний","Стратегічний"},0),0.19,0.22,0.28,0.26,0.32) | AC39: =CHOOSE(MATCH(IF($U39="","Основний",$U39),{"Трафіковий","Основний","Маржинальний","Сезонний","Стратегічний"},0),0.17,0.2,0.25,0.24,0.28) | AD39: =CHOOSE(MATCH(IF($U39="","Основний",$U39),{"Трафіковий","Основний","Маржинальний","Сезонний","Стратегічний"},0),0.18,0.21,0.26,0.25,0.3) | AE39: =CHOOSE(MATCH(IF($U39="","Основний",$U39),{"Трафіковий","Основний","Маржинальний","Сезонний","Стратегічний"},0),0.18,0.2,0.28,0.27,0.32) | AF39: =CHOOSE(MATCH(IF($U39="","Основний",$U39),{"Трафіковий","Основний","Маржинальний","Сезонний","Стратегічний"},0),0.15,0.175,0.22,0.21,0.25) | AG39: =CHOOSE(MATCH(IF($U39="","Основний",$U39),{"Трафіковий","Основний","Маржинальний","Сезонний","Стратегічний"},0),0.13,0.16,0.21,0.2,0.25) | AH39: =CHOOSE(MATCH(IF($U39="","Основний",$U39),{"Трафіковий","Основний","Маржинальний","Сезонний","Стратегічний"},0),0.15,0.18,0.23,0.22,0.27) | AI39: =CHOOSE(MATCH(IF($U39="","Основний",$U39),{"Трафіковий","Основний","Маржинальний","Сезонний","Стратегічний"},0),0.16,0.19,0.25,0.23,0.29) | AJ39: =CHOOSE(MATCH(IF($U39="","Основний",$U39),{"Трафіковий","Основний","Маржинальний","Сезонний","Стратегічний"},0),0.14,0.17,0.22,0.21,0.25) | AK39: =CHOOSE(MATCH(IF($U39="","Основний",$U39),{"Трафіковий","Основний","Маржинальний","Сезонний","Стратегічний"},0),0.15,0.18,0.23,0.22,0.27) | AL39: =CHOOSE(MATCH(IF($U39="","Основний",$U39),{"Трафіковий","Основний","Маржинальний","Сезонний","Стратегічний"},0),0.15,0.17,0.25,0.24,0.29) | AM39: =CHOOSE(MATCH(IF($U39="","Основний",$U39),{"Трафіковий","Основний","Маржинальний","Сезонний","Стратегічний"},0),0.12,0.145,0.19,0.18,0.22) | AN39: =CHOOSE(MATCH(IF($U39="","Основний",$U39),{"Трафіковий","Основний","Маржинальний","Сезонний","Стратегічний"},0),Settings!$B$78,Settings!$B$80,Settings!$B$82,Settings!$B$84,Settings!$B$86) | AO39: =CHOOSE(MATCH(IF($U39="","Основний",$U39),{"Трафіковий","Основний","Маржинальний","Сезонний","Стратегічний"},0),Settings!$C$78,Settings!$C$80,Settings!$C$82,Settings!$C$84,Settings!$C$86) | AP39: =CHOOSE(MATCH(IF($U39="","Основний",$U39),{"Трафіковий","Основний","Маржинальний","Сезонний","Стратегічний"},0),Settings!$D$78,Settings!$D$80,Settings!$D$82,Settings!$D$84,Settings!$D$86) | AQ39: =CHOOSE(MATCH(IF($U39="","Основний",$U39),{"Трафіковий","Основний","Маржинальний","Сезонний","Стратегічний"},0),Settings!$F$78,Settings!$F$80,Settings!$F$82,Settings!$F$84,Settings!$F$86) | AR39: =CHOOSE(MATCH(IF($U39="","Основний",$U39),{"Трафіковий","Основний","Маржинальний","Сезонний","Стратегічний"},0),Settings!$G$78,Settings!$G$80,Settings!$G$82,Settings!$G$84,Settings!$G$86) | AS39: =CHOOSE(MATCH(IF($U39="","Основний",$U39),{"Трафіковий","Основний","Маржинальний","Сезонний","Стратегічний"},0),Settings!$H$78,Settings!$H$80,Settings!$H$82,Settings!$H$84,Settings!$H$86) | AT39: =CHOOSE(MATCH(IF($U39="","Основний",$U39),{"Трафіковий","Основний","Маржинальний","Сезонний","Стратегічний"},0),Settings!$I$78,Settings!$I$80,Settings!$I$82,Settings!$I$84,Settings!$I$86) | AV39: 1.35
B40: P3848A | C40: LED TORCH 9 LED 3×AAA 24PCS | D40: Ліхтарі | E40: PC | F40: 1.927 | G40: 8513100000 | H40: 1.4 | I40: =IFERROR(F40*Settings!$B$2*H40*IF(AND(ISNUMBER(E40),E40>1),E40,1),"") | J40: =Settings!$B$66 | K40: =IFERROR(IF(T40="","",(T40*(1-AN40)*(1-Settings!$B$17)-I40)/(T40*(1-AN40)*(1-Settings!$B$17))),"") | L40: =IFERROR(IF(T40="","",(T40*(1-AO40)*(1-Settings!$C$17)-I40)/(T40*(1-AO40)*(1-Settings!$C$17))),"") | M40: =IFERROR(IF(T40="","",(T40*(1-AP40)*(1-Settings!$D$17)-I40)/(T40*(1-AP40)*(1-Settings!$D$17))),"") | N40: =IFERROR(IF(T40="","",(T40*(1-AQ40)*(1-Settings!$F$17)-I40)/(T40*(1-AQ40)*(1-Settings!$F$17))),"") | O40: =IFERROR(IF(T40="","",(T40*(1-AR40)*(1-Settings!$G$17)-I40)/(T40*(1-AR40)*(1-Settings!$G$17))),"") | P40: =IFERROR(IF(T40="","",(T40*(1-AS40)*(1-Settings!$H$17)-I40)/(T40*(1-AS40)*(1-Settings!$H$17))),"") | Q40: =IFERROR(IF(T40="","",(T40*(1-AT40)*(1-Settings!$I$68)*(1-Settings!$I$17)-I40)/(T40*(1-AT40)*(1-Settings!$I$68)*(1-Settings!$I$17))),"") | R40: =IFERROR(IF(OR(I40="",Z40>=1,Settings!$B$17>=1,AN40>=1),"",IF(MOD(ROUND(I40/(1-Z40)/(1-Settings!$B$17)/(1-AN40),0),10)=0,ROUND(I40/(1-Z40)/(1-Settings!$B$17)/(1-AN40),0)-1,IF(MOD(ROUND(I40/(1-Z40)/(1-Settings!$B$17)/(1-AN40),0),10)<=5,FLOOR(ROUND(I40/(1-Z40)/(1-Settings!$B$17)/(1-AN40),0),10)+6,FLOOR(ROUND(I40/(1-Z40)/(1-Settings!$B$17)/(1-AN40),0),10)+9))),"") | T40: =IF(S40<>"", IF(MOD(S40,10)=0,S40-1,IF(MOD(S40,10)<=5,FLOOR(S40,10)+6,FLOOR(S40,10)+9)), R40) | U40: Основний | X40: =IFERROR(IF(OR(V40="",W40="",T40=""),"", IF(T40>W40,"Дорогий",IF(T40<V40,"Дешевий","У ринку"))),"") | Z40: =CHOOSE(MATCH(IF($U40="","Основний",$U40),{"Трафіковий","Основний","Маржинальний","Сезонний","Стратегічний"},0),0.16,0.19,0.24,0.23,0.28) | AA40: =CHOOSE(MATCH(IF($U40="","Основний",$U40),{"Трафіковий","Основний","Маржинальний","Сезонний","Стратегічний"},0),0.18,0.21,0.26,0.25,0.3) | AB40: =CHOOSE(MATCH(IF($U40="","Основний",$U40),{"Трафіковий","Основний","Маржинальний","Сезонний","Стратегічний"},0),0.19,0.22,0.28,0.26,0.32) | AC40: =CHOOSE(MATCH(IF($U40="","Основний",$U40),{"Трафіковий","Основний","Маржинальний","Сезонний","Стратегічний"},0),0.17,0.2,0.25,0.24,0.28) | AD40: =CHOOSE(MATCH(IF($U40="","Основний",$U40),{"Трафіковий","Основний","Маржинальний","Сезонний","Стратегічний"},0),0.18,0.21,0.26,0.25,0.3) | AE40: =CHOOSE(MATCH(IF($U40="","Основний",$U40),{"Трафіковий","Основний","Маржинальний","Сезонний","Стратегічний"},0),0.18,0.2,0.28,0.27,0.32) | AF40: =CHOOSE(MATCH(IF($U40="","Основний",$U40),{"Трафіковий","Основний","Маржинальний","Сезонний","Стратегічний"},0),0.15,0.175,0.22,0.21,0.25) | AG40: =CHOOSE(MATCH(IF($U40="","Основний",$U40),{"Трафіковий","Основний","Маржинальний","Сезонний","Стратегічний"},0),0.13,0.16,0.21,0.2,0.25) | AH40: =CHOOSE(MATCH(IF($U40="","Основний",$U40),{"Трафіковий","Основний","Маржинальний","Сезонний","Стратегічний"},0),0.15,0.18,0.23,0.22,0.27) | AI40: =CHOOSE(MATCH(IF($U40="","Основний",$U40),{"Трафіковий","Основний","Маржинальний","Сезонний","Стратегічний"},0),0.16,0.19,0.25,0.23,0.29) | AJ40: =CHOOSE(MATCH(IF($U40="","Основний",$U40),{"Трафіковий","Основний","Маржинальний","Сезонний","Стратегічний"},0),0.14,0.17,0.22,0.21,0.25) | AK40: =CHOOSE(MATCH(IF($U40="","Основний",$U40),{"Трафіковий","Основний","Маржинальний","Сезонний","Стратегічний"},0),0.15,0.18,0.23,0.22,0.27) | AL40: =CHOOSE(MATCH(IF($U40="","Основний",$U40),{"Трафіковий","Основний","Маржинальний","Сезонний","Стратегічний"},0),0.15,0.17,0.25,0.24,0.29) | AM40: =CHOOSE(MATCH(IF($U40="","Основний",$U40),{"Трафіковий","Основний","Маржинальний","Сезонний","Стратегічний"},0),0.12,0.145,0.19,0.18,0.22) | AN40: =CHOOSE(MATCH(IF($U40="","Основний",$U40),{"Трафіковий","Основний","Маржинальний","Сезонний","Стратегічний"},0),Settings!$B$78,Settings!$B$80,Settings!$B$82,Settings!$B$84,Settings!$B$86) | AO40: =CHOOSE(MATCH(IF($U40="","Основний",$U40),{"Трафіковий","Основний","Маржинальний","Сезонний","Стратегічний"},0),Settings!$C$78,Settings!$C$80,Settings!$C$82,Settings!$C$84,Settings!$C$86) | AP40: =CHOOSE(MATCH(IF($U40="","Основний",$U40),{"Трафіковий","Основний","Маржинальний","Сезонний","Стратегічний"},0),Settings!$D$78,Settings!$D$80,Settings!$D$82,Settings!$D$84,Settings!$D$86) | AQ40: =CHOOSE(MATCH(IF($U40="","Основний",$U40),{"Трафіковий","Основний","Маржинальний","Сезонний","Стратегічний"},0),Settings!$F$78,Settings!$F$80,Settings!$F$82,Settings!$F$84,Settings!$F$86) | AR40: =CHOOSE(MATCH(IF($U40="","Основний",$U40),{"Трафіковий","Основний","Маржинальний","Сезонний","Стратегічний"},0),Settings!$G$78,Settings!$G$80,Settings!$G$82,Settings!$G$84,Settings!$G$86) | AS40: =CHOOSE(MATCH(IF($U40="","Основний",$U40),{"Трафіковий","Основний","Маржинальний","Сезонний","Стратегічний"},0),Settings!$H$78,Settings!$H$80,Settings!$H$82,Settings!$H$84,Settings!$H$86) | AT40: =CHOOSE(MATCH(IF($U40="","Основний",$U40),{"Трафіковий","Основний","Маржинальний","Сезонний","Стратегічний"},0),Settings!$I$78,Settings!$I$80,Settings!$I$82,Settings!$I$84,Settings!$I$86) | AV40: 1.35
